Workbook

Sheet Angelica
A1: Angelica Lopez
B5: Week of 26/02/2018 | C5: Start | D5: Finish | E5: Hrs worked | F5: Total Pay | G5: Description
B6: Monday
B7: Tuesday
B8: Wednesday
B9: Thursday | C9: 0.54166667 | D9: 0.625 | E9: 2
B10: Friday | C10: 0.54166667 | D10: 0.625 | E10: 2
B11: Saturday
B12: Sunday
B16: Week of 05/03/2018 | C16: Start | D16: Finish | E16: Hrs worked | F16: Total Pay | G16: Description
B17: Monday
B18: Tuesday
B19: Wednesday | E19: 3
B20: Thursday | C20: 0.39583333 | D20: 0.45833333 | E20: 1.5
C21: 0.54166667 | D21: 0.625 | E21: 2
B22: Friday
B23: Saturday
B24: Sunday
E25: =SUM(E9:E10,E19:E21) -> 10.5
A27: before this point all work was PAID IN VOUCHERS…
B29: ANTHONY's INPUT
B34: Week of 12/03/2018 | C34: Start | D34: Finish | E34: Hrs worked | F34: Hrs Paid | G34: Description | H34: Payment received
A35: 12 | B35: Monday
A36: 13 | B36: Tuesday | C36: 0.375 | D36: 0.5 | E36: 3 | G36: Seaching by courses using different terminology to list the list of statistical courses offered at UC. The whole dataset is complete it
A37: 14 | B37: Wednesday
A38: 15 | B38: Thursday | C38: 0.54166667 | D38: 0.625 | E38: 2 | G38: Regular Drop in
A39: 16 | B39: Friday | C39: 0.375 | D39: 0.5 | E39: 3 | G39: organized files. In dropbox. Reading and organized the whole files and build a dataset of files.
A40: 17 | B40: Saturday
A41: 18 | B41: Sunday
B42: TOTAL | E42: =SUM(E35:E41) -> 8 | F42: Hours submitted | G42: Hours owing
A43: Tuesday 21 March | B43: Payday | E43: =SUM(E35:E39) -> 8 | F43: =SUM(1*Angelica_hist!G3) -> 5 | G43: =SUM(E43-F43) -> 3
B46: Week of 19/03/2018 | C46: Start | D46: Finish | E46: Hrs worked | F46: Hrs Paid | G46: Description | H46: Payment received
A47: 19 | B47: Monday
A48: 20 | B48: Tuesday
A49: 21 | B49: Wednesday
A50: 22 | B50: Thursday | C50: 0.54166667 | D50: 0.625 | E50: 2 | G50: Regular Drop in
A51: 23 | B51: Friday | C51: 0.375 | D51: 0.45833333 | E51: 2 | G51: Statistical Network project process and possible tasks. In dropbox.
A52: 24 | B52: Saturday
A53: 25 | B53: Sunday
B54: TOTAL | E54: =SUM(E46:E53) -> 4
B56: Week of 26/03/2018 | C56: Start | D56: Finish | E56: Hrs worked | F56: Total Pay | G56: Description
A57: 26 | B57: Monday | C57: 0.375 | D57: 0.41666667 | E57: 1 | G57: meeting with Anthony check face
A58: 27 | B58: Tuesday
A59: 28 | B59: Wednesday 28 march
A60: 29 | B60: Thursday | C60: 0.54166667 | D60: 0.625 | E60: 2 | G60: Regular Drop in
A61: 30 | B61: Friday | C61: 0.375 | D61: 0.45833333 | E61: 2 | G61: Buiding document for stats process.
A62: 31 | B62: Saturday
A63: 1 | B63: Sunday
B64: TOTAL | E64: =SUM(E57:E63) -> 5 | F64: Hours submitted | G64: Hours owing
A65: Tuesday 4th April | B65: Payday | E65: =SUM(E64,E54) -> 9 | F65: =SUM(1*Angelica_hist!G9) -> 5 | G65: =SUM(E65+G43)-F65 -> 7
B67: Week of 02/04/2018 | C67: Start | D67: Finish | E67: Hrs worked | F67: Total Pay | G67: Description | H67: Where did this come from? I Have added this in as hours but not sure if this was a mistake or actual hours
A68: 2 | B68: Monday
A69: 3 | B69: Tuesday 3 April
A70: 4 | B70: Wednesday
A71: 5 | B71: Thursday | C71: 0.54166667 | D71: 0.125 | E71: 2 | G71: Drop in session
A72: 6 | C72: 0.625 | D72: 0.70833333 | E72: 2 | G72: Writing Process document
A73: 7 | B73: Friday
A74: 8 | B74: Saturday
A75: 9 | B75: Sunday
B76: TOTAL | E76: =SUM(E68:E75) -> 4
B80: Week of 02/04/2018 | C80: Start | D80: Finish | E80: Hrs worked | F80: Total Pay | G80: Description
B81: Monday | G81: Easter monday
B82: Tuesday
B83: Wednesday
B84: Thursday | C84: 0.5 | D84: 0.54166667 | E84: 1 | G84: meeting Anthony, set up email and tasks
C85: 0.54166667 | D85: 0.125 | E85: 2 | G85: Drop in session
C86: 0.75 | D86: 0.83333333 | E86: 2 | G86: Coding Anna meta analysis
B87: Friday | C87: 0.70833333 | D87: 0.75 | E87: 1 | G87: Emails and fixing plots for Anna
B88: Saturday | C88: 0.41666667 | D88: 0.47916667 | E88: 1.5 | G88: Emails, follow up (Abel Zhou, conversation with Anna)
B89: Sunday
B90: TOTAL | E90: =SUM(E81:E89) -> 7.5 | G90: minus5previous pay
B93: Week of 09/04/2018 | C93: Start | D93: Finish | E93: Hrs worked | F93: Total Pay | G93: Description
B94: Monday | C94: 0.45833333 | D94: 0.54166667 | E94: 2 | G94: Individual consultation Anna
C95: 0.58333333 | D95: 15:30 PM | E95: 1.5 | G95: Admin, answering and writing emails (Sam Kosari and Sucholana)
B96: Tuesday 17payday
B97: Wednesday
B98: Thursday | C98: 0.041666667 | D98: 0.125 | E98: 2 | G98: Drop in session
B99: Friday | C99: 0.125 | D99: 0.16666667 | E99: 1 | G99: Meeting Anthony
B100: Saturday | F100: 3.5
B101: Sunday
B102: TOTAL | E102: =SUM(E94:E101) -> 6.5
A103: MISSED | B103: TOTAL | E103: =SUM(E102,E90,E76) -> 18 | F103: Hours submitted | G103: hours owing
B104: Payday | E104: MISSED | F104: n/a | G104: =SUM(E103+G65) -> 25 | H104: This includes missed hours from this pay
B106: Week of 16/04/2018 | C106: Start | D106: Finish | E106: Hrs worked | F106: Total Pay | G106: Description
B107: Monday | C107: 11.30 am | D107: 0.5 | E107: 0.5 | G107: Response emails, references to Anna and ackwoledgement
B108: Tuesday
B109: Wednesday
B110: Thursday | C110: 0.5 | D110: 0.041666667 | E110: 1 | G110: Meeting Anthony
C111: 0.041666667 | D111: 0.125 | E111: 2 | G111: Drop in session
C112: 0.125 | D112: 0.14583333 | E112: 0.5 | G112: Meeting with Kym
B113: Friday
B117: Saturday
B118: Sunday | C118: 0.54166667 | D118: 0.64583333 | E118: 2.5 | G118: First report Kym, see the email
B119: TOTAL | E119: =SUM(E107:E118) -> 6.5
A120: END CONTRACT START A NEW ONE
B122: Week of 23/04/2018 | C122: Start | D122: Finish | E122: Hrs worked | F122: Total Pay | G122: Description
A123: 23 | B123: Monday | C123: 11.30 am | D123: 0.5 | E123: 0.5 | G123: Update dataset of drop-in sessions and emails.
C124: 4:30pm | D124: 0.70833333 | E124: 0.5 | G124: Response to Michelle Montgomery about her Logistic regression problem
A125: 24 | B125: Tuesday | C125: 0.625 | D125: 0.70833333 | E125: 2 | G125: Second response to kym, analysis of survey II part
A126: 25 | B126: Wednesday | G126: ANZAC DAY
...

Sheet Angelica_hist
A1: Period End Date | B1: Surname | C1: Preferred Name | D1: GL Record Type Description | E1: Account Number Prefix | F1: Paycode | G1: Salary Hours | H1: Amt$
A2: 43180
A3: 43180 | B3: LOPEZ | C3: Angelica | D3: Earnings | E3: 50002 | F3: Rate P - Other | G3: 5 | H3: 226.4
A4: 43180 | B4: LOPEZ | C4: Angelica | D4: Oncosts | E4: 50018 | F4: Oncosts | H4: 15.51
A5: 43180 | B5: LOPEZ | C5: Angelica | D5: Oncosts | E5: 50020 | F5: Oncosts | H5: 1.47
A6: 43180 | B6: LOPEZ | C6: Angelica | D6: Oncosts | E6: 50021 | F6: Oncosts | H6: 2.83
A7: 43180 | B7: LOPEZ | C7: Angelica | D7: Subsidies | E7: 50016 | F7: Super | H7: 21.51
A8: 43194
A9: 43194 | B9: LOPEZ | C9: Angelica | D9: Earnings | E9: 50002 | F9: Rate P - Other | G9: 5 | H9: 226.4
A10: 43194 | B10: LOPEZ | C10: Angelica | D10: Oncosts | E10: 50018 | F10: Oncosts | H10: 15.51
A11: 43194 | B11: LOPEZ | C11: Angelica | D11: Oncosts | E11: 50021 | F11: Oncosts | H11: 2.83
A12: 43208 | B12: LOPEZ | C12: Angelica | D12: Oncosts | E12: 50020 | F12: Oncosts | H12: 1.47
A13: 43208 | B13: LOPEZ | C13: Angelica | D13: Subsidies | E13: 50016 | F13: Super | H13: 21.51
A14: 43222
A15: 43222 | B15: LOPEZ | C15: Angelica | D15: Earnings | E15: 50002 | F15: Rate P - Other | G15: 10 | H15: 452.78
A16: 43222 | B16: LOPEZ | C16: Angelica | D16: Oncosts | E16: 50018 | F16: Oncosts | H16: 31.02
A17: 43222 | B17: LOPEZ | C17: Angelica | D17: Oncosts | E17: 50020 | F17: Oncosts | H17: 2.95
A18: 43222 | B18: LOPEZ | C18: Angelica | D18: Oncosts | E18: 50021 | F18: Oncosts | H18: 5.66
A19: 43222 | B19: LOPEZ | C19: Angelica | D19: Subsidies | E19: 50016 | F19: Super | H19: 43.01
A20: 43236
A21: 43236 | B21: LOPEZ | C21: Angelica | D21: Earnings | E21: 50002 | F21: Rate O - Marking | G21: 22.5 | H21: 1215.87
A22: 43236 | B22: LOPEZ | C22: Angelica | D22: Oncosts | E22: 50018 | F22: Oncosts | H22: 83.29
A23: 43236 | B23: LOPEZ | C23: Angelica | D23: Oncosts | E23: 50020 | F23: Oncosts | H23: 7.91
A24: 43236 | B24: LOPEZ | C24: Angelica | D24: Oncosts | E24: 50021 | F24: Oncosts | H24: 15.19
A25: 43236 | B25: LOPEZ | C25: Angelica | D25: Subsidies | E25: 50016 | F25: Super | H25: 115.51
A26: 43250
A27: 43250 | B27: LOPEZ | C27: Angelica | D27: Earnings | E27: 50002 | F27: Rate O - Marking | G27: -22.5 | H27: -1215.87
A28: 43250 | B28: LOPEZ | C28: Angelica | D28: Earnings | E28: 50002 | F28: Rate P - Other | G28: 52.5 | H28: 2377.15
A29: 43250 | B29: LOPEZ | C29: Angelica | D29: Earnings | E29: 50002 | F29: Rate Q - Other | G29: 25 | H29: 1350.96
A30: 43250 | B30: LOPEZ | C30: Angelica | D30: Oncosts | E30: 50018 | F30: Oncosts | H30: 172.08
A31: 43250 | B31: LOPEZ | C31: Angelica | D31: Oncosts | E31: 50020 | F31: Oncosts | H31: 17.82
A32: 43250 | B32: LOPEZ | C32: Angelica | D32: Oncosts | E32: 50021 | F32: Oncosts | H32: 31.4
A33: 43250 | B33: LOPEZ | C33: Angelica | D33: Subsidies | E33: 50016 | F33: Super | H33: 260.17
A34: 43264
A35: 43264 | B35: LOPEZ | C35: Angelica | D35: Earnings | E35: 50002 | F35: Rate P - Other | G35: 30 | H35: 1358.37
A36: 43264 | B36: LOPEZ | C36: Angelica | D36: Oncosts | E36: 50018 | F36: Oncosts | H36: 93.04
A37: 43264 | B37: LOPEZ | C37: Angelica | D37: Oncosts | E37: 50020 | F37: Oncosts | H37: 8.84
A38: 43264 | B38: LOPEZ | C38: Angelica | D38: Oncosts | E38: 50021 | F38: Oncosts | H38: 16.98
A39: 43264 | B39: LOPEZ | C39: Angelica | D39: Subsidies | E39: 50016 | F39: Super | H39: 129.05
A40: 43278
A41: 43278 | B41: LOPEZ | C41: Angelica | D41: Earnings | E41: 50002 | F41: Rate P - Other | G41: 30 | H41: 1358.37
A42: 43278 | B42: LOPEZ | C42: Angelica | D42: Oncosts | E42: 50018 | F42: Oncosts | H42: 93.04
A43: 43278 | B43: LOPEZ | C43: Angelica | D43: Oncosts | E43: 50020 | F43: Oncosts | H43: 8.84
A44: 43278 | B44: LOPEZ | C44: Angelica | D44: Oncosts | E44: 50021 | F44: Oncosts | H44: 16.98
A45: 43278 | B45: LOPEZ | C45: Angelica | D45: Subsidies | E45: 50016 | F45: Super | H45: 129.05
A46: 43292
A47: 43292 | B47: LOPEZ | C47: Angelica | D47: Earnings | E47: 50002 | F47: Rate P - Other | G47: 15 | H47: 679.19
A48: 43292 | B48: LOPEZ | C48: Angelica | D48: Earnings | E48: 50002 | F48: Rate Q - Other | G48: 16 | H48: 864.62
A49: 43292 | B49: LOPEZ | C49: Angelica | D49: Oncosts | E49: 50018 | F49: Oncosts | H49: 105.75
A50: 43292 | B50: LOPEZ | C50: Angelica | D50: Oncosts | E50: 50020 | F50: Oncosts | H50: 10.05
A51: 43292 | B51: LOPEZ | C51: Angelica | D51: Oncosts | E51: 50021 | F51: Oncosts | H51: 19.3
A52: 43292 | B52: LOPEZ | C52: Angelica | D52: Subsidies | E52: 50016 | F52: Super | H52: 146.66
A54: TOTAL | G54: =SUM(G47:G52,G41:G45,G35:G39,G27:G33,G21:G25,G15:G19,G9:G13,G3:G7) -> 188.5 | H54: =SUM(H47:H52,H41:H45,H35:H39,H27:H33,H21:H25,H15:H19,H9:H13,H3:H7) -> 10540.47 | I54: =SUM(H54/G54) -> 55.917613
