Workbook

Sheet Finalised_timesheet
A1: Overall proposed timesheet | H1: Stage | I1: Time | J1: Status | K1: Due date
A2: For the next set of Acidemic contracts: Stage three (July 2018 - September 2018) | H2: Stage one | I2: 1st February - 13th May | J2: DONE
H3: Stage two | I3: 14th May - 1 July | J3: DONE
H4: Stage three | I4: 2 July 2018 - 1st September 2018 | J4: CURRENT | K4: 31st July 2018
H5: Stage four | I5: 2nd September 2018 - 31st December 2018 | J5: DRAFT NEEDED | K5: 28th August 2018
A7: The extra two weeks of the contract are included in the finalised timesheets under each advisor
A9: 23-29 July 2018 | B9: WS=W1 | C9: Monday | D9: Tuesday | E9: Wednesday | F9: Thursday | G9: Friday | H9: Saturday | I9: Sunday | J9: Total
B10: Anthony | E10: 4.5 | F10: 5 | G10: 5 | H10: 4 | I10: 5 | J10: =SUM(C10:I10) -> 23.5 | K10: NOTE: Must have timesheet to be pay this by Monday 30th
C11: 9am - 5pm office (3C3)
B12: Margarita | C12: 0 | D12: 0 | E12: RDO | F12: 2 | G12: 0 | J12: =SUM(C12:I12) -> 2
C13: One-on-one | F13: Drop-in session | G13: One-on-one
B14: Angelica | C14: RDO | D14: RDO | E14: RDO | F14: RDO | G14: RDO | I14: 8 | J14: =SUM(C14:I14) -> 8
H15: 5hrs over weekend or evenings with previous researchers
B16: Kyle | C16: RDO | D16: RDO | E16: RDO | F16: 2 | G16: RDO | J16: =SUM(C16:I16) -> 2
F17: Drop-in session
B18: Researcher development
B19: Total | C19: 2 | D19: 4 | E19: 2 | F19: 7 | G19: 4 | J19: =SUM(J10:J18) -> 35.5
A22: 30 July-5 August 2018 | B22: WS=W2 | C22: Monday | D22: Tuesday | E22: Wednesday | F22: Thursday | G22: Friday | H22: Saturday | I22: Sunday | J22: Total
B23: Anthony | C23: 2 | D23: 3 | J23: =SUM(C23:I23) -> 5 | K23: NOTE: Must have timesheet to be pay this by Monday 6th
C24: 9am - 5pm office (3C3)
B25: Margarita | C25: 2 | D25: 0 | E25: RDO | F25: 3 | G25: 2 | J25: =SUM(C25:I25) -> 7
C26: One-on-one | F26: 9am - 4.30pm (30min break) | G26: One-on-one
B27: Angelica | C27: RDO | D27: RDO | E27: RDO | F27: RDO | G27: RDO | I27: 6 | J27: =SUM(C27:I27) -> 6
H28: 5hrs over weekend or evenings with previous researchers
B29: New Staff 1 | F29: 2 | J29: 2
F30: Drop-in session
B31: Kyle | C31: RDO | D31: RDO | E31: RDO | F31: 2 | G31: RDO | J31: =SUM(C31:I31) -> 2
F32: Drop-in session
B33: Researcher development | J33: =SUM(C32:I32) -> 0
B34: Total | C34: 2 | D34: 4 | E34: 2 | F34: 7 | G34: 4 | J34: =SUM(J23:J33) -> 22
A37: 6-12 August 2018 | B37: WS=W3 | C37: Monday | D37: Tuesday | E37: Wednesday | F37: Thursday | G37: Friday | H37: Saturday | I37: Sunday | J37: Total
B38: Anthony | D38: 0.5 | J38: =SUM(C38:I38) -> 0.5 | K38: NOTE: Must have timesheet to be pay this by Monday 13th
C39: 9am - 5pm office (3C3)
B40: Margarita | C40: 2 | D40: 4 | E40: RDO | F40: 7 | G40: 2 | J40: =SUM(C40:I40) -> 15
C41: One-on-one | F41: 9am - 4.30pm (30min break) | G41: One-on-one
B42: New Staff 1 | C42: RDO | D42: RDO | E42: RDO | F42: 2 | G42: RDO | H42: Over weekend or evenings as needed | J42: =SUM(C42:I42) -> 2
F43: Drop-in session
B44: Kyle | C44: RDO | D44: RDO | E44: RDO | F44: 2 | G44: RDO | J44: =SUM(C44:I44) -> 2
F45: Drop-in session
B46: Angelica | I46: 5 | J46: =SUM(H46:I46) -> 5
H47: 5hrs over weekend or evenings with previous researchers
B48: Total | C48: 2 | D48: 4 | E48: 2 | F48: 7 | G48: 4 | J48: =SUM(J38:J47) -> 24.5
A51: 13-19 August 2018 | B51: WS=W4 | C51: Monday | D51: Tuesday | E51: Wednesday | F51: Thursday | G51: Friday | H51: Saturday | I51: Sunday | J51: Total
B52: Anthony | D52: 2 | J52: =SUM(C52:I52) -> 2 | K52: NOTE: Must have timesheet to be pay this by Monday 20th
C53: 9am - 5pm office (3C3)
B54: Margarita | C54: 2 | D54: 4 | E54: RDO | F54: 7 | G54: 2 | J54: =SUM(C54:I54) -> 15
C55: One-on-one | F55: 9am - 4.30pm (30min break) | G55: One-on-one
B56: New Staff 1 | C56: RDO | D56: RDO | E56: RDO | F56: 2 | G56: RDO | H56: Over weekend or evenings as needed | J56: =SUM(C56:I56) -> 2
F57: Drop-in session
B58: Kyle | C58: RDO | D58: RDO | E58: RDO | F58: 2 | G58: RDO | J58: =SUM(C58:I58) -> 2
F59: Drop-in session
B60: `Angelica | C60: Use hours still owing to the statistics network for the rest of the month
B62: Angelica | I62: 5 | J62: =SUM(H62:I62) -> 5
H63: 5hrs over weekend or evenings with previous researchers
B64: Total | C64: 2 | D64: 4 | E64: 2 | F64: 7 | G64: 4 | J64: =SUM(J52:J63) -> 26
A67: 20-26 August 2018 | B67: WS=W4 | C67: Monday | D67: Tuesday | E67: Wednesday | F67: Thursday | G67: Friday | H67: Saturday | I67: Sunday | J67: Total
B68: Anthony | F68: 3 | J68: =SUM(C68:I68) -> 3 | K68: NOTE: Must have timesheet to be pay this by Monday 27th
C69: 9am - 5pm office (3C3)
B70: Margarita | C70: 2 | D70: 4 | E70: RDO | F70: 7 | G70: 2 | J70: =SUM(C70:I70) -> 15
C71: One-on-one | F71: 9am - 4.30pm (30min break) | G71: One-on-one
B72: New Staff 1 | C72: RDO | D72: RDO | E72: RDO | F72: 2 | G72: RDO | H72: Over weekend or evenings as needed | I72: 2 | J72: =SUM(C72:I72) -> 4
F73: Drop-in session
B74: Kyle | C74: RDO | F74: 2 | G74: RDO | J74: =SUM(C74:I74) -> 2
F75: Drop-in session (1:00 - 3:00)
B76: Angelica | C76: Use hours still owing to the statistics network for the rest of the month
B78: Researcher development | J78: =SUM(C77:I77) -> 0
B79: Total | C79: 2 | D79: 4 | E79: 2 | F79: 7 | G79: 4 | J79: =SUM(J68:J78) -> 24
A82: 27 August - 2 September 2018 | B82: WS=W4 | C82: Monday | D82: Tuesday | E82: Wednesday | F82: Thursday | G82: Friday | H82: Saturday | I82: Sunday | J82: Total
B83: Anthony | D83: 3 | J83: =SUM(C83:I83) -> 3 | K83: NOTE: Must have timesheet to be pay this by Monday 3rd
C84: 9am - 5pm office (3C3)
B85: Margarita | C85: 2 | D85: 4 | E85: RDO | F85: 7 | G85: 2 | J85: =SUM(C85:I85) -> 15
C86: One-on-one | F86: 9am - 4.30pm (30min break) | G86: One-on-one
B87: New Staff 1 | C87: RDO | D87: RDO | E87: 5 | F87: 2 | G87: 1 | J87: =SUM(C87:H87) -> 8
E88: One-on-one | F88: Drop-in session | G88: One-on-one | H88: Over weekend or evenings as needed
B89: Angelica | C89: Use hours still owing to the statistics network for the rest of the month
B91: Kyle | C91: RDO | D91: RDO | E91: RDO | F91: 2 | G91: RDO | J91: =SUM(C91:I91) -> 2
F92: Drop-in session (1:00 - 3:00)
B93: Researcher development | J93: =SUM(C93:I93) -> 0
B94: Total | C94: =SUM(F88,C91,C87,C85) -> 2 | D94: =SUM(G88,D91,D87,D85) -> 4 | E94: =SUM(H88,E91,E87,E85) -> 5 | F94: =SUM(I88,F91,F87,F85) -> 11 | G94: =SUM(J88,G91,G87,G85) -> 3 | H94: =SUM(K88,H91,H87,H85) -> 0 | I94: =SUM(#REF!,I91,I87,I85) -> #REF! | J94: =SUM(J83:J93) -> 28
A97: NEW CONTRACT (2nd September - 31st December 2018)

Sheet Final_Anthony
A1: Anthony Davidson
B5: Payday | C5: Hours submitted | D5: Hours owing
A6: Tuesday 24th January | B6: 43124 | C6: =SUM([1]Anthony_hist!G3) -> 12.5 | D6: 73.5
A7: Tuesday 7th Febuary | B7: 43138 | C7: =SUM([1]Anthony_hist!G9) -> 73.5 | D7: =SUM(D6-C7) -> 0
B9: Week of 26/02/2018 | C9: Start | D9: Finish | E9: Hrs worked | F9: Total Pay | G9: General | H9: Details
B10: Monday
B11: Tuesday
B12: Wednesday
B13: Thursday | C13: 0.54166667 | D13: 0.625 | E13: 2 | G13: Drop-in
C14: 0.625 | D14: 0.66666667 | E14: 1 | G14: Jenni
B15: Friday | C15: 0.54166667 | D15: 0.625 | E15: 2 | G15: Ant+ Angelica
B16: Saturday | C16: 0.54166667 | D16: 0.58333333 | E16: 1 | G16: Admin | H16: Emailing network people
B17: Sunday | C17: 0.375 | D17: 0.625 | E17: 6 | G17: Haysem one-on-one. | H17: Regression and research management
B18: TOTAL | E18: =SUM(E10:E17) -> 12 | F18: Hours submitted | G18: Hours owing
A19: Tuesday 7th March | B19: Payday | E19: =SUM(E11,E18) -> 12 | F19: =SUM([1]Anthony_hist!G15) -> 6 | G19: =SUM(E19+D7)-F19 -> 6
B22: Week of 05/03/2018 | C22: Start | D22: Finish | E22: Hrs worked | F22: Total Pay | G22: Description
B23: Monday | C23: 0.41666667 | D23: 0.45833333 | E23: 1 | G23: Admin(emails)
B24: Tuesday | C24: 0.41666667 | D24: 0.45833333 | E24: 1 | G24: Admin(emails)
C25: 0.52083333 | D25: 0.54166667 | E25: 0.5 | G25: Lecture
C26: 0.64583333 | D26: 0.6875 | E26: 1 | G26: Contracts meeting and admin
B27: Wednesday | C27: 0.5625 | D27: 0.66666667 | E27: 3.5 | G27: Network building
C28: 0.72916667 | D28: 0.9375 | E28: 5 | G28: Haysem
C29: 0.97916667 | D29: 0.052083333 | E29: 1.75 | G29: Admin(emails)
B30: Thursday | C30: 0.45833333 | D30: 0.5 | E30: 1 | G30: Admin meeting maths&stats
C31: 0.5 | D31: 0.625 | E31: 3 | G31: Shalini one-on-one
C32: 0.625 | D32: 0.66666667 | E32: 1 | G32: Admin meeting contracts + anna
B33: Friday | E33: =SUM(D33-C33) -> 0
B34: Saturday | E34: =SUM(D34-C34) -> 0
B35: Sunday | E35: =SUM(D35-C35) -> 0
A36: MISSED | B36: TOTAL | E36: =SUM(E23:E35) -> 18.75 | F36: Hours owing
F37: 0 | G37: =SUM(E36,G19) -> 24.75
A38: Before this point all work was under trial but have carryover tooooo
B40: Week of 12/03/2018 | C40: Start | D40: Finish | E40: Hrs worked | F40: Hrs Paid | G40: Description | H40: Notes
A41: 12 | B41: Monday | C41: 0.5 | D41: 0.625 | E41: 2 | G41: Jackson about publication options for network (Public holiday so caught up on this work instead)
A42: 13 | B42: Tuesday | C42: 0.41666667 | D42: 0.54166667 | E42: 3 | G42: Admin
A43: 14 | B43: Wednesday
A44: 15 | B44: Thursday | C44: 0.5 | D44: 0.58333333 | E44: 2 | G44: Admin
A45: 16 | B45: Friday
A46: 17 | B46: Saturday
A47: 18 | B47: Sunday | H47: This includes hours from previous contract that will still be in this contracts hours for now
A48: MISSED | B48: TOTAL | E48: =SUM(E41:E47) -> 7 | F48: Hours submitted | G48: Hours owing
A49: Tuesday 21 March | B49: Payday | E49: =SUM(E41:E47) -> 7 | F49: =SUM([1]Anthony_hist!G19) -> 1 | G49: =SUM(E49 + G37) -> 31.75
B52: Week of 19/03/2018 | C52: Start | D52: Finish | E52: Hrs worked | F52: Hrs Paid | G52: Description | H52: Payment received
A53: 19 | B53: Monday | C53: 0.5 | D53: 0.70833333 | E53: 5 | G53: Admin, emails and document development
A54: 20 | B54: Tuesday
A55: 21 | B55: Wednesday | C55: 1:00PM | D55: 3:00PM | E55: 2 | G55: Admin dramas with Outlook
A56: 22 | B56: Thursday | C56: Sick
A57: 23 | B57: Friday | C57: 0.75 | D57: 0.91666667 | E57: 4 | G57: kasia stats
A58: 24 | B58: Saturday
A59: 25 | B59: Sunday | C59: 0.54166667 | D59: 0.70833333 | E59: 4 | G59: kasia stats
B60: TOTAL | E60: =SUM(E53:E59) -> 15
B62: Week of 26/03/2018 | C62: Start | D62: Finish | E62: Hrs worked | F62: Total Pay | G62: Description
A63: 26 | B63: Monday | C63: 0.375 | D63: 0.41666667 | E63: 1 | G63: meeting with Angelica check face
C64: 0.41666667 | D64: 0.5 | E64: 2 | G64: maths&stats meeting
A65: 27 | B65: Tuesday | C65: 0.66666667 | D65: 0.70833333 | E65: 1 | G65: meeting mel
A66: 28 | B66: Wednesday
A67: 29 | B67: Thursday
A68: 30 | B68: Friday | G68: Easter Friday
A69: 31 | B69: Saturday
A70: 1 | B70: Sunday | E70: 4
A71: MISSED | B71: TOTAL | E71: =SUM(E63:E70) -> 8 | F71: Hours submitted | G71: Hours owing
A72: Tuesday 4th April | B72: Payday | E72: =SUM(E60,E71) -> 23 | F72: 0 | G72: =SUM(E72+G49) -> 54.75
B75: Week of 02/04/2018 | C75: Start | D75: Finish | E75: Hrs worked | F75: Total Pay | G75: Description
A76: 2 | B76: Monday | G76: Easter monday
A77: 3 | B77: Tuesday
A78: 4 | B78: Wednesday
A79: 5 | B79: Thursday | C79: 0.5 | D79: 0.54166667 | E79: 1 | G79: meeting Anthony, set up email and tasks
A82: 6 | B82: Friday | C82: 0.33333333 | D82: 0.375 | E82: 1 | G82: Eithics ideas and options for SN
A83: 7 | B83: Saturday
A84: 8 | B84: Sunday | E84: 7 | G84: Admin/general running around over week
B85: TOTAL | E85: =SUM(E76:E84) -> 9
B88: Week of 09/04/2018 | C88: Start | D88: Finish | E88: Hrs worked | F88: Total Pay | G88: Description
A89: 9 | B89: Monday | C89: 0.75 | D89: 0.89583333 | E89: 3.5 | G89: Admin, emails to crew, hugh, and room location
A91: 10 | B91: Tuesday 17payday
A92: 11 | B92: Wednesday
A93: 12 | B93: Thursday
A94: 13 | B94: Friday | C94: 0.125 | D94: 0.16666667 | E94: 1 | G94: Meeting Anthony
A95: 14 | B95: Saturday | E95: 14 | G95: Overall hours from admin and co-ordination over the week
A96: 15 | B96: Sunday | C96: 0.375 | D96: 0.70833333 | E96: 7 | G96: Haysem one-on-one
B97: TOTAL | E97: =SUM(E89:E96) -> 25.5
A98: MISSED | B98: Payday | E98: =SUM(E89:E96,E76:E84) -> 34.5 | F98: Hours submitted | G98: hours owing
E99: MISSED | F99: 0 | G99: =SUM(E98+G72) -> 89.25
B101: Week of 16/04/2018 | C101: Start | D101: Finish | E101: Hrs worked | F101: Total Pay | G101: Description
A102: 16 | B102: Monday
A103: 17 | B103: Tuesday
A104: 18 | B104: Wednesday
A105: 19 | B105: Thursday | C105: 0.5 | D105: 0.041666667 | E105: 1 | G105: Meeting Anthony
A106: 20 | B106: Friday
A107: 21 | B107: Saturday
A108: 22 | B108: Sunday
B109: TOTAL | E109: =SUM(E102:E108) -> 1
A111: END CONTRACT START A NEW ONE
B113: Week of 23/04/2018 | C113: Start | D113: Finish | E113: Hrs worked | F113: Total Pay | G113: Description
A114: 23 | B114: Monday
A116: 24 | B116: Tuesday
A117: 25 | B117: Wednesday
A118: 26 | B118: Thursday
A120: 27 | B120: Friday
A121: 28 | B121: Saturday
A122: 29 | B122: Sunday | E122: 7 | G122: Admin/general running around over week
...

Sheet Final_Angelica
A1: Angelica Lopez
B5: Week of 26/02/2018 | C5: Start | D5: Finish | E5: Hrs worked | F5: Total Pay | G5: Description
B6: Monday
B7: Tuesday
B8: Wednesday
B9: Thursday | C9: 0.54166667 | D9: 0.625 | E9: 2
B10: Friday | C10: 0.54166667 | D10: 0.625 | E10: 2
B11: Saturday
B12: Sunday
B16: Week of 05/03/2018 | C16: Start | D16: Finish | E16: Hrs worked | F16: Total Pay | G16: Description
B17: Monday
B18: Tuesday
B19: Wednesday | E19: 3
B20: Thursday | C20: 0.39583333 | D20: 0.45833333 | E20: 1.5
C21: 0.54166667 | D21: 0.625 | E21: 2
B22: Friday
B23: Saturday
B24: Sunday
E25: =SUM(E9:E10,E19:E21) -> 10.5
A27: before this point all work was PAID IN VOUCHERS…
B29: ANTHONY's INPUT
B34: Week of 12/03/2018 | C34: Start | D34: Finish | E34: Hrs worked | F34: Hrs Paid | G34: Description | H34: Payment received
A35: 12 | B35: Monday
A36: 13 | B36: Tuesday | C36: 0.375 | D36: 0.5 | E36: 3 | G36: Seaching by courses using different terminology to list the list of statistical courses offered at UC. The whole dataset is complete it
A37: 14 | B37: Wednesday
A38: 15 | B38: Thursday | C38: 0.54166667 | D38: 0.625 | E38: 2 | G38: Regular Drop in
A39: 16 | B39: Friday | C39: 0.375 | D39: 0.5 | E39: 3 | G39: organized files. In dropbox. Reading and organized the whole files and build a dataset of files.
A40: 17 | B40: Saturday
A41: 18 | B41: Sunday
B42: TOTAL | E42: =SUM(E35:E41) -> 8 | F42: Hours submitted | G42: Hours owing
A43: Tuesday 21 March | B43: Payday | E43: =SUM(E35:E39) -> 8 | F43: =SUM(1*[2]Angelica_hist!G3) -> 5 | G43: =SUM(E43-F43) -> 3
B46: Week of 19/03/2018 | C46: Start | D46: Finish | E46: Hrs worked | F46: Hrs Paid | G46: Description | H46: Payment received
A47: 19 | B47: Monday
A48: 20 | B48: Tuesday
A49: 21 | B49: Wednesday
A50: 22 | B50: Thursday | C50: 0.54166667 | D50: 0.625 | E50: 2 | G50: Regular Drop in
A51: 23 | B51: Friday | C51: 0.375 | D51: 0.45833333 | E51: 2 | G51: Statistical Network project process and possible tasks. In dropbox.
A52: 24 | B52: Saturday
A53: 25 | B53: Sunday
B54: TOTAL | E54: =SUM(E46:E53) -> 4
B56: Week of 26/03/2018 | C56: Start | D56: Finish | E56: Hrs worked | F56: Total Pay | G56: Description
A57: 26 | B57: Monday | C57: 0.375 | D57: 0.41666667 | E57: 1 | G57: meeting with Anthony check face
A58: 27 | B58: Tuesday
A59: 28 | B59: Wednesday 28 march
A60: 29 | B60: Thursday | C60: 0.54166667 | D60: 0.625 | E60: 2 | G60: Regular Drop in
A61: 30 | B61: Friday | C61: 0.375 | D61: 0.45833333 | E61: 2 | G61: Buiding document for stats process.
A62: 31 | B62: Saturday
A63: 1 | B63: Sunday
B64: TOTAL | E64: =SUM(E57:E63) -> 5 | F64: Hours submitted | G64: Hours owing
A65: Tuesday 4th April | B65: Payday | E65: =SUM(E64,E54) -> 9 | F65: =SUM(1*[2]Angelica_hist!G9) -> 5 | G65: =SUM(E65+G43)-F65 -> 7
B67: Week of 02/04/2018 | C67: Start | D67: Finish | E67: Hrs worked | F67: Total Pay | G67: Description | H67: Where did this come from? I Have added this in as hours but not sure if this was a mistake or actual hours
A68: 2 | B68: Monday
A69: 3 | B69: Tuesday 3 April
A70: 4 | B70: Wednesday
A71: 5 | B71: Thursday | C71: 0.54166667 | D71: 0.125 | E71: 2 | G71: Drop in session
A72: 6 | C72: 0.625 | D72: 0.70833333 | E72: 2 | G72: Writing Process document
A73: 7 | B73: Friday
A74: 8 | B74: Saturday
A75: 9 | B75: Sunday
B76: TOTAL | E76: =SUM(E68:E75) -> 4
B80: Week of 02/04/2018 | C80: Start | D80: Finish | E80: Hrs worked | F80: Total Pay | G80: Description
B81: Monday | G81: Easter monday
B82: Tuesday
B83: Wednesday
B84: Thursday | C84: 0.5 | D84: 0.54166667 | E84: 1 | G84: meeting Anthony, set up email and tasks
C85: 0.54166667 | D85: 0.125 | E85: 2 | G85: Drop in session
C86: 0.75 | D86: 0.83333333 | E86: 2 | G86: Coding Anna meta analysis
B87: Friday | C87: 0.70833333 | D87: 0.75 | E87: 1 | G87: Emails and fixing plots for Anna
B88: Saturday | C88: 0.41666667 | D88: 0.47916667 | E88: 1.5 | G88: Emails, follow up (Abel Zhou, conversation with Anna)
B89: Sunday
B90: TOTAL | E90: =SUM(E81:E89) -> 7.5 | G90: minus5previous pay
B93: Week of 09/04/2018 | C93: Start | D93: Finish | E93: Hrs worked | F93: Total Pay | G93: Description
B94: Monday | C94: 0.45833333 | D94: 0.54166667 | E94: 2 | G94: Individual consultation Anna
C95: 0.58333333 | D95: 15:30 PM | E95: 1.5 | G95: Admin, answering and writing emails (Sam Kosari and Sucholana)
B96: Tuesday 17payday
B97: Wednesday
B98: Thursday | C98: 0.041666667 | D98: 0.125 | E98: 2 | G98: Drop in session
B99: Friday | C99: 0.125 | D99: 0.16666667 | E99: 1 | G99: Meeting Anthony
B100: Saturday | F100: 3.5
B101: Sunday
B102: TOTAL | E102: =SUM(E94:E101) -> 6.5
A103: MISSED | B103: TOTAL | E103: =SUM(E102,E90,E76) -> 18 | F103: Hours submitted | G103: hours owing
B104: Payday | E104: MISSED | F104: n/a | G104: =SUM(E103+G65) -> 25 | H104: This includes missed hours from this pay
B106: Week of 16/04/2018 | C106: Start | D106: Finish | E106: Hrs worked | F106: Total Pay | G106: Description
B107: Monday | C107: 11.30 am | D107: 0.5 | E107: 0.5 | G107: Response emails, references to Anna and ackwoledgement
B108: Tuesday
B109: Wednesday
B110: Thursday | C110: 0.5 | D110: 0.041666667 | E110: 1 | G110: Meeting Anthony
C111: 0.041666667 | D111: 0.125 | E111: 2 | G111: Drop in session
C112: 0.125 | D112: 0.14583333 | E112: 0.5 | G112: Meeting with Kym
B113: Friday
B117: Saturday
B118: Sunday | C118: 0.54166667 | D118: 0.64583333 | E118: 2.5 | G118: First report Kym, see the email
B119: TOTAL | E119: =SUM(E107:E118) -> 6.5
A120: END CONTRACT START A NEW ONE
B122: Week of 23/04/2018 | C122: Start | D122: Finish | E122: Hrs worked | F122: Total Pay | G122: Description
A123: 23 | B123: Monday | C123: 11.30 am | D123: 0.5 | E123: 0.5 | G123: Update dataset of drop-in sessions and emails.
C124: 4:30pm | D124: 0.70833333 | E124: 0.5 | G124: Response to Michelle Montgomery about her Logistic regression problem
A125: 24 | B125: Tuesday | C125: 0.625 | D125: 0.70833333 | E125: 2 | G125: Second response to kym, analysis of survey II part
A126: 25 | B126: Wednesday | G126: ANZAC DAY
...

Sheet Final_Marg
A1: Margarita
A8: ANTHONY's INPUT
A9: NEW CONTRACT
A11: END CONTRACT START A NEW ONE | B11: Week of 05/03/2018 | C11: Start | D11: Finish | E11: Hrs worked | F11: Total Pay | G11: Description | I11: Stage one | J11: 1st February - 13th May
A12: 4 | B12: Monday | C12: 0.625 | D12: 0.66666667 | E12: 1 | G12: Asking about job situation and lining up timetables | I12: Stage two | J12: 14th May - 1 July
A13: 5 | B13: Tuesday | I13: Stage three: Current | J13: 2 July 2018 - 1st September 2018
A14: 6 | B14: Wednesday | C14: 0.625 | D14: 0.66666667 | E14: 1 | G14: Meeting for contracts etc
A15: 7 | B15: Thursday
A16: 8
A17: 9 | B17: Friday
A18: 10 | B18: Saturday
A19: 11 | B19: Sunday
B20: TOTAL | E20: =SUM(E12:E19) -> 2
B22: Week of 12/03/2018 | C22: Start | D22: Finish | E22: Hrs worked | F22: Hrs Paid | G22: Description | H22: Payment received
A23: 12 | B23: Monday
A24: 13 | B24: Tuesday
A25: 14 | B25: Wednesday
A26: 15 | B26: Thursday
A27: 16 | B27: Friday
A28: 17 | B28: Saturday
A29: 18 | B29: Sunday
B30: TOTAL | E30: =SUM(E23:E29) -> 0 | F30: Hours submitted | G30: Hours owing
A31: Tuesday 21 March | B31: Payday | E31: =SUM(E30+E20) -> 2 | F31: =SUM(1*[3]Marg_hist!G3) -> 5 | G31: =SUM(E31+G20)-F31 -> -3
A32: 43180
B34: Week of 19/03/2018 | C34: Start | D34: Finish | E34: Hrs worked | F34: Hrs Paid | G34: Description | H34: Payment received
A35: 19 | B35: Monday
A36: 20 | B36: Tuesday
A37: 21 | B37: Wednesday
A38: 22 | B38: Thursday
A39: 23 | B39: Friday
A40: 24 | B40: Saturday
A41: 25 | B41: Sunday
B42: TOTAL | E42: =SUM(E34:E41) -> 0
B44: Week of 26/03/2018 | C44: Start | D44: Finish | E44: Hrs worked | F44: Total Pay | G44: Description
A45: 26 | B45: Monday
A46: 27 | B46: Tuesday
A47: 28 | B47: Wednesday 28 march
A48: 29 | B48: Thursday | C48: 0.5 | D48: 0.66666667 | E48: 4 | G48: Meeting / admin / emails
A49: 30 | B49: Friday
A50: 31 | B50: Saturday
A51: 1 | B51: Sunday
B52: TOTAL | E52: =SUM(E44:E51) -> 4 | F52: Hours submitted | G52: Hours owing
A53: Tuesday 3 April | B53: Payday | E53: =SUM(E45:E51,E35:E41) -> 4 | F53: =SUM([3]Marg_hist!G9) -> 5 | G53: =SUM(E53+G31)-F53 -> -4
A54: 43194
B55: Week of 02/04/2018 | C55: Start | D55: Finish | E55: Hrs worked | F55: Total Pay | G55: Description
A56: 2 | B56: Monday | G56: Easter monday
A57: 3 | B57: Tuesday
A58: 4 | B58: Wednesday
A59: 5 | B59: Thursday
A60: 6 | B60: Friday | C60: 0.39583333 | D60: 0.47916667 | E60: 2 | G60: Meeting / admin / emails
A61: 7 | B61: Saturday | C61: 0.5 | D61: 0.54166667 | E61: 1 | G61: Meeting with Angelica
A62: 8 | B62: Sunday | C62: 0.5 | D62: 0.58333333 | E62: 2 | G62: Survey for drop-in
B63: TOTAL | E63: =SUM(E56:E62) -> 5
B68: Week of 09/04/2018 | C68: Start | D68: Finish | E68: Hrs worked | F68: Total Pay | G68: Description
A69: 9 | B69: Monday
A70: 10 | B70: Tuesday | C70: 0.60416667 | D70: 0.625 | E70: 0.5 | G70: Fayah statistics one-on-one
C71: 0.625 | D71: 0.64583333 | E71: 0.5 | G71: Admin meeting with Anthony
A72: 11 | B72: Wednesday
A73: 12 | B73: Thursday | C73: 0.41666667 | D73: 0.4375 | E73: 0.5 | G73: survey
A74: 13 | B74: Friday | C74: 0.58333333 | D74: 0.64583333 | E74: 1.5 | G74: admin emails
A75: 14 | B75: Saturday
A76: 15 | B76: Sunday
A77: MISSED | B77: TOTAL | E77: =SUM(E69:E76) -> 3 | F77: Hours submitted | G77: Hours owing
B78: Payday | D78: MISSED | E78: =SUM(E63,E77) -> 8 | F78: n/a | G78: =SUM(E77+G53+E63) -> 4 | H78: Owe you 4hrs
B81: Week of 16/04/2018 | C81: Start | D81: Finish | E81: Hrs worked | F81: Total Pay | G81: Description
A82: 16 | B82: Monday | C82: 0.29166667 | D82: 9;00 | E82: 2 | G82: mails in folders
A83: 17 | B83: Tuesday
A84: 18 | B84: Wednesday
A85: 19 | B85: Thursday | C85: 0.40277778 | D85: 0.48611111 | E85: 2 | G85: shut up and write
A86: 20 | B86: Friday
A87: 21 | B87: Saturday | C87: 0.41666667 | D87: 0.45833333 | E87: 1 | G87: admin
A88: 22 | B88: Sunday
B89: TOTAL | E89: =SUM(E82:E88) -> 5
B92: Week of 23/04/2018 | C92: Start | D92: Finish | E92: Hrs worked | F92: Total Pay | G92: Description
A93: 23 | B93: Monday | C93: 0.375 | D93: 0.45833333 | E93: 2 | G93: fayha
A94: 24 | B94: Tuesday
A95: 25 | B95: Wednesday
A96: 26 | B96: Thursday | C96: 0.375 | D96: 0.41666667 | E96: 1 | G96: florence
A97: 27 | B97: Friday
A98: 28 | B98: Saturday | C98: 0.41666667 | D98: 0.45833333 | E98: 1 | G98: admin emails
A99: 29 | B99: Sunday
B100: TOTAL | E100: =SUM(E91:E99) -> 4 | F100: Hours submitted | G100: Hours owing | H100: After this Margie owes network 5hrs
A101: Tuesday 2nd May 2018 | B101: Payday | E101: =SUM(E89,E100) -> 9 | F101: =SUM(1*[3]Marg_hist!G15) -> 18 | G101: =SUM(E101 + G78)-F101 -> -5 | H101: Behind including pay missed from previous pay cycle
A102: 43222
B103: Week of 30/04/2018 | C103: Start | D103: Finish | E103: Hrs worked | F103: Total Pay | G103: Description | I103: Stage one | J103: 1st February - 13th May
A104: 30 | B104: Monday | I104: Stage two | J104: 14th May - 1 July
A105: 1 | B105: Tuesday | C105: 0.58333333 | D105: 0.625 | E105: 1 | G105: Fayha | I105: Stage three: Current | J105: 2 July 2018 - 1st September 2018
A106: 2 | B106: Wednesday
A107: 3 | B107: Thursday
A108: 4 | B108: Friday | C108: 0.41666667 | D108: 0.45833333 | E108: 1 | G108: admin/emails
A109: 5 | B109: Saturday
A110: 6 | B110: Sunday
B111: TOTAL | E111: 2
B114: Week of 07/05/2018 | C114: Start | D114: Finish | E114: Hrs worked | F114: Total Pay | G114: Description
A115: 7 | B115: Monday
A116: 8 | B116: Tuesday
A117: 9 | B117: Wednesday | C117: 0.5625 | D117: 0.60416667 | E117: 1 | G117: Fayha meeting
A118: 10 | B118: Thursday
A119: 11 | B119: Friday | C119: 0.41666667 | D119: 0.45833333 | E119: 1 | G119: admin/emails
A120: 12 | B120: Saturday
...

Sheet Final_kyle
A1: Kyle Hemming
A2: Weekly roster
B3: Start | C3: Finish | D3: Hrs worked | E3: Total Pay | F3: Description
A4: Monday | G4: Kyle has been doing the drop-in sessions from the very beginning of the statistics network in 2017. There has been mininal variation in the timesheets or workload other than during transistion periods.
A5: Tuesday
A6: Wednesday
A7: Thursday | B7: 0.54166667 | C7: 0.125 | D7: 2 | F7: Drop-in session
A8: Friday
A9: Saturday
A10: Sunday
A11: TOTAL | D11: 2
A14: Submit paper forms | B14: Submit electronic | C14: Payday | D14: Hrs worked | E14: Hrs submitted | F14: Hrs paid | G14: NOTES
A15: Previous trial period……
C18: 11th January 2018 | D18: 4
C19: 25th January 2018 | D19: 4 | E19: =SUM(#REF!) -> #REF!
C20: 8th February 2018 | D20: 4 | E20: =SUM(#REF!) -> #REF! | G20: Back pay
C21: 22nd February 2018 | D21: 4
C22: 8th March 2018 | D22: 4 | E22: =SUM(#REF!) -> #REF!
C23: 22nd March 2018 | D23: 4 | E23: =SUM(#REF!) -> #REF!
C24: 5th April 2018 | D24: 4 | E24: =SUM(#REF!) -> #REF!
C25: 19th April 2018 | D25: 4 | E25: =SUM(#REF!) -> #REF!
C26: 3rd May 2018 | D26: 4 | E26: =SUM(#REF!) -> #REF! | G26: Pay screw-up
C27: 17th May 2018 | D27: 2 | E27: =SUM(#REF!) -> #REF! | G27: Pay screw-up
C28: 31st May 2018 | D28: 4 | E28: =SUM(#REF!) -> #REF!
C29: 14th June 2018 | D29: 4 | E29: =SUM(#REF!) -> #REF!
C30: 27th June 2018 | D30: 4 | E30: =SUM(#REF!) -> #REF!
C31: 11th July 2018 | D31: 4 | E31: =SUM(#REF!) -> #REF! | G31: Shut-up and write too…??
C32: 26th July 2018 | D32: 4 | E32: 4 | F32: 0 | G32: 4hours owing orginally
C33: 9th August 2018 | D33: 4 | E33: 0 | F33: 4
C34: 23rd August 2018 | D34: 4 | E34: 0 | F34: 4
C35: 6th September 2018 | E35: 0 | F35: 4
C36: 20th September 2018
C37: 4th October 2018
C38: 18th October 2018
C39: 1st November 2018
C40: 15th Novermber 2018
C41: 29th November 2018
C42: 13th December 2018
C43: 27th December 2018
A44: TOTALS | B44: Estimate | C44: TOTAL | D44: =SUM(D18:D43) -> 66 | E44: =SUM(E18:E43) -> #REF! | G44: Extra paid that shouldn't be there..Shutupand write etc…
B45: Accounting for issues | C45: extra work | E45: =SUM(E44-E20-3) -> #REF! | G45: Back pay difference
B46: Final statement | C46: Difference | E46: =SUM(E45-D44) -> #REF! | G46: half an hour extra somewhere but don't worry about it….
A48: END CONTRACT START A NEW ONE
A50: 4hours owing orginally | B50: Week of 02/07/2018 | C50: Start | D50: Finish | E50: Hrs worked | F50: Total Pay | G50: Description
A51: 2 | B51: Monday
A52: 3 | B52: Tuesday
A53: 4 | B53: Wednesday
A54: 5 | B54: Thursday | C54: 0.54166667 | D54: 0.625 | E54: 2 | G54: drop-in
A56: 6 | B56: Friday
A57: 7 | B57: Saturday
A58: 8 | B58: Sunday
B59: TOTAL | E59: =SUM(E51:E58) -> 2 | F59: Hours submitted | G59: Hours owing
A60: 11th July 2018 | B60: Payday | E60: 2 | F60: =SUM(#REF!) -> #REF! | G60: =SUM(E60-F60)-4 -> #REF! | H60: Now this should be set to 4hours extra from here….
G61: =SUM(E60-F60)+1 -> #REF!
B62: Week of 09/07/2018 | C62: Start | D62: Finish | E62: Hrs worked | F62: Total Pay | G62: Description
A63: 9 | B63: Monday
A64: 10 | B64: Tuesday
A65: 11 | B65: Wednesday
A66: 12 | B66: Thursday | C66: 0.54166667 | D66: 0.625 | E66: 2 | G66: drop-in
A67: 13 | B67: Friday
A68: 14 | B68: Saturday
A69: 15 | B69: Sunday
B70: TOTAL | E70: 2
B72: Week of 16/07/2018 | C72: Start | D72: Finish | E72: Hrs worked | F72: Total Pay | G72: Description
B73: Monday
B74: Tuesday
B75: Wednesday
B76: Thursday | C76: 0.54166667 | D76: 0.625 | E76: 2 | G76: drop-in
B77: Friday
B78: Saturday
B79: Sunday
A80: MISSED | B80: TOTAL | E80: =SUM(E72:E79) -> 2 | F80: Hours submitted | G80: Hours owing
B81: Payday | D81: MISSED | E81: 4 | F81: 0 | G81: =SUM(E81+G61)-F81 -> #REF! | H81: SQUARE!!!
B83: Week of 23/07/2018 | C83: Start | D83: Finish | E83: Hrs worked | F83: Total Pay | G83: Description
B84: Monday
B85: Tuesday
B86: Wednesday
B87: Thursday | C87: 0.54166667 | D87: 0.625 | E87: 2 | G87: drop-in
B88: Friday
B89: Saturday
B90: Sunday
B91: TOTAL | E91: =SUM(E83:E90) -> 2
B93: Week of 30/07/2018 | C93: Start | D93: Finish | E93: Hrs worked | F93: Total Pay | G93: Description
B94: Monday
A95: SUMIT ON 31st July 2018 | B95: Tuesday
B96: Wednesday
B97: Thursday | C97: 0.54166667 | D97: 0.625 | E97: 2 | G97: drop-in
B98: Friday
B99: Saturday
B100: Sunday
B101: TOTAL | E101: =SUM(E93:E100) -> 2 | F101: Hours submitted | G101: Hours owing
A102: 9th August 2018 | B102: Payday | E102: 4 | G102: =SUM(E102+G81)-F102 -> #REF! | H102: SUMIT ON 31st July 2018
B104: Week of 06/08/2018 | C104: Start | D104: Finish | E104: Hrs worked | F104: Total Pay | G104: Description
B105: Monday
B106: Tuesday
B107: Wednesday
B108: Thursday | C108: 0.54166667 | D108: 0.625 | E108: 2 | G108: drop-in
B109: Friday
B110: Saturday
B111: Sunday
...

Sheet Anthony
A1: NEW CONTRACT | O1: Monday
O2: Tuesday
A3: END CONTRACT START A NEW ONE | B3: Week of 05/03/2018 | C3: Start | D3: Finish | E3: Hrs worked | F3: Total Pay | G3: Description | I3: Stage one | J3: 1st February - 13th May | O3: Wednesday
A4: 4 | B4: Monday | C4: 0.625 | D4: 0.66666667 | E4: 1 | G4: Asking about job situation and lining up timetables | I4: Stage two | J4: 14th May - 1 July | O4: Thursday | P4: 0.54166667 | Q4: 0.625 | R4: 2 | T4: Drop-in
A5: 5 | B5: Tuesday | I5: Stage three: Current | J5: 2 July 2018 - 1st September 2018 | P5: 0.625 | Q5: 0.66666667 | R5: 1 | T5: Jenni
A6: 6 | B6: Wednesday | C6: 0.625 | D6: 0.66666667 | E6: 1 | G6: Meeting for contracts etc | O6: Friday | P6: 0.54166667 | Q6: 0.625 | R6: 2 | T6: Ant+ Angelica
A7: 7 | B7: Thursday | O7: Saturday | P7: 0.54166667 | Q7: 0.58333333 | R7: 1 | T7: Admin | U7: Emailing network people
A8: 8 | O8: Sunday | P8: 0.375 | Q8: 0.625 | R8: 6 | T8: Haysem one-on-one. | U8: Regression and research management
A9: 9 | B9: Friday | O9: TOTAL | R9: =SUM(R1:R8) -> 12
A10: 10 | B10: Saturday
A11: 11 | B11: Sunday
B12: TOTAL | E12: =SUM(E4:E11) -> 2 | G12: 2hrs owed | O12: Week of 05/03/2018 | P12: Start | Q12: Finish | R12: Hrs worked | S12: Total Pay | T12: Description
O13: Monday | P13: 0.41666667 | Q13: 0.45833333 | R13: 1 | T13: Admin(emails)
B14: Week of 12/03/2018 | C14: Start | D14: Finish | E14: Hrs worked | F14: Hrs Paid | G14: Description | H14: Payment received | O14: Tuesday | P14: 0.41666667 | Q14: 0.45833333 | R14: 1 | T14: Admin(emails)
A15: 12 | B15: Monday | P15: 0.52083333 | Q15: 0.54166667 | R15: 0.5 | T15: Lecture
A16: 13 | B16: Tuesday | P16: 0.64583333 | Q16: 0.6875 | R16: 1 | T16: Contracts meeting and admin
A17: 14 | B17: Wednesday | O17: Wednesday | P17: 0.5625 | Q17: 0.66666667 | R17: 3.5 | T17: Network building
A18: 15 | B18: Thursday | P18: 0.72916667 | Q18: 0.9375 | R18: 5 | T18: Haysem
A19: 16 | B19: Friday | P19: 0.97916667 | Q19: 0.052083333 | R19: 1.75 | T19: Admin(emails)
A20: 17 | B20: Saturday | O20: Thursday | P20: 0.45833333 | Q20: 0.5 | R20: 1 | T20: Admin meeting maths&stats
A21: 18 | B21: Sunday | P21: 0.5 | Q21: 0.625 | R21: 3 | T21: Shalini one-on-one
B22: TOTAL | E22: =SUM(E15:E21) -> 0 | G22: 2hrs owed | P22: 0.625 | Q22: 0.66666667 | R22: 1 | T22: Admin meeting contracts + anna
A23: Tuesday 21 March | B23: Payday | E23: =SUM(E15:E19, E4:E11) -> 2 | F23: 10hrs submitted | G23: 8hrs extra | H23: 10hrs paid | O23: Friday | R23: =SUM(Q23-P23) -> 0
O24: Saturday | R24: =SUM(Q24-P24) -> 0
O25: Sunday | R25: =SUM(Q25-P25) -> 0
B26: Week of 19/03/2018 | C26: Start | D26: Finish | E26: Hrs worked | F26: Hrs Paid | G26: Description | H26: Payment received | O26: TOTAL | R26: =SUM(R13:R25) -> 18.75
A27: 19 | B27: Monday | O27: PAID | S27: 30.75 hrs submitted 13/04/2018
A28: 20 | B28: Tuesday
A29: 21 | B29: Wednesday
A30: 22 | B30: Thursday | O30: Week of 12/03/2018 | P30: Start | Q30: Finish | R30: Hrs worked | S30: Total Pay | T30: Description
A31: 23 | B31: Friday | O31: Monday
A32: 24 | B32: Saturday | O32: Tuesday
A33: 25 | B33: Sunday | O33: Wednesday
B34: TOTAL | E34: =SUM(E26:E33) -> 0 | G34: 8hrs extra | O34: Thursday
O35: Friday
B36: Week of 26/03/2018 | C36: Start | D36: Finish | E36: Hrs worked | F36: Total Pay | G36: Description | O36: Saturday
A37: 26 | B37: Monday | O37: Sunday
A38: 27 | B38: Tuesday | O38: TOTAL | R38: 7
A39: 28 | B39: Wednesday 28 march
A40: 29 | B40: Thursday | C40: 0.5 | D40: 0.66666667 | E40: 4 | G40: Meeting / admin / emails
A41: 30 | B41: Friday
A42: 31 | B42: Saturday | O42: Week of 19/03/2018 | P42: Start | Q42: Finish | R42: Hrs worked | S42: Total Pay | T42: Description
A43: 1 | B43: Sunday | O43: Monday
B44: TOTAL | E44: =SUM(E36:E43) -> 4 | G44: 4hrs extra | O44: Tuesday
A45: Tuesday 3 April | B45: Payday | E45: =SUM(E37:E43,E27:E33) -> 4 | F45: 10hrs submitted | G45: 14hrs extra | H45: 10hrs paid | O45: Wednesday
O46: Thursday
B47: Week of 02/04/2018 | C47: Start | D47: Finish | E47: Hrs worked | F47: Total Pay | G47: Description | O47: Friday | P47: 0.75 | Q47: 0.91666667 | R47: 4 | T47: kasia stats
A48: 2 | B48: Monday | G48: Easter monday | O48: Saturday
A49: 3 | B49: Tuesday | O49: Sunday | R49: 3
A50: 4 | B50: Wednesday | O50: TOTAL | R50: =SUM(R43:R49) -> 7
A51: 5 | B51: Thursday
A52: 6 | B52: Friday | C52: 0.39583333 | D52: 0.47916667 | E52: 2 | G52: Meeting / admin / emails
A53: 7 | B53: Saturday | C53: 0.5 | D53: 0.54166667 | E53: 1 | G53: Meeting with Angelica
A54: 8 | B54: Sunday | C54: 0.5 | D54: 0.58333333 | E54: 2 | G54: Survey for drop-in | O54: Week of 26/03/2018 | P54: Start | Q54: Finish | R54: Hrs worked | S54: Total Pay | T54: Description
B55: TOTAL | E55: =SUM(E48:E54) -> 5 | G55: 9hrs extra | O55: Monday | P55: 0.41666667 | Q55: 0.5 | R55: 2 | T55: maths&stats meeting
O56: Tuesday | P56: 0.66666667 | Q56: 0.70833333 | R56: 1 | T56: meeting mel
O57: Wednesday
O58: Thursday
O59: Friday | T59: Easter Friday
B60: Week of 09/04/2018 | C60: Start | D60: Finish | E60: Hrs worked | F60: Total Pay | G60: Description | O60: Saturday
A61: 9 | B61: Monday | O61: Sunday | R61: 4
A62: 10 | B62: Tuesday | C62: 0.60416667 | D62: 0.625 | E62: 0.5 | G62: Fayah statistics one-on-one | O62: TOTAL | R62: =SUM(R55:R61) -> 7
C63: 0.625 | D63: 0.64583333 | E63: 0.5 | G63: Admin meeting with Anthony
A64: 11 | B64: Wednesday
A65: 12 | B65: Thursday | C65: 0.41666667 | D65: 0.4375 | E65: 0.5 | G65: survey
A66: 13 | B66: Friday | C66: 0.58333333 | D66: 0.64583333 | E66: 1.5 | G66: admin emails | O66: Week of 02/04/2018 | P66: Start | Q66: Finish | R66: Hrs worked | S66: Total Pay | T66: Description
A67: 14 | B67: Saturday | O67: Monday | T67: Easter monday
A68: 15 | B68: Sunday | O68: Tuesday
B69: TOTAL | E69: =SUM(E61:E68) -> 3 | G69: 6hrs extra | O69: Wednesday
O70: Thursday
A71: Tuesday 17 April | B71: Payday | E71: =SUM(E48:E54,E61:E68) -> 8 | F71: 10hrs submitted | G71: 16hrs extra | H71: 10hrs paid | O71: Friday
O72: Saturday
B73: Week of 16/04/2018 | C73: Start | D73: Finish | E73: Hrs worked | F73: Total Pay | G73: Description | O73: Sunday | R73: 7
A74: 16 | B74: Monday | C74: 0.29166667 | D74: 9;00 | E74: 2 | G74: mails in folders | O74: TOTAL | R74: =SUM(R67:R73) -> 7
A75: 17 | B75: Tuesday
A76: 18 | B76: Wednesday
A77: 19 | B77: Thursday | C77: 0.40277778 | D77: 0.48611111 | E77: 2 | G77: shut up and write | O77: Week of 09/04/2018 | P77: Start | Q77: Finish | R77: Hrs worked | S77: Total Pay | T77: Description
A78: 20 | B78: Friday | O78: Monday | P78: 0.75 | Q78: 0.89583333 | R78: 3.5 | T78: Admin, emails to crew, hugh, and room location
A79: 21 | B79: Saturday | C79: 0.41666667 | D79: 0.45833333 | E79: 1 | G79: admin | O79: Tuesday
A80: 22 | B80: Sunday | O80: Wednesday
B81: TOTAL | E81: =SUM(E74:E80) -> 5 | G81: 11hrs extra | O81: Thursday
O82: Friday
O83: Saturday
B84: Week of 23/04/2018 | C84: Start | D84: Finish | E84: Hrs worked | F84: Total Pay | G84: Description | O84: Sunday
A85: 23 | B85: Monday | C85: 0.375 | D85: 0.45833333 | E85: 2 | G85: fayha | O85: TOTAL | R85: =SUM(R78:R84) -> 3.5
A86: 24 | B86: Tuesday | R86: 31.5hrs | S86: Timesheet
A87: 25 | B87: Wednesday | R87: 14hrs
A88: 26 | B88: Thursday | C88: 0.375 | D88: 0.41666667 | E88: 1 | G88: florence
A89: 27 | B89: Friday
A90: 28 | B90: Saturday | C90: 0.41666667 | D90: 0.45833333 | E90: 1 | G90: admin emails | O90: Week of 16/04/2018 | P90: Start | Q90: Finish | R90: Hrs worked | S90: Total Pay | T90: Description
A91: 29 | B91: Sunday | O91: Monday
B92: TOTAL | E92: =SUM(E85:E91) -> 4 | G92: 7hrs extra | O92: Tuesday
A93: Tuesday 17 April | B93: Payday | E93: =SUM(E70:E76,E83:E90) -> 14 | F93: 10hrs submitted | G93: 17hrs extra | H93: 10hrs paid | O93: Wednesday
O94: Thursday
B95: Week of 30/04/2018 | C95: Start | D95: Finish | E95: Hrs worked | F95: Total Pay | G95: Description | I95: Stage one | J95: 1st February - 13th May | O95: Friday
A96: 30 | B96: Monday | I96: Stage two | J96: 14th May - 1 July | O96: Saturday
A97: 1 | B97: Tuesday | C97: 0.58333333 | D97: 0.625 | E97: 1 | G97: Fayha | I97: Stage three: Current | J97: 2 July 2018 - 1st September 2018 | O97: Sunday
A98: 2 | B98: Wednesday | O98: TOTAL | R98: 5
A99: 3 | B99: Thursday
A100: 4 | B100: Friday | C100: 0.41666667 | D100: 0.45833333 | E100: 1 | G100: admin/emails
...

Sheet Anthony_hist
A1: Period End Date | B1: Surname | C1: Preferred Name | D1: GL Record Type Description | E1: Account Number Prefix | F1: Paycode | G1: Salary Hours | H1: Amt$
A2: 43124
A3: 43124 | B3: DAVIDSON | C3: Anthony | D3: Earnings | E3: 50007 | F3: Salary Casual | G3: 12.5 | H3: 716.91
A4: 43124 | B4: DAVIDSON | C4: Anthony | D4: Oncosts | E4: 50031 | F4: Oncosts | H4: 49.11
A5: 43124 | B5: DAVIDSON | C5: Anthony | D5: Oncosts | E5: 50032 | F5: Oncosts | H5: 4.67
A6: 43124 | B6: DAVIDSON | C6: Anthony | D6: Oncosts | E6: 50033 | F6: Oncosts | H6: 8.95
A7: 43124 | B7: DAVIDSON | C7: Anthony | D7: Subsidies | E7: 50027 | F7: Super | H7: 68.11
A8: 43138
A9: 43138 | B9: DAVIDSON | C9: Anthony | D9: Earnings | E9: 50007 | F9: Salary Casual | G9: 73.5 | H9: 4258.2
A10: 43138 | B10: DAVIDSON | C10: Anthony | D10: Oncosts | E10: 50031 | F10: Oncosts | H10: 291.7
A11: 43138 | B11: DAVIDSON | C11: Anthony | D11: Oncosts | E11: 50032 | F11: Oncosts | H11: 27.71
A12: 43138 | B12: DAVIDSON | C12: Anthony | D12: Oncosts | E12: 50033 | F12: Oncosts | H12: 53.22
A13: 43138 | B13: DAVIDSON | C13: Anthony | D13: Subsidies | E13: 50027 | F13: Super | H13: 404.53
A14: 43166
A15: 43166 | B15: DAVIDSON | C15: Anthony | D15: Earnings | E15: 50007 | F15: Salary Casual | G15: 6 | H15: 347.6
A16: 43166 | B16: DAVIDSON | C16: Anthony | D16: Oncosts | E16: 50031 | F16: Oncosts | H16: 23.81
A17: 43166 | B17: DAVIDSON | C17: Anthony | D17: Oncosts | E17: 50033 | F17: Oncosts | H17: 4.35
A18: 43180
A19: 43180 | B19: DAVIDSON | C19: Anthony | D19: Earnings | E19: 50007 | F19: Salary Casual | G19: 1 | H19: 57.93
A20: 43180 | B20: DAVIDSON | C20: Anthony | D20: Oncosts | E20: 50031 | F20: Oncosts | H20: 3.97
A21: 43180 | B21: DAVIDSON | C21: Anthony | D21: Oncosts | E21: 50033 | F21: Oncosts | H21: 0.72
A22: 43222
A23: 43222 | B23: DAVIDSON | C23: Anthony | D23: Earnings | E23: 50002 | F23: Rate P - Other | G23: 40.75 | H23: 1845.12
A24: 43222 | B24: DAVIDSON | C24: Anthony | D24: Oncosts | E24: 50018 | F24: Oncosts | H24: 126.39
A25: 43222 | B25: DAVIDSON | C25: Anthony | D25: Oncosts | E25: 50020 | F25: Oncosts | H25: 12.01
A26: 43222 | B26: DAVIDSON | C26: Anthony | D26: Oncosts | E26: 50021 | F26: Oncosts | H26: 23.06
A27: 43222 | B27: DAVIDSON | C27: Anthony | D27: Subsidies | E27: 50016 | F27: Super | H27: 175.29
A28: 43236
A29: 43236 | B29: DAVIDSON | C29: Anthony | D29: Earnings | E29: 50002 | F29: Rate P - Other | G29: 10 | H29: 452.79
A30: 43236 | B30: DAVIDSON | C30: Anthony | D30: Oncosts | E30: 50018 | F30: Oncosts | H30: 31.02
A31: 43236 | B31: DAVIDSON | C31: Anthony | D31: Oncosts | E31: 50020 | F31: Oncosts | H31: 2.95
A32: 43236 | B32: DAVIDSON | C32: Anthony | D32: Oncosts | E32: 50021 | F32: Oncosts | H32: 5.66
A33: 43236 | B33: DAVIDSON | C33: Anthony | D33: Subsidies | E33: 50016 | F33: Super | H33: 43.02
A34: 43250
A35: 43250 | B35: DAVIDSON | C35: Anthony | D35: Earnings | E35: 50002 | F35: Rate P - Other | G35: 65.5 | H35: 2965.78
A36: 43250 | B36: DAVIDSON | C36: Anthony | D36: Oncosts | E36: 50018 | F36: Oncosts | H36: 203.15
A37: 43250 | B37: DAVIDSON | C37: Anthony | D37: Oncosts | E37: 50020 | F37: Oncosts | H37: 19.3
A38: 43250 | B38: DAVIDSON | C38: Anthony | D38: Oncosts | E38: 50021 | F38: Oncosts | H38: 37.07
A39: 43250 | B39: DAVIDSON | C39: Anthony | D39: Subsidies | E39: 50016 | F39: Super | H39: 281.75
A40: 43264
A41: 43264 | B41: DAVIDSON | C41: Anthony | D41: Earnings | E41: 50002 | F41: Rate P - Other | G41: 4 | H41: 181.12
A42: 43264 | B42: DAVIDSON | C42: Anthony | D42: Oncosts | E42: 50018 | F42: Oncosts | H42: 12.4
A43: 43264 | B43: DAVIDSON | C43: Anthony | D43: Oncosts | E43: 50021 | F43: Oncosts | H43: 2.26
A44: 43278
A45: 43278 | B45: DAVIDSON | C45: Anthony | D45: Earnings | E45: 50002 | F45: Rate P - Other | G45: 4 | H45: 181.12
A46: 43278 | B46: DAVIDSON | C46: Anthony | D46: Oncosts | E46: 50018 | F46: Oncosts | H46: 12.4
A47: 43278 | B47: DAVIDSON | C47: Anthony | D47: Oncosts | E47: 50021 | F47: Oncosts | H47: 2.26
A48: 43292
A49: 43292 | B49: DAVIDSON | C49: Anthony | D49: Earnings | E49: 50002 | F49: Rate P - Other | G49: 2 | H49: 90.56
A50: 43292 | B50: DAVIDSON | C50: Anthony | D50: Oncosts | E50: 50018 | F50: Oncosts | H50: 6.2
A51: 43292 | B51: DAVIDSON | C51: Anthony | D51: Oncosts | E51: 50021 | F51: Oncosts | H51: 1.13
A52: TOTAL | G52: =SUM(G3:G51) -> 219.25 | H52: =SUM(H3:H51) -> 13035.3 | I52: =SUM(H52/G52) -> 59.454048

Sheet Angelica_hist
A1: Period End Date | B1: Surname | C1: Preferred Name | D1: GL Record Type Description | E1: Account Number Prefix | F1: Paycode | G1: Salary Hours | H1: Amt$
A2: 43180
A3: 43180 | B3: LOPEZ | C3: Angelica | D3: Earnings | E3: 50002 | F3: Rate P - Other | G3: 5 | H3: 226.4
A4: 43180 | B4: LOPEZ | C4: Angelica | D4: Oncosts | E4: 50018 | F4: Oncosts | H4: 15.51
A5: 43180 | B5: LOPEZ | C5: Angelica | D5: Oncosts | E5: 50020 | F5: Oncosts | H5: 1.47
A6: 43180 | B6: LOPEZ | C6: Angelica | D6: Oncosts | E6: 50021 | F6: Oncosts | H6: 2.83
A7: 43180 | B7: LOPEZ | C7: Angelica | D7: Subsidies | E7: 50016 | F7: Super | H7: 21.51
A8: 43194
A9: 43194 | B9: LOPEZ | C9: Angelica | D9: Earnings | E9: 50002 | F9: Rate P - Other | G9: 5 | H9: 226.4
A10: 43194 | B10: LOPEZ | C10: Angelica | D10: Oncosts | E10: 50018 | F10: Oncosts | H10: 15.51
A11: 43194 | B11: LOPEZ | C11: Angelica | D11: Oncosts | E11: 50021 | F11: Oncosts | H11: 2.83
A12: 43208 | B12: LOPEZ | C12: Angelica | D12: Oncosts | E12: 50020 | F12: Oncosts | H12: 1.47
A13: 43208 | B13: LOPEZ | C13: Angelica | D13: Subsidies | E13: 50016 | F13: Super | H13: 21.51
A14: 43222
A15: 43222 | B15: LOPEZ | C15: Angelica | D15: Earnings | E15: 50002 | F15: Rate P - Other | G15: 10 | H15: 452.78
A16: 43222 | B16: LOPEZ | C16: Angelica | D16: Oncosts | E16: 50018 | F16: Oncosts | H16: 31.02
A17: 43222 | B17: LOPEZ | C17: Angelica | D17: Oncosts | E17: 50020 | F17: Oncosts | H17: 2.95
A18: 43222 | B18: LOPEZ | C18: Angelica | D18: Oncosts | E18: 50021 | F18: Oncosts | H18: 5.66
A19: 43222 | B19: LOPEZ | C19: Angelica | D19: Subsidies | E19: 50016 | F19: Super | H19: 43.01
A20: 43236
A21: 43236 | B21: LOPEZ | C21: Angelica | D21: Earnings | E21: 50002 | F21: Rate O - Marking | G21: 22.5 | H21: 1215.87
A22: 43236 | B22: LOPEZ | C22: Angelica | D22: Oncosts | E22: 50018 | F22: Oncosts | H22: 83.29
A23: 43236 | B23: LOPEZ | C23: Angelica | D23: Oncosts | E23: 50020 | F23: Oncosts | H23: 7.91
A24: 43236 | B24: LOPEZ | C24: Angelica | D24: Oncosts | E24: 50021 | F24: Oncosts | H24: 15.19
A25: 43236 | B25: LOPEZ | C25: Angelica | D25: Subsidies | E25: 50016 | F25: Super | H25: 115.51
A26: 43250
A27: 43250 | B27: LOPEZ | C27: Angelica | D27: Earnings | E27: 50002 | F27: Rate O - Marking | G27: -22.5 | H27: -1215.87
A28: 43250 | B28: LOPEZ | C28: Angelica | D28: Earnings | E28: 50002 | F28: Rate P - Other | G28: 52.5 | H28: 2377.15
A29: 43250 | B29: LOPEZ | C29: Angelica | D29: Earnings | E29: 50002 | F29: Rate Q - Other | G29: 25 | H29: 1350.96
A30: 43250 | B30: LOPEZ | C30: Angelica | D30: Oncosts | E30: 50018 | F30: Oncosts | H30: 172.08
A31: 43250 | B31: LOPEZ | C31: Angelica | D31: Oncosts | E31: 50020 | F31: Oncosts | H31: 17.82
A32: 43250 | B32: LOPEZ | C32: Angelica | D32: Oncosts | E32: 50021 | F32: Oncosts | H32: 31.4
A33: 43250 | B33: LOPEZ | C33: Angelica | D33: Subsidies | E33: 50016 | F33: Super | H33: 260.17
A34: 43264
A35: 43264 | B35: LOPEZ | C35: Angelica | D35: Earnings | E35: 50002 | F35: Rate P - Other | G35: 30 | H35: 1358.37
A36: 43264 | B36: LOPEZ | C36: Angelica | D36: Oncosts | E36: 50018 | F36: Oncosts | H36: 93.04
A37: 43264 | B37: LOPEZ | C37: Angelica | D37: Oncosts | E37: 50020 | F37: Oncosts | H37: 8.84
A38: 43264 | B38: LOPEZ | C38: Angelica | D38: Oncosts | E38: 50021 | F38: Oncosts | H38: 16.98
A39: 43264 | B39: LOPEZ | C39: Angelica | D39: Subsidies | E39: 50016 | F39: Super | H39: 129.05
A40: 43278
A41: 43278 | B41: LOPEZ | C41: Angelica | D41: Earnings | E41: 50002 | F41: Rate P - Other | G41: 30 | H41: 1358.37
A42: 43278 | B42: LOPEZ | C42: Angelica | D42: Oncosts | E42: 50018 | F42: Oncosts | H42: 93.04
A43: 43278 | B43: LOPEZ | C43: Angelica | D43: Oncosts | E43: 50020 | F43: Oncosts | H43: 8.84
A44: 43278 | B44: LOPEZ | C44: Angelica | D44: Oncosts | E44: 50021 | F44: Oncosts | H44: 16.98
A45: 43278 | B45: LOPEZ | C45: Angelica | D45: Subsidies | E45: 50016 | F45: Super | H45: 129.05
A46: 43292
A47: 43292 | B47: LOPEZ | C47: Angelica | D47: Earnings | E47: 50002 | F47: Rate P - Other | G47: 15 | H47: 679.19
A48: 43292 | B48: LOPEZ | C48: Angelica | D48: Earnings | E48: 50002 | F48: Rate Q - Other | G48: 16 | H48: 864.62
A49: 43292 | B49: LOPEZ | C49: Angelica | D49: Oncosts | E49: 50018 | F49: Oncosts | H49: 105.75
A50: 43292 | B50: LOPEZ | C50: Angelica | D50: Oncosts | E50: 50020 | F50: Oncosts | H50: 10.05
A51: 43292 | B51: LOPEZ | C51: Angelica | D51: Oncosts | E51: 50021 | F51: Oncosts | H51: 19.3
A52: 43292 | B52: LOPEZ | C52: Angelica | D52: Subsidies | E52: 50016 | F52: Super | H52: 146.66
A54: TOTAL | G54: =SUM(G47:G52,G41:G45,G35:G39,G27:G33,G21:G25,G15:G19,G9:G13,G3:G7) -> 188.5 | H54: =SUM(H47:H52,H41:H45,H35:H39,H27:H33,H21:H25,H15:H19,H9:H13,H3:H7) -> 10540.47 | I54: =SUM(H54/G54) -> 55.917613

Sheet Marg_hist
A1: Period End Date | B1: Surname | C1: Preferred Name | D1: GL Record Type Description | E1: Account Number Prefix | F1: Paycode | G1: Salary Hours | H1: Amt$
A2: 43180
A3: 43180 | B3: MEDINA | C3: Margarita | D3: Earnings | E3: 50002 | F3: Rate P - Other | G3: 5 | H3: 226.4
A4: 43180 | B4: MEDINA | C4: Margarita | D4: Oncosts | E4: 50018 | F4: Oncosts | H4: 15.51
A5: 43180 | B5: MEDINA | C5: Margarita | D5: Oncosts | E5: 50020 | F5: Oncosts | H5: 1.47
A6: 43180 | B6: MEDINA | C6: Margarita | D6: Oncosts | E6: 50021 | F6: Oncosts | H6: 2.83
A7: 43180 | B7: MEDINA | C7: Margarita | D7: Subsidies | E7: 50016 | F7: Super | H7: 21.51
A8: 43194
A9: 43194 | B9: MEDINA | C9: Margarita | D9: Earnings | E9: 50002 | F9: Rate P - Other | G9: 5 | H9: 226.4
A10: 43194 | B10: MEDINA | C10: Margarita | D10: Oncosts | E10: 50018 | F10: Oncosts | H10: 15.51
A11: 43194 | B11: MEDINA | C11: Margarita | D11: Oncosts | E11: 50020 | F11: Oncosts | H11: 1.47
A12: 43194 | B12: MEDINA | C12: Margarita | D12: Oncosts | E12: 50021 | F12: Oncosts | H12: 2.83
A13: 43194 | B13: MEDINA | C13: Margarita | D13: Subsidies | E13: 50016 | F13: Super | H13: 21.51
A14: 43222
A15: 43222 | B15: MEDINA | C15: Margarita | D15: Earnings | E15: 50002 | F15: Rate P - Other | G15: 18 | H15: 815.01
A16: 43222 | B16: MEDINA | C16: Margarita | D16: Oncosts | E16: 50018 | F16: Oncosts | H16: 55.83
A17: 43222 | B17: MEDINA | C17: Margarita | D17: Oncosts | E17: 50020 | F17: Oncosts | H17: 5.31
A18: 43222 | B18: MEDINA | C18: Margarita | D18: Oncosts | E18: 50021 | F18: Oncosts | H18: 10.19
A19: 43222 | B19: MEDINA | C19: Margarita | D19: Subsidies | E19: 50016 | F19: Super | H19: 77.43
A20: 43236
A21: 43236 | B21: MEDINA | C21: Margarita | D21: Earnings | E21: 50002 | F21: Rate P - Other | G21: 10 | H21: 452.79
A22: 43236 | B22: MEDINA | C22: Margarita | D22: Oncosts | E22: 50018 | F22: Oncosts | H22: 31.02
A23: 43236 | B23: MEDINA | C23: Margarita | D23: Oncosts | E23: 50020 | F23: Oncosts | H23: 2.95
A24: 43236 | B24: MEDINA | C24: Margarita | D24: Oncosts | E24: 50021 | F24: Oncosts | H24: 5.66
A25: 43236 | B25: MEDINA | C25: Margarita | D25: Subsidies | E25: 50016 | F25: Super | H25: 43.02
A26: 43250
A27: 43250 | B27: MEDINA | C27: Margarita | D27: Earnings | E27: 50002 | F27: Rate P - Other | G27: 14 | H27: 633.91
A28: 43250 | B28: MEDINA | C28: Margarita | D28: Oncosts | E28: 50018 | F28: Oncosts | H28: 43.42
A29: 43250 | B29: MEDINA | C29: Margarita | D29: Oncosts | E29: 50020 | F29: Oncosts | H29: 4.14
A30: 43250 | B30: MEDINA | C30: Margarita | D30: Oncosts | E30: 50021 | F30: Oncosts | H30: 7.92
A31: 43250 | B31: MEDINA | C31: Margarita | D31: Subsidies | E31: 50016 | F31: Super | H31: 60.22
A32: 43264
A33: 43264 | B33: MEDINA | C33: Margarita | D33: Earnings | E33: 50002 | F33: Rate P - Other | G33: 14 | H33: 633.91
A34: 43264 | B34: MEDINA | C34: Margarita | D34: Oncosts | E34: 50018 | F34: Oncosts | H34: 43.42
A35: 43264 | B35: MEDINA | C35: Margarita | D35: Oncosts | E35: 50020 | F35: Oncosts | H35: 4.13
A36: 43264 | B36: MEDINA | C36: Margarita | D36: Oncosts | E36: 50021 | F36: Oncosts | H36: 7.92
A37: 43264 | B37: MEDINA | C37: Margarita | D37: Subsidies | E37: 50016 | F37: Super | H37: 60.22
A38: 43278
A39: 43278 | B39: MEDINA | C39: Margarita | D39: Earnings | E39: 50002 | F39: Rate P - Other | G39: 14 | H39: 633.91
A40: 43278 | B40: MEDINA | C40: Margarita | D40: Oncosts | E40: 50018 | F40: Oncosts | H40: 43.42
A41: 43278 | B41: MEDINA | C41: Margarita | D41: Oncosts | E41: 50020 | F41: Oncosts | H41: 4.13
A42: 43278 | B42: MEDINA | C42: Margarita | D42: Oncosts | E42: 50021 | F42: Oncosts | H42: 7.92
A43: 43278 | B43: MEDINA | C43: Margarita | D43: Subsidies | E43: 50016 | F43: Super | H43: 60.22
A44: 43292
A45: 43292 | B45: MEDINA | C45: Margarita | D45: Earnings | E45: 50002 | F45: Rate P - Other | G45: 7 | H45: 316.95
A46: 43292 | B46: MEDINA | C46: Margarita | D46: Oncosts | E46: 50018 | F46: Oncosts | H46: 21.71
A47: 43292 | B47: MEDINA | C47: Margarita | D47: Oncosts | E47: 50021 | F47: Oncosts | H47: 3.96
A48: TOTAL | G48: =SUM(G3:G47) -> 87 | H48: =SUM(H3:H47) -> 4626.08 | I48: =SUM(H48/G48) -> 53.173333

Sheet Kyle_hist
A1: Period End Date | B1: Surname | C1: Preferred Name | D1: GL Record Type Description | E1: Account Number Prefix | F1: Paycode | G1: Salary Hours | H1: Amt$
A2: 43124
A3: 43124 | B3: HEMMING | C3: Kyle | D3: Earnings | E3: 50007 | F3: Salary Casual | G3: 6.5 | H3: 376.58
A4: 43124 | B4: HEMMING | C4: Kyle | D4: Oncosts | E4: 50031 | F4: Oncosts | H4: 25.8
A5: 43124 | B5: HEMMING | C5: Kyle | D5: Oncosts | E5: 50033 | F5: Oncosts | H5: 4.71
A6: 43138
A7: 43138 | B7: HEMMING | C7: Kyle | D7: Earnings | E7: 50007 | F7: Salary Casual | G7: 21.5 | H7: 1245.59
A8: 43138 | B8: HEMMING | C8: Kyle | D8: Oncosts | E8: 50031 | F8: Oncosts | H8: 85.33
A9: 43138 | B9: HEMMING | C9: Kyle | D9: Oncosts | E9: 50032 | F9: Oncosts | H9: 8.11
A10: 43138 | B10: HEMMING | C10: Kyle | D10: Oncosts | E10: 50033 | F10: Oncosts | H10: 15.57
A11: 43138 | B11: HEMMING | C11: Kyle | D11: Subsidies | E11: 50027 | F11: Super | H11: 118.33
A12: 43166
A13: 43166 | B13: HEMMING | C13: Kyle | D13: Earnings | E13: 50007 | F13: Salary Casual | G13: 6 | H13: 347.61
A14: 43166 | B14: HEMMING | C14: Kyle | D14: Oncosts | E14: 50031 | F14: Oncosts | H14: 23.82
A15: 43166 | B15: HEMMING | C15: Kyle | D15: Oncosts | E15: 50033 | F15: Oncosts | H15: 4.35
A16: 43180
A17: 43180 | B17: HEMMING | C17: Kyle | D17: Earnings | E17: 50007 | F17: Salary Casual | G17: 4 | H17: 231.74
A18: 43180 | B18: HEMMING | C18: Kyle | D18: Oncosts | E18: 50031 | F18: Oncosts | H18: 15.88
A19: 43180 | B19: HEMMING | C19: Kyle | D19: Oncosts | E19: 50032 | F19: Oncosts | H19: 3.77
A20: 43180 | B20: HEMMING | C20: Kyle | D20: Oncosts | E20: 50033 | F20: Oncosts | H20: 2.9
A21: 43180 | B21: HEMMING | C21: Kyle | D21: Subsidies | E21: 50027 | F21: Super | H21: 55.04
A22: 43194
A23: 43194 | B23: HEMMING | C23: Kyle | D23: Earnings | E23: 50007 | F23: Salary Casual | G23: 5 | H23: 289.67
A24: 43194 | B24: HEMMING | C24: Kyle | D24: Oncosts | E24: 50031 | F24: Oncosts | H24: 19.85
A25: 43194 | B25: HEMMING | C25: Kyle | D25: Oncosts | E25: 50032 | F25: Oncosts | H25: 0
A26: 43194 | B26: HEMMING | C26: Kyle | D26: Oncosts | E26: 50033 | F26: Oncosts | H26: 3.62
A27: 43194 | B27: HEMMING | C27: Kyle | D27: Subsidies | E27: 50027 | F27: Super | H27: 0
A28: 43208
A29: 43208 | B29: HEMMING | C29: Kyle | D29: Oncosts | E29: 50032 | F29: Oncosts | H29: 0
A30: 43208 | B30: HEMMING | C30: Kyle | D30: Subsidies | E30: 50027 | F30: Super | H30: 0
A31: 43222
A32: 43222 | B32: HEMMING | C32: Kyle | D32: Oncosts | E32: 50032 | F32: Oncosts | H32: 0
A33: 43222 | B33: HEMMING | C33: Kyle | D33: Subsidies | E33: 50027 | F33: Super | H33: 0
A34: 43222 | B34: HEMMING | C34: Kyle | D34: Earnings | E34: 50002 | F34: Rate P - Other | G34: 40 | H34: 1811.16
A35: 43222 | B35: HEMMING | C35: Kyle | D35: Oncosts | E35: 50018 | F35: Oncosts | H35: 124.05
A36: 43222 | B36: HEMMING | C36: Kyle | D36: Oncosts | E36: 50020 | F36: Oncosts | H36: 11.79
A37: 43222 | B37: HEMMING | C37: Kyle | D37: Oncosts | E37: 50021 | F37: Oncosts | H37: 22.64
A38: 43222 | B38: HEMMING | C38: Kyle | D38: Subsidies | E38: 50016 | F38: Super | H38: 172.06
A39: 43236
A40: 43236 | B40: HEMMING | C40: Kyle | D40: Oncosts | E40: 50032 | F40: Oncosts | H40: 0
A41: 43236 | B41: HEMMING | C41: Kyle | D41: Subsidies | E41: 50027 | F41: Super | H41: 0
A42: 43236 | B42: HEMMING | C42: Kyle | D42: Earnings | E42: 50002 | F42: Rate P - Other | G42: -19 | H42: -860.3
A43: 43236 | B43: HEMMING | C43: Kyle | D43: Oncosts | E43: 50018 | F43: Oncosts | H43: -58.94
A44: 43236 | B44: HEMMING | C44: Kyle | D44: Oncosts | E44: 50020 | F44: Oncosts | H44: -5.6
A45: 43236 | B45: HEMMING | C45: Kyle | D45: Oncosts | E45: 50021 | F45: Oncosts | H45: -10.76
A46: 43236 | B46: HEMMING | C46: Kyle | D46: Subsidies | E46: 50016 | F46: Super | H46: -81.73
A47: 43250
A48: 43250 | B48: HEMMING | C48: Kyle | D48: Oncosts | E48: 50032 | F48: Oncosts | H48: -0.01
A49: 43250 | B49: HEMMING | C49: Kyle | D49: Subsidies | E49: 50027 | F49: Super | H49: -5.3290705e-15
A50: 43250 | B50: HEMMING | C50: Kyle | D50: Earnings | E50: 50002 | F50: Rate P - Other | G50: 4 | H50: 181.12
A51: 43250 | B51: HEMMING | C51: Kyle | D51: Oncosts | E51: 50018 | F51: Oncosts | H51: 12.4
A52: 43250 | B52: HEMMING | C52: Kyle | D52: Oncosts | E52: 50020 | F52: Oncosts | H52: 1.18
A53: 43250 | B53: HEMMING | C53: Kyle | D53: Oncosts | E53: 50021 | F53: Oncosts | H53: 2.26
A54: 43250 | B54: HEMMING | C54: Kyle | D54: Subsidies | E54: 50016 | F54: Super | H54: 17.21
A55: 43264
A56: 43264 | B56: HEMMING | C56: Kyle | D56: Earnings | E56: 50002 | F56: Rate P - Other | G56: 4 | H56: 181.12
A57: 43264 | B57: HEMMING | C57: Kyle | D57: Oncosts | E57: 50018 | F57: Oncosts | H57: 12.4
A58: 43264 | B58: HEMMING | C58: Kyle | D58: Oncosts | E58: 50021 | F58: Oncosts | H58: 2.26
A59: 43278
A60: 43278 | B60: HEMMING | C60: Kyle | D60: Earnings | E60: 50002 | F60: Rate P - Other | G60: 4 | H60: 181.12
A61: 43278 | B61: HEMMING | C61: Kyle | D61: Oncosts | E61: 50018 | F61: Oncosts | H61: 12.4
A62: 43278 | B62: HEMMING | C62: Kyle | D62: Oncosts | E62: 50021 | F62: Oncosts | H62: 2.26
A63: 43292
A64: 43292 | B64: HEMMING | C64: Kyle | D64: Earnings | E64: 50002 | F64: Rate P - Other | G64: 7 | H64: 316.95
A65: 43292 | B65: HEMMING | C65: Kyle | D65: Oncosts | E65: 50018 | F65: Oncosts | H65: 21.71
A66: 43292 | B66: HEMMING | C66: Kyle | D66: Oncosts | E66: 50021 | F66: Oncosts | H66: 3.96
A67: TOTAL | G67: =SUM(G2:G66) -> 83 | H67: =SUM(H2:H66) -> 4950.98 | I67: =SUM(H67/G67) -> 59.650361

Sheet Angelica
A1: Angelica Lopez
B5: Week of 26/02/2018 | C5: Start | D5: Finish | E5: Hrs worked | F5: Total Pay | G5: Description
B6: Monday
B7: Tuesday
B8: Wednesday
B9: Thursday | C9: 0.54166667 | D9: 0.625 | E9: 2
B10: Friday | C10: 0.54166667 | D10: 0.625 | E10: 2
B11: Saturday
B12: Sunday
B16: Week of 05/03/2018 | C16: Start | D16: Finish | E16: Hrs worked | F16: Total Pay | G16: Description
B17: Monday
B18: Tuesday
B19: Wednesday | E19: 3
B20: Thursday | C20: 0.39583333 | D20: 0.45833333 | E20: 1.5
C21: 0.54166667 | D21: 0.625 | E21: 2
B22: Friday
B23: Saturday
B24: Sunday
E25: =SUM(E9:E10,E19:E21) -> 10.5
A27: before this point all work was PAID IN VOUCHERS…
B29: ANTHONY's INPUT | J29: ANGELICA's RECORDED HOURS
L33: Week of 12/03/2018
B34: Week of 12/03/2018 | C34: Start | D34: Finish | E34: Hrs worked | F34: Hrs Paid | G34: Description | H34: Payment received | K34: W5 | L34: Week of 12/03/2018 | M34: Start | N34: Finish | O34: Hrs worked | P34: Payment received
A35: 12 | B35: Monday | K35: 12 | L35: Monday
A36: 13 | B36: Tuesday | C36: 0.375 | D36: 0.5 | E36: 3 | G36: Seaching by courses using different terminology to list the list of statistical courses offered at UC. The whole dataset is complete it | K36: 13 | L36: Tuesday | M36: 0.375 | N36: 0.95833333 | O36: 2 | Q36: Seaching by courses using different terminology to list the list of statistical courses offered at UC. The whole dataset is complete it
A37: 14 | B37: Wednesday | K37: 14 | L37: Wednesday
A38: 15 | B38: Thursday | C38: 0.54166667 | D38: 0.625 | E38: 2 | G38: Regular Drop in | K38: 15 | L38: Thursday | M38: 0.54166667 | N38: 0.125 | O38: 2 | Q38: Regular Drop in
A39: 16 | B39: Friday | C39: 0.375 | D39: 0.5 | E39: 3 | G39: organized files. In dropbox. Reading and organized the whole files and build a dataset of files. | K39: 16 | L39: Friday | M39: 0.375 | N39: 0.95833333 | O39: 2 | P39: 5 | Q39: organized files. In dropbox. Reading and organized the whole files and build a dataset of files. Check face history for discussion
A40: 17 | B40: Saturday | K40: 17 | L40: Saturday
A41: 18 | B41: Sunday | K41: 18 | L41: Sunday
B42: TOTAL | E42: =SUM(E35:E41) -> 8 | F42: Hours submitted | G42: Hours owing
A43: Tuesday 21 March | B43: Payday | E43: =SUM(E35:E39) -> 8 | F43: =SUM(1*Angelica_hist!G3) -> 5 | G43: =SUM(E43-F43) -> 3
B46: Week of 19/03/2018 | C46: Start | D46: Finish | E46: Hrs worked | F46: Hrs Paid | G46: Description | H46: Payment received | K46: W6 | L46: Week of 19/03/2018 | M46: Start | N46: Finish | O46: Hrs worked
A47: 19 | B47: Monday | K47: 19 | L47: Monday
A48: 20 | B48: Tuesday | K48: 20 | L48: Tuesday
A49: 21 | B49: Wednesday | K49: 21 | L49: Wednesday
A50: 22 | B50: Thursday | C50: 0.54166667 | D50: 0.625 | E50: 2 | G50: Regular Drop in | K50: 22 | L50: Thursday | M50: 0.54166667 | N50: 0.125 | O50: 2 | Q50: Regular Drop in
A51: 23 | B51: Friday | C51: 0.375 | D51: 0.45833333 | E51: 2 | G51: Statistical Network project process and possible tasks. In dropbox. | K51: 23 | L51: Friday | M51: 0.375 | N51: 0.45833333 | O51: 2 | P51: 5 | Q51: organized files. In dropbox. Reading and organized the whole files and build a dataset of files.
A52: 24 | B52: Saturday | K52: 24 | L52: Saturday
A53: 25 | B53: Sunday | K53: 25 | L53: Sunday
B54: TOTAL | E54: =SUM(E46:E53) -> 4 | O54: =SUM(O47:O53,O35:O41) -> 10 | P54: =SUM(P35:P53) -> 10
B56: Week of 26/03/2018 | C56: Start | D56: Finish | E56: Hrs worked | F56: Total Pay | G56: Description | K56: W7 | L56: Week of 26/03/2018 | M56: Start | N56: Finish | O56: Hrs worked | P56: Payment PROGRAMMED | Q56: Description
A57: 26 | B57: Monday | C57: 0.375 | D57: 0.41666667 | E57: 1 | G57: meeting with Anthony check face | K57: 26 | L57: Monday | M57: 0.375 | N57: 0.41666667 | O57: 1 | Q57: Meeting with Anthony. Check face history
A58: 27 | B58: Tuesday | K58: 27 | L58: Tuesday
A59: 28 | B59: Wednesday 28 march | K59: 28 | L59: Wednesday
A60: 29 | B60: Thursday | C60: 0.54166667 | D60: 0.625 | E60: 2 | G60: Regular Drop in | K60: 29 | L60: Thursday | M60: 0.54166667 | N60: 0.125 | O60: 2 | Q60: Drop in session
A61: 30 | B61: Friday | C61: 0.375 | D61: 0.45833333 | E61: 2 | G61: Buiding document for stats process. | M61: 0.625 | N61: 0.70833333 | O61: 2 | Q61: Writing Process document
A62: 31 | B62: Saturday | K62: 30 | L62: Friday | P62: 4
A63: 1 | B63: Sunday | K63: 31 | L63: Saturday
B64: TOTAL | E64: =SUM(E57:E63) -> 5 | F64: Hours submitted | G64: Hours owing | K64: 1 | L64: Sunday
A65: Tuesday 4th April | B65: Payday | E65: =SUM(E57:E61) -> 5 | F65: =SUM(1*Angelica_hist!G9) -> 5 | G65: =SUM(E65+G43)-F65 -> 3 | L65: TOTAL | O65: =SUM(O57:O64) -> 5
B67: Week of 02/04/2018 | C67: Start | D67: Finish | E67: Hrs worked | F67: Total Pay | G67: Description | H67: Where did this come from?
A68: 2 | B68: Monday
A69: 3 | B69: Tuesday 3 April
A70: 4 | B70: Wednesday
A71: 5 | B71: Thursday | C71: 0.54166667 | D71: 0.125 | E71: 2 | G71: Drop in session
A72: 6 | C72: 0.625 | D72: 0.70833333 | E72: 2 | G72: Writing Process document
A73: 7 | B73: Friday
A74: 8 | B74: Saturday
A75: 9 | B75: Sunday
B76: TOTAL | E76: =SUM(E68:E75) -> 4
B80: Week of 02/04/2018 | C80: Start | D80: Finish | E80: Hrs worked | F80: Total Pay | G80: Description | K80: W8 | L80: Week of 02/04/2018 | M80: Start | N80: Finish | O80: Hrs worked | P80: Total Pay | Q80: Description
B81: Monday | G81: Easter monday | K81: 2 | L81: Monday | Q81: Easter monday
B82: Tuesday | K82: 3 | L82: Tuesday
B83: Wednesday | K83: 4 | L83: Wednesday
B84: Thursday | C84: 0.5 | D84: 0.54166667 | E84: 1 | G84: meeting Anthony, set up email and tasks | K84: 5 | L84: Thursday | M84: 0.5 | N84: 0.54166667 | O84: 1 | Q84: meeting Anthony, set up email and tasks
C85: 0.54166667 | D85: 0.125 | E85: 2 | G85: Drop in session | M85: 0.54166667 | N85: 0.125 | O85: 2 | Q85: Drop in session
C86: 0.75 | D86: 0.83333333 | E86: 2 | G86: Coding Anna meta analysis | M86: 0.75 | N86: 0.83333333 | O86: 2 | Q86: Coding Anna meta analysis
B87: Friday | C87: 0.70833333 | D87: 0.75 | E87: 1 | G87: Emails and fixing plots for Anna | K87: 6 | L87: Friday | M87: 0.70833333 | N87: 0.75 | O87: 1 | P87: 2.5 | Q87: Emails and fixing plots for Anna
B88: Saturday | C88: 0.41666667 | D88: 0.47916667 | E88: 1.5 | G88: Emails, follow up (Abel Zhou, conversation with Anna) | K88: 7 | L88: Saturday | M88: 0.41666667 | N88: 0.47916667 | O88: 1.5 | Q88: Emails, follow up (Abel Zhou, conversation with Anna)
B89: Sunday | K89: 8 | L89: Sunday
B90: TOTAL | E90: =SUM(E81:E89) -> 7.5 | G90: minus5previous pay | L90: TOTAL | O90: =SUM(O81:O89) -> 7.5
B93: Week of 09/04/2018 | C93: Start | D93: Finish | E93: Hrs worked | F93: Total Pay | G93: Description | K93: W9 | L93: Week of 09/04/2018 | M93: Start | N93: Finish | O93: Hrs worked | P93: Total Pay | Q93: Description
B94: Monday | C94: 0.45833333 | D94: 0.54166667 | E94: 2 | G94: Individual consultation Anna | K94: 9 | L94: Monday | M94: 0.45833333 | N94: 0.54166667 | O94: 2 | Q94: Individual consultation Anna
C95: 0.58333333 | D95: 15:30 PM | E95: 1.5 | G95: Admin, answering and writing emails (Sam Kosari and Sucholana) | M95: 0.58333333 | N95: 0.66666667 | O95: 2 | Q95: Admin, answering and writing emails (Sam Kosari and Sucholana)
B96: Tuesday 17payday | K96: 10 | L96: Tuesday
B97: Wednesday | K97: 11 | L97: Wednesday
B98: Thursday | C98: 0.041666667 | D98: 0.125 | E98: 2 | G98: Drop in session | K98: 12 | L98: Thursday | M98: 0.041666667 | N98: 0.125 | O98: 2 | Q98: Drop in session
B99: Friday | C99: 0.125 | D99: 0.16666667 | E99: 1 | G99: Meeting Anthony | M99: 0.125 | N99: 0.16666667 | O99: 1 | Q99: Meeting Anthony
B100: Saturday | F100: 3.5 | K100: 13 | L100: Friday | P100: 3.5
B101: Sunday | K101: 14 | L101: Saturday
B102: TOTAL | E102: =SUM(E94:E101) -> 6.5 | K102: 15 | L102: Sunday
A103: MISSED | B103: TOTAL | E103: =SUM(E94:E101,E81:E89) -> 14 | F103: Hours submitted | G103: hours owing | L103: TOTAL | O103: =SUM(O94:O102) -> 7
B104: Payday | E104: MISSED | F104: n/a | G104: =SUM(E103+G65) -> 17 | H104: This includes missed hours from this pay | O104: =SUM(O65,O90,O103) -> 19.5 | P104: =SUM(P62,P87,P100) -> 10
B106: Week of 16/04/2018 | C106: Start | D106: Finish | E106: Hrs worked | F106: Total Pay | G106: Description | K106: W10 | L106: Week of 16/04/2018 | M106: Start | N106: Finish | O106: Hrs worked | P106: Total Pay | Q106: Description
B107: Monday | C107: 11.30 am | D107: 0.5 | E107: 0.5 | G107: Response emails, references to Anna and ackwoledgement | K107: 16 | L107: Monday | M107: 11.30 am | N107: 0.5 | O107: 0.5 | Q107: Response emails, references to Anna and ackwoledgement
B108: Tuesday | K108: 17 | L108: Tuesday
B109: Wednesday | K109: 18 | L109: Wednesday
B110: Thursday | C110: 0.5 | D110: 0.041666667 | E110: 1 | G110: Meeting Anthony | K110: 19 | L110: Thursday | M110: 0.5 | N110: 0.041666667 | O110: 1 | Q110: Meeting Anthony
C111: 0.041666667 | D111: 0.125 | E111: 2 | G111: Drop in session | M111: 0.041666667 | N111: 0.125 | O111: 2 | Q111: Drop in session
C112: 0.125 | D112: 0.14583333 | E112: 0.5 | G112: Meeting with Kym | M112: 0.125 | N112: 0.14583333 | O112: 0.5 | Q112: Meeting with Kym
B113: Friday | K113: 20 | L113: Friday
B117: Saturday | K117: 21 | L117: Saturday
B118: Sunday | C118: 0.54166667 | D118: 0.64583333 | E118: 2.5 | G118: First report Kym, see the email | K118: 22 | L118: Sunday | M118: 0.54166667 | N118: 0.64583333 | O118: 2.5 | Q118: First report Kym, see the email
B119: TOTAL | E119: =SUM(E107:E118) -> 6.5 | L119: TOTAL | O119: =SUM(O107:O118) -> 6.5
A120: END CONTRACT START A NEW ONE
B122: Week of 23/04/2018 | C122: Start | D122: Finish | E122: Hrs worked | F122: Total Pay | G122: Description | K122: W11 | L122: Week of 23/04/2018 | M122: Start | N122: Finish | O122: Hrs worked | P122: Total Pay | Q122: Description
A123: 23 | B123: Monday | C123: 11.30 am | D123: 0.5 | E123: 0.5 | G123: Update dataset of drop-in sessions and emails. | K123: 23 | L123: Monday | M123: 11.30 am | N123: 0.5 | O123: 0.5 | Q123: Update dataset of drop-in sessions and emails.
C124: 4:30pm | D124: 0.70833333 | E124: 0.5 | G124: Response to Michelle Montgomery about her Logistic regression problem | M124: 4:30pm | N124: 0.70833333 | O124: 0.5 | Q124: Response to Michelle Montgomery about her Logistic regression problem
A125: 24 | B125: Tuesday | C125: 0.625 | D125: 0.70833333 | E125: 2 | G125: Second response to kym, analysis of survey II part | K125: 24 | L125: Tuesday | M125: 0.625 | N125: 0.70833333 | O125: 2 | Q125: Second response to kym, analysis of survey II part
...

Sheet Margarita
A1: Margarita | B1: ANTHONY's INPUT
A2: NEW CONTRACT
A4: END CONTRACT START A NEW ONE | B4: Week of 05/03/2018 | C4: Start | D4: Finish | E4: Hrs worked | F4: Total Pay | G4: Description | I4: Stage one | J4: 1st February - 13th May | O4: Week of 05/03/2018 | P4: Start | Q4: Finish | R4: Hrs worked | S4: Total Pay | T4: Description
A5: 4 | B5: Monday | C5: 0.625 | D5: 0.66666667 | E5: 1 | G5: Asking about job situation and lining up timetables | I5: Stage two | J5: 14th May - 1 July | O5: Monday | P5: 0.625 | Q5: 0.66666667 | R5: 1 | T5: Asking about job situation and lining up timetables
A6: 5 | B6: Tuesday | I6: Stage three: Current | J6: 2 July 2018 - 1st September 2018 | O6: Tuesday
A7: 6 | B7: Wednesday | C7: 0.625 | D7: 0.66666667 | E7: 1 | G7: Meeting for contracts etc | O7: Wednesday | P7: 0.625 | Q7: 0.66666667 | R7: 1 | T7: Meeting for contracts etc
A8: 7 | B8: Thursday | O8: Thursday
A9: 8 | O9: Friday
A10: 9 | B10: Friday | O10: Saturday
A11: 10 | B11: Saturday | O11: Sunday
A12: 11 | B12: Sunday | O12: TOTAL | R12: =SUM(R5:R11) -> 2
B13: TOTAL | E13: =SUM(E5:E12) -> 2
B15: Week of 12/03/2018 | C15: Start | D15: Finish | E15: Hrs worked | F15: Hrs Paid | G15: Description | H15: Payment received | O15: Week of 12/03/2018 | P15: Start | Q15: Finish | R15: Hrs worked | S15: Total Pay | T15: Description
A16: 12 | B16: Monday | O16: Monday
A17: 13 | B17: Tuesday | O17: Tuesday
A18: 14 | B18: Wednesday | O18: Wednesday
A19: 15 | B19: Thursday | O19: Thursday
A20: 16 | B20: Friday | O20: Friday
A21: 17 | B21: Saturday | O21: Saturday
A22: 18 | B22: Sunday | O22: Sunday
B23: TOTAL | E23: =SUM(E16:E22) -> 0 | F23: Hours submitted | G23: Hours owing | O23: TOTAL
A24: Tuesday 21 March | B24: Payday | E24: =SUM(E23+E13) -> 2 | F24: =SUM(1*Marg_hist!G3) -> 5 | G24: =SUM(E24+G13)-F24 -> -3
B27: Week of 19/03/2018 | C27: Start | D27: Finish | E27: Hrs worked | F27: Hrs Paid | G27: Description | H27: Payment received | O27: Week of 19/03/2018 | P27: Start | Q27: Finish | R27: Hrs worked | S27: Total Pay | T27: Description
A28: 19 | B28: Monday | O28: Monday
A29: 20 | B29: Tuesday | O29: Tuesday
A30: 21 | B30: Wednesday | O30: Wednesday
A31: 22 | B31: Thursday | O31: Thursday
A32: 23 | B32: Friday | O32: Friday
A33: 24 | B33: Saturday | O33: Saturday
A34: 25 | B34: Sunday | O34: Sunday
B35: TOTAL | E35: =SUM(E27:E34) -> 0 | O35: TOTAL
O36: PAID | R36: 8hrs owing | S36: 10hrs paid
B37: Week of 26/03/2018 | C37: Start | D37: Finish | E37: Hrs worked | F37: Total Pay | G37: Description | O37: Week of 26/03/2018 | P37: Start | Q37: Finish | R37: Hrs worked | S37: Total Pay | T37: Description
A38: 26 | B38: Monday | O38: Monday
A39: 27 | B39: Tuesday | O39: Tuesday
A40: 28 | B40: Wednesday 28 march | O40: Wednesday
A41: 29 | B41: Thursday | C41: 0.5 | D41: 0.66666667 | E41: 4 | G41: Meeting / admin / emails | O41: Thursday | P41: 0.5 | Q41: 0.66666667 | R41: 4 | T41: Meeting / admin / emails
A42: 30 | B42: Friday | O42: Friday
A43: 31 | B43: Saturday | O43: Saturday
A44: 1 | B44: Sunday | O44: Sunday
B45: TOTAL | E45: =SUM(E37:E44) -> 4 | F45: Hours submitted | G45: Hours owing | O45: TOTAL | R45: =SUM(R38:R44) -> 4
A46: Tuesday 3 April | B46: Payday | E46: =SUM(E38:E44,E28:E34) -> 4 | F46: =SUM(Marg_hist!G9) -> 5 | G46: =SUM(E46+G24)-F46 -> -4
B48: Week of 02/04/2018 | C48: Start | D48: Finish | E48: Hrs worked | F48: Total Pay | G48: Description | O48: Week of 02/04/2018 | P48: Start | Q48: Finish | R48: Hrs worked | S48: Total Pay | T48: Description
A49: 2 | B49: Monday | G49: Easter monday | O49: Monday | T49: Easter monday
A50: 3 | B50: Tuesday | O50: Tuesday
A51: 4 | B51: Wednesday | O51: Wednesday
A52: 5 | B52: Thursday | O52: Thursday
A53: 6 | B53: Friday | C53: 0.39583333 | D53: 0.47916667 | E53: 2 | G53: Meeting / admin / emails | O53: Friday | P53: 0.39583333 | Q53: 0.47916667 | R53: 2 | T53: Meeting / admin / emails
A54: 7 | B54: Saturday | C54: 0.5 | D54: 0.54166667 | E54: 1 | G54: Meeting with Angelica | O54: Saturday | P54: 0.5 | Q54: 0.54166667 | R54: 1 | T54: Meeting with Angelica
A55: 8 | B55: Sunday | C55: 0.5 | D55: 0.58333333 | E55: 2 | G55: Survey for drop-in | O55: Sunday | P55: 0.5 | Q55: 0.58333333 | R55: 2 | T55: Survey for drop-in
B56: TOTAL | E56: =SUM(E49:E55) -> 5 | O56: TOTAL | R56: =SUM(R49:R55) -> 5 | T56: (9 hours worked, 0 owing)
O59: Week of 09/04/2018 | P59: Start | Q59: Finish | R59: Hrs worked | S59: Total Pay | T59: Description
O60: Monday
B61: Week of 09/04/2018 | C61: Start | D61: Finish | E61: Hrs worked | F61: Total Pay | G61: Description | O61: Tuesday | P61: 0.60416667 | Q61: 0.625 | R61: 0.5 | S61: Fayah statistics one-on-one
A62: 9 | B62: Monday | P62: 0.625 | Q62: 0.64583333 | R62: 0.5 | S62: Admin meeting with Anthony
A63: 10 | B63: Tuesday | C63: 0.60416667 | D63: 0.625 | E63: 0.5 | G63: Fayah statistics one-on-one | O63: Wednesday
C64: 0.625 | D64: 0.64583333 | E64: 0.5 | G64: Admin meeting with Anthony | O64: Thursday | P64: 0.41666667 | Q64: 0.4375 | R64: 0.5 | S64: survey
A65: 11 | B65: Wednesday | P65: 0.58333333 | Q65: 0.64583333 | R65: 1.5 | S65: admin emails
A66: 12 | B66: Thursday | C66: 0.41666667 | D66: 0.4375 | E66: 0.5 | G66: survey | O66: Friday
A67: 13 | B67: Friday | C67: 0.58333333 | D67: 0.64583333 | E67: 1.5 | G67: admin emails | O67: TOTAL | R67: =SUM(R60:R66) -> 3 | S67: minus2hrs from last week
A68: 14 | B68: Saturday | O68: PAID | R68: =SUM(R67+R56+R45) -> 12 | S68: 8hrs paid | T68: (5 hours worked)
A69: 15 | B69: Sunday | R69: 4hrs owing
A70: MISSED | B70: TOTAL | E70: =SUM(E62:E69) -> 3 | F70: Hours submitted | G70: Hours owing | O70: Saturday
B71: Payday | D71: MISSED | E71: =SUM(E56,E70) -> 8 | F71: n/a | G71: =SUM(E70+G46+E56) -> 4 | H71: Owe you 4hrs | O71: Sunday
O72: TOTAL
B74: Week of 16/04/2018 | C74: Start | D74: Finish | E74: Hrs worked | F74: Total Pay | G74: Description | O74: Week of 16/04/2018 | P74: Start | Q74: Finish | R74: Hrs worked | S74: Total Pay | T74: Description
A75: 16 | B75: Monday | C75: 0.29166667 | D75: 9;00 | E75: 2 | G75: mails in folders | O75: Monday | P75: 0.29166667 | Q75: 9;00 | R75: 2 | S75: mails in folders
A76: 17 | B76: Tuesday | O76: Tuesday
A77: 18 | B77: Wednesday | O77: Wednesday
A78: 19 | B78: Thursday | C78: 0.40277778 | D78: 0.48611111 | E78: 2 | G78: shut up and write | O78: Thursday | P78: 0.40277778 | Q78: 0.48611111 | R78: 2 | S78: shut up and write
A79: 20 | B79: Friday | O79: Friday
A80: 21 | B80: Saturday | C80: 0.41666667 | D80: 0.45833333 | E80: 1 | G80: admin | O80: Saturday | P80: 0.41666667 | Q80: 0.45833333 | R80: 1 | S80: admin
A81: 22 | B81: Sunday | O81: Sunday
B82: TOTAL | E82: =SUM(E75:E81) -> 5 | O82: TOTAL | R82: 5
B85: Week of 23/04/2018 | C85: Start | D85: Finish | E85: Hrs worked | F85: Total Pay | G85: Description | O85: Week of 23/04/2018 | P85: Start | Q85: Finish | R85: Hrs worked | S85: Total Pay | T85: Description
A86: 23 | B86: Monday | C86: 0.375 | D86: 0.45833333 | E86: 2 | G86: fayha | O86: Monday | P86: 0.375 | Q86: 0.45833333 | R86: 2 | S86: fayha
A87: 24 | B87: Tuesday | O87: Tuesday
A88: 25 | B88: Wednesday | O88: Wednesday
A89: 26 | B89: Thursday | C89: 0.375 | D89: 0.41666667 | E89: 1 | G89: florence | O89: Thursday | P89: 0.375 | Q89: 0.41666667 | R89: 1 | S89: florence
A90: 27 | B90: Friday | O90: Friday
A91: 28 | B91: Saturday | C91: 0.41666667 | D91: 0.45833333 | E91: 1 | G91: admin emails | O91: Saturday | P91: 0.41666667 | Q91: 0.45833333 | R91: 1 | S91: admin emails
A92: 29 | B92: Sunday | O92: Sunday
B93: TOTAL | E93: =SUM(E84:E92) -> 4 | F93: Hours submitted | G93: Hours owing | H93: After this Margie owes network 5hrs | O93: TOTAL | R93: 4 | T93: (owing 1)
A94: Tuesday 2nd May 2018 | B94: Payday | E94: =SUM(E82,E93) -> 9 | F94: =SUM(1*Marg_hist!G15) -> 18 | G94: =SUM(E94 + G71)-F94 -> -5 | H94: Behind including pay missed from previous pay cycle
B96: Week of 30/04/2018 | C96: Start | D96: Finish | E96: Hrs worked | F96: Total Pay | G96: Description | I96: Stage one | J96: 1st February - 13th May | O96: Week of 30/04/2018 | P96: Start | Q96: Finish | R96: Hrs worked | S96: Total Pay | T96: Description
A97: 30 | B97: Monday | I97: Stage two | J97: 14th May - 1 July | O97: Monday
A98: 1 | B98: Tuesday | C98: 0.58333333 | D98: 0.625 | E98: 1 | G98: Fayha | I98: Stage three: Current | J98: 2 July 2018 - 1st September 2018 | O98: Tuesday | P98: 0.58333333 | Q98: 0.625 | R98: 1 | S98: Fayha
A99: 2 | B99: Wednesday | O99: Wednesday
A100: 3 | B100: Thursday | O100: Thursday
A101: 4 | B101: Friday | C101: 0.41666667 | D101: 0.45833333 | E101: 1 | G101: admin/emails | O101: Friday | P101: 0.41666667 | Q101: 0.45833333 | R101: 1 | S101: admin/emails
A102: 5 | B102: Saturday | O102: Saturday
A103: 6 | B103: Sunday | O103: Sunday
B104: TOTAL | E104: 2 | O104: TOTAL | R104: 2 | T104: (owing 3)
B107: Week of 07/05/2018 | C107: Start | D107: Finish | E107: Hrs worked | F107: Total Pay | G107: Description | O107: Week of 07/05/2018 | P107: Start | Q107: Finish | R107: Hrs worked | S107: Total Pay | T107: Description
A108: 7 | B108: Monday | O108: Monday
A109: 8 | B109: Tuesday | O109: Tuesday
A110: 9 | B110: Wednesday | C110: 0.5625 | D110: 0.60416667 | E110: 1 | G110: Fayha meeting | O110: Wednesday | P110: 0.5625 | Q110: 0.60416667 | R110: 1 | S110: Fayha meeting
A111: 10 | B111: Thursday | O111: Thursday
A112: 11 | B112: Friday | C112: 0.41666667 | D112: 0.45833333 | E112: 1 | G112: admin/emails | O112: Friday | P112: 0.41666667 | Q112: 0.45833333 | R112: 1 | S112: admin/emails
A113: 12 | B113: Saturday | O113: Saturday
...

Sheet Margarita (2)
A1: Margarita
A8: ANTHONY's INPUT
A9: NEW CONTRACT
A11: END CONTRACT START A NEW ONE | B11: Week of 05/03/2018 | C11: Start | D11: Finish | E11: Hrs worked | F11: Total Pay | G11: Description | I11: Stage one | J11: 1st February - 13th May
A12: 4 | B12: Monday | C12: 0.625 | D12: 0.66666667 | E12: 1 | G12: Asking about job situation and lining up timetables | I12: Stage two | J12: 14th May - 1 July
A13: 5 | B13: Tuesday | I13: Stage three: Current | J13: 2 July 2018 - 1st September 2018
A14: 6 | B14: Wednesday | C14: 0.625 | D14: 0.66666667 | E14: 1 | G14: Meeting for contracts etc
A15: 7 | B15: Thursday
A16: 8
A17: 9 | B17: Friday
A18: 10 | B18: Saturday
A19: 11 | B19: Sunday
B20: TOTAL | E20: =SUM(E12:E19) -> 2
B22: Week of 12/03/2018 | C22: Start | D22: Finish | E22: Hrs worked | F22: Hrs Paid | G22: Description | H22: Payment received
A23: 12 | B23: Monday
A24: 13 | B24: Tuesday
A25: 14 | B25: Wednesday
A26: 15 | B26: Thursday
A27: 16 | B27: Friday
A28: 17 | B28: Saturday
A29: 18 | B29: Sunday
B30: TOTAL | E30: =SUM(E23:E29) -> 0 | F30: Hours submitted | G30: Hours owing
A31: Tuesday 21 March | B31: Payday | E31: =SUM(E30+E20) -> 2 | F31: =SUM(1*[3]Marg_hist!G3) -> 5 | G31: =SUM(E31+G20)-F31 -> -3
A32: 43180
B34: Week of 19/03/2018 | C34: Start | D34: Finish | E34: Hrs worked | F34: Hrs Paid | G34: Description | H34: Payment received
A35: 19 | B35: Monday
A36: 20 | B36: Tuesday
A37: 21 | B37: Wednesday
A38: 22 | B38: Thursday
A39: 23 | B39: Friday
A40: 24 | B40: Saturday
A41: 25 | B41: Sunday
B42: TOTAL | E42: =SUM(E34:E41) -> 0
B44: Week of 26/03/2018 | C44: Start | D44: Finish | E44: Hrs worked | F44: Total Pay | G44: Description
A45: 26 | B45: Monday
A46: 27 | B46: Tuesday
A47: 28 | B47: Wednesday 28 march
A48: 29 | B48: Thursday | C48: 0.5 | D48: 0.66666667 | E48: 4 | G48: Meeting / admin / emails
A49: 30 | B49: Friday
A50: 31 | B50: Saturday
A51: 1 | B51: Sunday
B52: TOTAL | E52: =SUM(E44:E51) -> 4 | F52: Hours submitted | G52: Hours owing
A53: Tuesday 3 April | B53: Payday | E53: =SUM(E45:E51,E35:E41) -> 4 | F53: =SUM([3]Marg_hist!G9) -> 5 | G53: =SUM(E53+G31)-F53 -> -4
A54: 43194
B55: Week of 02/04/2018 | C55: Start | D55: Finish | E55: Hrs worked | F55: Total Pay | G55: Description
A56: 2 | B56: Monday | G56: Easter monday
A57: 3 | B57: Tuesday
A58: 4 | B58: Wednesday
A59: 5 | B59: Thursday
A60: 6 | B60: Friday | C60: 0.39583333 | D60: 0.47916667 | E60: 2 | G60: Meeting / admin / emails
A61: 7 | B61: Saturday | C61: 0.5 | D61: 0.54166667 | E61: 1 | G61: Meeting with Angelica
A62: 8 | B62: Sunday | C62: 0.5 | D62: 0.58333333 | E62: 2 | G62: Survey for drop-in
B63: TOTAL | E63: =SUM(E56:E62) -> 5
B68: Week of 09/04/2018 | C68: Start | D68: Finish | E68: Hrs worked | F68: Total Pay | G68: Description
A69: 9 | B69: Monday
A70: 10 | B70: Tuesday | C70: 0.60416667 | D70: 0.625 | E70: 0.5 | G70: Fayah statistics one-on-one
C71: 0.625 | D71: 0.64583333 | E71: 0.5 | G71: Admin meeting with Anthony
A72: 11 | B72: Wednesday
A73: 12 | B73: Thursday | C73: 0.41666667 | D73: 0.4375 | E73: 0.5 | G73: survey
A74: 13 | B74: Friday | C74: 0.58333333 | D74: 0.64583333 | E74: 1.5 | G74: admin emails
A75: 14 | B75: Saturday
A76: 15 | B76: Sunday
A77: MISSED | B77: TOTAL | E77: =SUM(E69:E76) -> 3 | F77: Hours submitted | G77: Hours owing
B78: Payday | D78: MISSED | E78: =SUM(E63,E77) -> 8 | F78: n/a | G78: =SUM(E77+G53+E63) -> 4 | H78: Owe you 4hrs
B81: Week of 16/04/2018 | C81: Start | D81: Finish | E81: Hrs worked | F81: Total Pay | G81: Description
A82: 16 | B82: Monday | C82: 0.29166667 | D82: 9;00 | E82: 2 | G82: mails in folders
A83: 17 | B83: Tuesday
A84: 18 | B84: Wednesday
A85: 19 | B85: Thursday | C85: 0.40277778 | D85: 0.48611111 | E85: 2 | G85: shut up and write
A86: 20 | B86: Friday
A87: 21 | B87: Saturday | C87: 0.41666667 | D87: 0.45833333 | E87: 1 | G87: admin
A88: 22 | B88: Sunday
B89: TOTAL | E89: =SUM(E82:E88) -> 5
B92: Week of 23/04/2018 | C92: Start | D92: Finish | E92: Hrs worked | F92: Total Pay | G92: Description
A93: 23 | B93: Monday | C93: 0.375 | D93: 0.45833333 | E93: 2 | G93: fayha
A94: 24 | B94: Tuesday
A95: 25 | B95: Wednesday
A96: 26 | B96: Thursday | C96: 0.375 | D96: 0.41666667 | E96: 1 | G96: florence
A97: 27 | B97: Friday
A98: 28 | B98: Saturday | C98: 0.41666667 | D98: 0.45833333 | E98: 1 | G98: admin emails
A99: 29 | B99: Sunday
B100: TOTAL | E100: =SUM(E91:E99) -> 4 | F100: Hours submitted | G100: Hours owing | H100: After this Margie owes network 5hrs
A101: Tuesday 2nd May 2018 | B101: Payday | E101: =SUM(E89,E100) -> 9 | F101: =SUM(1*[3]Marg_hist!G15) -> 18 | G101: =SUM(E101 + G78)-F101 -> -5 | H101: Behind including pay missed from previous pay cycle
A102: 43222
B103: Week of 30/04/2018 | C103: Start | D103: Finish | E103: Hrs worked | F103: Total Pay | G103: Description | I103: Stage one | J103: 1st February - 13th May
A104: 30 | B104: Monday | I104: Stage two | J104: 14th May - 1 July
A105: 1 | B105: Tuesday | C105: 0.58333333 | D105: 0.625 | E105: 1 | G105: Fayha | I105: Stage three: Current | J105: 2 July 2018 - 1st September 2018
A106: 2 | B106: Wednesday
A107: 3 | B107: Thursday
A108: 4 | B108: Friday | C108: 0.41666667 | D108: 0.45833333 | E108: 1 | G108: admin/emails
A109: 5 | B109: Saturday
A110: 6 | B110: Sunday
B111: TOTAL | E111: 2
B114: Week of 07/05/2018 | C114: Start | D114: Finish | E114: Hrs worked | F114: Total Pay | G114: Description
A115: 7 | B115: Monday
A116: 8 | B116: Tuesday
A117: 9 | B117: Wednesday | C117: 0.5625 | D117: 0.60416667 | E117: 1 | G117: Fayha meeting
A118: 10 | B118: Thursday
A119: 11 | B119: Friday | C119: 0.41666667 | D119: 0.45833333 | E119: 1 | G119: admin/emails
A120: 12 | B120: Saturday
...

Sheet Kyle
A1: Kyle Hemming
A2: Weekly roster | L2: Stock take 17/07/2018
B3: Start | C3: Finish | D3: Hrs worked | E3: Total Pay | F3: Description | M3: Hrs Paid | N3: Estimated pay | O3: Cash received | P3: Difference | Q3: Description
A4: Monday | G4: Kyle has been doing the drop-in sessions from the very beginning of the statistics network in 2017. There has been mininal variation in the timesheets or workload other than during transistion periods. | L4: Trial
A5: Tuesday | L5: 2months
A6: Wednesday | L6: 6months
A7: Thursday | B7: 0.54166667 | C7: 0.125 | D7: 2 | F7: Drop-in session | L7: July….
A8: Friday
A9: Saturday
A10: Sunday
A11: TOTAL | D11: 2
A14: Submit paper forms | B14: Submit electronic | C14: Payday | D14: Hrs worked | E14: Hrs submitted | F14: Hrs paid
A15: Previous trial period……
C18: 11th January 2018 | D18: 4
C19: 25th January 2018 | D19: 4 | E19: =SUM(Kyle_hist!G3) -> 6.5
C20: 8th February 2018 | D20: 4 | E20: =SUM(Kyle_hist!G7) -> 21.5 | G20: Back pay
C21: 22nd February 2018 | D21: 4
C22: 8th March 2018 | D22: 4 | E22: =SUM(Kyle_hist!G13) -> 6
C23: 22nd March 2018 | D23: 4 | E23: =SUM(Kyle_hist!G17) -> 4
C24: 5th April 2018 | D24: 4 | E24: =SUM(Kyle_hist!G23) -> 5
C25: 19th April 2018 | D25: 4 | E25: =SUM(Kyle_hist!G9) -> 0
C26: 3rd May 2018 | D26: 4 | E26: =SUM(Kyle_hist!G34) -> 40 | G26: Pay screw-up
C27: 17th May 2018 | D27: 2 | E27: =SUM(Kyle_hist!G42) -> -19 | G27: Pay screw-up
C28: 31st May 2018 | D28: 4 | E28: =SUM(Kyle_hist!G50) -> 4
C29: 14th June 2018 | D29: 4 | E29: =SUM(Kyle_hist!G56) -> 4
C30: 27th June 2018 | D30: 4 | E30: =SUM(Kyle_hist!G60) -> 4
C31: 11th July 2018 | D31: 4 | E31: =SUM(Kyle_hist!G64) -> 7 | G31: Shut-up and write too…??
C32: 26th July 2018
C33: 9th August 2018
C34: 23rd August 2018
C35: 6th September 2018
C36: 20th September 2018
C37: 4th October 2018
C38: 18th October 2018
C39: 1st November 2018
C40: 15th Novermber 2018
C41: 29th November 2018
C42: 13th December 2018
C43: 27th December 2018
A44: TOTALS | C44: TOTAL | E44: =SUM(E18:E43) -> 83
D45: =SUM(D18:D43) -> 54 | E45: =SUM(E44-E20-3) -> 58.5 | G45: Back pay difference
A48: NEW CONTRACT July 1st - Sept 1st 2018
A50: Proposed hours | N50: Confirmed hours
A51: END CONTRACT START A NEW ONE | B51: Week of 09/07/2018 | C51: Start | D51: Finish | E51: Hrs worked | F51: Total Pay | G51: Description | O51: Week of 9/07/2018 | P51: Start | Q51: Finish | R51: Hrs worked | S51: Total Pay | T51: Description
A52: 9 | B52: Monday | N52: 9 | O52: Monday
A53: 10 | B53: Tuesday | N53: 10 | O53: Tuesday
A54: 11 | B54: Wednesday | N54: 11 | O54: Wednesday
A55: 12 | B55: Thursday | C55: 0.54166667 | D55: 0.625 | E55: 2 | N55: 12 | O55: Thursday
A57: 13 | B57: Friday | N57: 13 | O57: Friday
A58: 14 | B58: Saturday | N58: 14 | O58: Saturday
A59: 15 | B59: Sunday | N59: 15 | O59: Sunday
B60: TOTAL | E60: =SUM(E51:E59) -> 2 | O60: TOTAL | R60: =SUM(R52:R59) -> 0
B63: Week of 16/07/2018 | C63: Start | D63: Finish | E63: Hrs worked | F63: Total Pay | G63: Description | O63: Week of 16/07/2018 | P63: Start | Q63: Finish | R63: Hrs worked | S63: Total Pay | T63: Description
A64: 16 | B64: Monday | N64: 16 | O64: Monday
A65: 17 | B65: Tuesday | N65: 17 | O65: Tuesday
A66: 18 | B66: Wednesday | N66: 18 | O66: Wednesday
A67: 19 | B67: Thursday | C67: 0.54166667 | D67: 0.625 | E67: 2 | N67: 19 | O67: Thursday
A69: 20 | B69: Friday | N69: 20 | O69: Friday
A70: 21 | B70: Saturday | N70: 21 | O70: Saturday
A71: 22 | B71: Sunday | N71: 22 | O71: Sunday
B72: TOTAL | E72: =SUM(E63:E71) -> 2 | O72: TOTAL | R72: =SUM(R64:R71) -> 0
B73: Payday | O73: Payday
A75: 23-29 July 2018 | B75: WS=W1 | C75: Monday | D75: Tuesday | E75: Wednesday | F75: Thursday | G75: Friday | H75: Saturday | I75: Sunday | J75: Total
B76: Anthony | D76: 4 | G76: 4 | J76: =SUM(C76:I76) -> 8 | K76: NOTE: Must have timesheet to be pay this by Monday 30th | O76: Week of 23/07/2018 | P76: Start | Q76: Finish | R76: Hrs worked | S76: Total Pay | T76: Description
C77: 9am - 5pm office (3C3) | N77: 23 | O77: Monday
B78: Margarita | C78: 2 | D78: 4 | E78: RDO | F78: 7 | G78: 2 | J78: =SUM(C78:I78) -> 15 | N78: 24 | O78: Tuesday
C79: One-on-one | F79: 9am - 4.30pm (30min break) | G79: One-on-one | N79: 25 | O79: Wednesday
B80: Angelica | C80: RDO | D80: RDO | E80: RDO | F80: RDO | G80: RDO | H80: 5hrs over weekend or evenings with previous researchers | J80: 5 | N80: 26 | O80: Thursday
N81: 27 | O81: Friday
B82: Kyle | C82: RDO | D82: RDO | E82: RDO | F82: 2 | G82: RDO | J82: =SUM(C82:I82) -> 2 | N82: 28 | O82: Saturday
F83: Drop-in session | N83: 29 | O83: Sunday
B84: Researcher development | J84: =SUM(C84:I84) -> 0 | O84: TOTAL | R84: =SUM(R76:R83) -> 0
B85: Total | C85: 2 | D85: 4 | E85: 2 | F85: 7 | G85: 4 | J85: =SUM(J76:J84) -> 30
A88: 30 July-5 August 2018 | B88: WS=W2 | C88: Monday | D88: Tuesday | E88: Wednesday | F88: Thursday | G88: Friday | H88: Saturday | I88: Sunday | J88: Total
B89: Anthony | D89: 4 | G89: 4 | J89: =SUM(C89:I89) -> 8 | K89: NOTE: Must have timesheet to be pay this by Monday 6th
C90: 9am - 5pm office (3C3) | O90: Week of 30/07/2018 | P90: Start | Q90: Finish | R90: Hrs worked | S90: Total Pay | T90: Description
B91: Margarita | C91: 2 | D91: 4 | E91: RDO | F91: 7 | G91: 2 | J91: =SUM(C91:I91) -> 15 | N91: 30 | O91: Monday
C92: One-on-one | F92: 9am - 4.30pm (30min break) | G92: One-on-one | N92: 31 | O92: Tuesday
B93: Angelica | C93: RDO | D93: RDO | E93: RDO | F93: RDO | G93: RDO | H93: 2hrs over weekend or evenings with previous researchers | J93: 2 | N93: 1 | O93: Wednesday
N94: 2 | O94: Thursday
B95: New Staff 1 | F95: 2 | J95: 2 | N95: 3 | O95: Friday
F96: Drop-in session | N96: 4 | O96: Saturday
B97: Kyle | C97: RDO | D97: RDO | E97: RDO | F97: 2 | G97: RDO | J97: =SUM(C97:I97) -> 2 | N97: 5 | O97: Sunday
F98: Drop-in session | O98: TOTAL | R98: =SUM(R90:R97) -> 0
B99: Researcher development | J99: =SUM(C99:I99) -> 0 | N99: 9th August 2018 | O99: Payday
B100: Total | C100: 2 | D100: 4 | E100: 2 | F100: 7 | G100: 4 | J100: =SUM(J89:J99) -> 29
A103: 6-12 August 2018 | B103: WS=W3 | C103: Monday | D103: Tuesday | E103: Wednesday | F103: Thursday | G103: Friday | H103: Saturday | I103: Sunday | J103: Total
B104: Anthony | D104: 4 | G104: 4 | J104: =SUM(C104:I104) -> 8 | K104: NOTE: Must have timesheet to be pay this by Monday 13th | O104: Week of 06/08/2018 | P104: Start | Q104: Finish | R104: Hrs worked | S104: Total Pay | T104: Description
C105: 9am - 5pm office (3C3) | N105: 6 | O105: Monday
B106: Margarita | C106: 2 | D106: 4 | E106: RDO | F106: 7 | G106: 2 | J106: =SUM(C106:I106) -> 15 | N106: 7 | O106: Tuesday
C107: One-on-one | F107: 9am - 4.30pm (30min break) | G107: One-on-one | N107: 8 | O107: Wednesday
B108: Angelica | C108: RDO | D108: RDO | E108: RDO | F108: RDO | G108: RDO | H108: Over weekend or evenings as needed | J108: =SUM(C108:I108) -> 0 | N108: 9 | O108: Thursday
N109: 10 | O109: Friday
B110: Kyle | C110: RDO | D110: RDO | E110: RDO | F110: 2 | G110: RDO | J110: =SUM(C110:I110) -> 2 | N110: 11 | O110: Saturday
F111: Drop-in session | N111: 12 | O111: Sunday
B112: Researcher development | J112: =SUM(C112:I112) -> 0 | O112: TOTAL
B113: Total | C113: 2 | D113: 4 | E113: 2 | F113: 7 | G113: 4 | J113: =SUM(J104:J112) -> 25
A116: 13-19 August 2018 | B116: WS=W4 | C116: Monday | D116: Tuesday | E116: Wednesday | F116: Thursday | G116: Friday | H116: Saturday | I116: Sunday | J116: Total
B117: Anthony | D117: 4 | G117: 4 | J117: =SUM(C117:I117) -> 8 | K117: NOTE: Must have timesheet to be pay this by Monday 20th | O117: Week of 13/08/2018 | P117: Start | Q117: Finish | R117: Hrs worked | S117: Total Pay | T117: Description
C118: 9am - 5pm office (3C3) | N118: 13 | O118: Monday
...

Sheet Draft_timesheet
A1: Overall timesheet | H1: Stage | I1: Time | J1: Status | K1: Due date
A2: For the next set of Acidemic contracts: Stage three (July 2018 - September 2018) | H2: Stage one | I2: 1st February - 13th May | J2: DONE
H3: Stage two | I3: 14th May - 1 July | J3: DONE
H4: Stage three | I4: 2 July 2018 - 1st September 2018 | J4: CURRENT | K4: 31st July 2018
H5: Stage four | I5: 2nd September 2018 - 31st December 2018 | J5: DRAFT NEEDED | K5: 28th August 2018
A9: 23-29 July 2018 | B9: WS=W1 | C9: Monday | D9: Tuesday | E9: Wednesday | F9: Thursday | G9: Friday | H9: Saturday | I9: Sunday | J9: Total
B10: Anthony | D10: 4 | G10: 4 | J10: =SUM(C10:I10) -> 8 | K10: NOTE: Must have timesheet to be pay this by Monday 30th
C11: 9am - 5pm office (3C3)
B12: Margarita | C12: 0 | D12: 0 | E12: RDO | F12: 7 | G12: 0 | J12: =SUM(C12:I12) -> 7
C13: One-on-one | F13: 9am - 4.30pm (30min break) | G13: One-on-one
B14: Angelica | C14: RDO | D14: RDO | E14: RDO | F14: RDO | G14: RDO | H14: 5hrs over weekend or evenings with previous researchers | I14: 5 | J14: =SUM(C14:I14) -> 5
B16: Kyle | C16: RDO | D16: RDO | E16: RDO | F16: 2 | G16: RDO | J16: =SUM(C16:I16) -> 2
F17: Drop-in session
B18: Researcher development
B19: Total | C19: 2 | D19: 4 | E19: 2 | F19: 7 | G19: 4 | J19: =SUM(J10:J18) -> 22
A22: 30 July-5 August 2018 | B22: WS=W2 | C22: Monday | D22: Tuesday | E22: Wednesday | F22: Thursday | G22: Friday | H22: Saturday | I22: Sunday | J22: Total
B23: Anthony | D23: 4 | G23: 4 | J23: =SUM(C23:I23) -> 8 | K23: NOTE: Must have timesheet to be pay this by Monday 6th
C24: 9am - 5pm office (3C3)
B25: Margarita | C25: 2 | D25: 0 | E25: RDO | F25: 7 | G25: 2 | J25: =SUM(C25:I25) -> 11
C26: One-on-one | F26: 9am - 4.30pm (30min break) | G26: One-on-one
B27: Angelica | C27: RDO | D27: RDO | E27: RDO | F27: RDO | G27: RDO | H27: 2hrs over weekend or evenings with previous researchers | J27: 2
B29: New Staff 1 | F29: 2 | J29: 2
F30: Drop-in session
B31: Kyle | C31: RDO | D31: RDO | E31: RDO | F31: 2 | G31: RDO | J31: =SUM(C31:I31) -> 2
F32: Drop-in session
B33: Researcher development | J33: =SUM(C32:I32) -> 0
B34: Total | C34: 2 | D34: 4 | E34: 2 | F34: 7 | G34: 4 | J34: =SUM(J23:J33) -> 25
A37: 6-12 August 2018 | B37: WS=W3 | C37: Monday | D37: Tuesday | E37: Wednesday | F37: Thursday | G37: Friday | H37: Saturday | I37: Sunday | J37: Total
B38: Anthony | D38: 4 | G38: 4 | J38: =SUM(C38:I38) -> 8 | K38: NOTE: Must have timesheet to be pay this by Monday 13th
C39: 9am - 5pm office (3C3)
B40: Margarita | C40: 2 | D40: 4 | E40: RDO | F40: 7 | G40: 2 | J40: =SUM(C40:I40) -> 15
C41: One-on-one | F41: 9am - 4.30pm (30min break) | G41: One-on-one
B42: New Staff 1 | C42: RDO | D42: RDO | E42: RDO | F42: 2 | G42: RDO | H42: Over weekend or evenings as needed | J42: =SUM(C42:I42) -> 2
F43: Drop-in session
B44: Kyle | C44: RDO | D44: RDO | E44: RDO | F44: 2 | G44: RDO | J44: =SUM(C44:I44) -> 2
F45: Drop-in session
B46: Researcher development | J46: =SUM(C45:I45) -> 0
B47: Total | C47: 2 | D47: 4 | E47: 2 | F47: 7 | G47: 4 | J47: =SUM(J38:J46) -> 27
A50: 13-19 August 2018 | B50: WS=W4 | C50: Monday | D50: Tuesday | E50: Wednesday | F50: Thursday | G50: Friday | H50: Saturday | I50: Sunday | J50: Total
B51: Anthony | D51: 4 | G51: 4 | J51: =SUM(C51:I51) -> 8 | K51: NOTE: Must have timesheet to be pay this by Monday 20th
C52: 9am - 5pm office (3C3)
B53: Margarita | C53: 2 | D53: 4 | E53: RDO | F53: 7 | G53: 2 | J53: =SUM(C53:I53) -> 15
C54: One-on-one | F54: 9am - 4.30pm (30min break) | G54: One-on-one
B55: New Staff 1 | C55: RDO | D55: RDO | E55: RDO | F55: 2 | G55: RDO | H55: Over weekend or evenings as needed | J55: =SUM(C55:I55) -> 2
F56: Drop-in session
B57: Kyle | C57: RDO | D57: RDO | E57: RDO | F57: 2 | G57: RDO | J57: =SUM(C57:I57) -> 2
F58: Drop-in session
B59: ` | C59: Use hours still owing to the statistics network for the rest of the month
B61: Researcher development | J61: =SUM(C58:I58) -> 0
B62: Total | C62: 2 | D62: 4 | E62: 2 | F62: 7 | G62: 4 | J62: =SUM(J51:J61) -> 27
A65: 20-26 August 2018 | B65: WS=W4 | C65: Monday | D65: Tuesday | E65: Wednesday | F65: Thursday | G65: Friday | H65: Saturday | I65: Sunday | J65: Total
B66: Anthony | D66: 4 | J66: =SUM(C66:I66) -> 4 | K66: NOTE: Must have timesheet to be pay this by Monday 27th
C67: 9am - 5pm office (3C3)
B68: Margarita | C68: 2 | D68: 4 | E68: RDO | F68: 7 | G68: 2 | J68: =SUM(C68:I68) -> 15
C69: One-on-one | F69: 9am - 4.30pm (30min break) | G69: One-on-one
B70: New Staff 1 | C70: RDO | D70: RDO | E70: RDO | F70: 2 | G70: RDO | H70: Over weekend or evenings as needed | J70: =SUM(C70:I70) -> 2
F71: Drop-in session
B72: Kyle | C72: RDO | D72: RDO | E72: RDO | F72: 2 | G72: RDO | J72: =SUM(C72:I72) -> 2
F73: Drop-in session (1:00 - 3:00)
B74: Researcher development | J74: =SUM(C73:I73) -> 0
B75: Total | C75: 2 | D75: 4 | E75: 2 | F75: 7 | G75: 4 | J75: =SUM(J66:J74) -> 23
A78: 27 August - 2 September 2018 | B78: WS=W4 | C78: Monday | D78: Tuesday | E78: Wednesday | F78: Thursday | G78: Friday | H78: Saturday | I78: Sunday | J78: Total
B79: Anthony | D79: 2 | J79: =SUM(C79:I79) -> 2 | K79: NOTE: Must have timesheet to be pay this by Monday 3rd
C80: 9am - 5pm office (3C3)
B81: Margarita | C81: 2 | D81: 4 | E81: RDO | F81: 7 | G81: 2 | J81: =SUM(C81:I81) -> 15
C82: One-on-one | F82: 9am - 4.30pm (30min break) | G82: One-on-one
B83: New Staff 1 | C83: RDO | D83: RDO | E83: 3 | F83: 2 | G83: 3 | H83: 2 | J83: =SUM(C83:H83) -> 10
E84: One-on-one | F84: Drop-in session | G84: One-on-one | H84: Over weekend or evenings as needed
B85: Kyle | C85: RDO | D85: RDO | E85: RDO | F85: 2 | G85: RDO | J85: =SUM(C85:I85) -> 2
F86: Drop-in session (1:00 - 3:00)
B87: Researcher development | J87: =SUM(C87:I87) -> 0
B88: Total | C88: =SUM(F84,C85,C83,C81) -> 2 | D88: =SUM(G84,D85,D83,D81) -> 4 | E88: =SUM(H84,E85,E83,E81) -> 3 | F88: =SUM(I84,F85,F83,F81) -> 11 | G88: =SUM(J84,G85,G83,G81) -> 5 | H88: =SUM(K84,H85,H83,H81) -> 2 | I88: =SUM(#REF!,I85,I83,I81) -> #REF! | J88: =SUM(J79:J87) -> 29
A93: NEW CONTRACT (2nd September - 31st December 2018)
A94: END CONTRACT START A NEW ONE | B94: First week of september | C94: Start | D94: Finish | E94: Hrs worked | F94: Total Pay | G94: Description

Sheet Dates

Sheet 2 CostByEmployee_Data
B2: Report by Cost Centre - All Employees including Casuals/ Sessionals
C4: Includes Earning, Oncosts and Super ('Subsidies'). Excludes Deductions
C6: Period End Date | D6: School | E6: Cost Centre Code | F6: Project Code | G6: Emp. No. | H6: Surname | I6: Preferred Name | J6: Highest Classification | K6: Job Number | L6: Position Title | M6: GL Record Type Description | N6: Account Number Prefix | O6: Paycode | P6: Salary Hours | Q6: Amt$
C7: 43124 | D7: Graduate Research | E7: 6283 | G7: 435389 | H7: DAVIDSON | I7: Anthony | K7: 02 | M7: Earnings | N7: 50007 | O7: Salary Casual | P7: 12.5 | Q7: 716.91
C8: 43124 | D8: Graduate Research | E8: 6283 | G8: 435389 | H8: DAVIDSON | I8: Anthony | K8: 02 | M8: Oncosts | N8: 50031 | O8: Oncosts | Q8: 49.11
C9: 43124 | D9: Graduate Research | E9: 6283 | G9: 435389 | H9: DAVIDSON | I9: Anthony | K9: 02 | M9: Oncosts | N9: 50032 | O9: Oncosts | Q9: 4.67
C10: 43124 | D10: Graduate Research | E10: 6283 | G10: 435389 | H10: DAVIDSON | I10: Anthony | K10: 02 | M10: Oncosts | N10: 50033 | O10: Oncosts | Q10: 8.95
C11: 43124 | D11: Graduate Research | E11: 6283 | G11: 435389 | H11: DAVIDSON | I11: Anthony | K11: 02 | M11: Subsidies | N11: 50027 | O11: Super | Q11: 68.11
C12: 43124 | D12: Graduate Research | E12: 6283 | G12: 436862 | H12: HEMMING | I12: Kyle | K12: 02 | M12: Earnings | N12: 50007 | O12: Salary Casual | P12: 6.5 | Q12: 376.58
C13: 43124 | D13: Graduate Research | E13: 6283 | G13: 436862 | H13: HEMMING | I13: Kyle | K13: 02 | M13: Oncosts | N13: 50031 | O13: Oncosts | Q13: 25.8
C14: 43124 | D14: Graduate Research | E14: 6283 | G14: 436862 | H14: HEMMING | I14: Kyle | K14: 02 | M14: Oncosts | N14: 50033 | O14: Oncosts | Q14: 4.71
C15: 43138 | D15: Graduate Research | E15: 6283 | G15: 435389 | H15: DAVIDSON | I15: Anthony | K15: 02 | M15: Earnings | N15: 50007 | O15: Salary Casual | P15: 73.5 | Q15: 4258.2
C16: 43138 | D16: Graduate Research | E16: 6283 | G16: 435389 | H16: DAVIDSON | I16: Anthony | K16: 02 | M16: Oncosts | N16: 50031 | O16: Oncosts | Q16: 291.7
C17: 43138 | D17: Graduate Research | E17: 6283 | G17: 435389 | H17: DAVIDSON | I17: Anthony | K17: 02 | M17: Oncosts | N17: 50032 | O17: Oncosts | Q17: 27.71
C18: 43138 | D18: Graduate Research | E18: 6283 | G18: 435389 | H18: DAVIDSON | I18: Anthony | K18: 02 | M18: Oncosts | N18: 50033 | O18: Oncosts | Q18: 53.22
C19: 43138 | D19: Graduate Research | E19: 6283 | G19: 435389 | H19: DAVIDSON | I19: Anthony | K19: 02 | M19: Subsidies | N19: 50027 | O19: Super | Q19: 404.53
C20: 43138 | D20: Graduate Research | E20: 6283 | G20: 436862 | H20: HEMMING | I20: Kyle | K20: 02 | M20: Earnings | N20: 50007 | O20: Salary Casual | P20: 21.5 | Q20: 1245.59
C21: 43138 | D21: Graduate Research | E21: 6283 | G21: 436862 | H21: HEMMING | I21: Kyle | K21: 02 | M21: Oncosts | N21: 50031 | O21: Oncosts | Q21: 85.33
C22: 43138 | D22: Graduate Research | E22: 6283 | G22: 436862 | H22: HEMMING | I22: Kyle | K22: 02 | M22: Oncosts | N22: 50032 | O22: Oncosts | Q22: 8.11
C23: 43138 | D23: Graduate Research | E23: 6283 | G23: 436862 | H23: HEMMING | I23: Kyle | K23: 02 | M23: Oncosts | N23: 50033 | O23: Oncosts | Q23: 15.57
C24: 43138 | D24: Graduate Research | E24: 6283 | G24: 436862 | H24: HEMMING | I24: Kyle | K24: 02 | M24: Subsidies | N24: 50027 | O24: Super | Q24: 118.33
C25: 43166 | D25: Graduate Research | E25: 6283 | G25: 432401 | H25: GALVIN | I25: Catherine | K25: 03 | M25: Earnings | N25: 50002 | O25: Rate B - Lecturing | P25: 6 | Q25: 1517.08
C26: 43166 | D26: Graduate Research | E26: 6283 | G26: 432401 | H26: GALVIN | I26: Catherine | K26: 03 | M26: Oncosts | N26: 50018 | O26: Oncosts | Q26: 103.92
C27: 43166 | D27: Graduate Research | E27: 6283 | G27: 432401 | H27: GALVIN | I27: Catherine | K27: 03 | M27: Oncosts | N27: 50020 | O27: Oncosts | Q27: 9.87
C28: 43166 | D28: Graduate Research | E28: 6283 | G28: 432401 | H28: GALVIN | I28: Catherine | K28: 03 | M28: Oncosts | N28: 50021 | O28: Oncosts | Q28: 18.96
C29: 43166 | D29: Graduate Research | E29: 6283 | G29: 432401 | H29: GALVIN | I29: Catherine | K29: 03 | M29: Subsidies | N29: 50016 | O29: Super | Q29: 144.12
C30: 43166 | D30: Graduate Research | E30: 6283 | G30: 435389 | H30: DAVIDSON | I30: Anthony | K30: 02 | M30: Earnings | N30: 50007 | O30: Salary Casual | P30: 6 | Q30: 347.6
C31: 43166 | D31: Graduate Research | E31: 6283 | G31: 435389 | H31: DAVIDSON | I31: Anthony | K31: 02 | M31: Oncosts | N31: 50031 | O31: Oncosts | Q31: 23.81
C32: 43166 | D32: Graduate Research | E32: 6283 | G32: 435389 | H32: DAVIDSON | I32: Anthony | K32: 02 | M32: Oncosts | N32: 50033 | O32: Oncosts | Q32: 4.35
C33: 43166 | D33: Graduate Research | E33: 6283 | G33: 436862 | H33: HEMMING | I33: Kyle | K33: 02 | M33: Earnings | N33: 50007 | O33: Salary Casual | P33: 6 | Q33: 347.61
C34: 43166 | D34: Graduate Research | E34: 6283 | G34: 436862 | H34: HEMMING | I34: Kyle | K34: 02 | M34: Oncosts | N34: 50031 | O34: Oncosts | Q34: 23.82
C35: 43166 | D35: Graduate Research | E35: 6283 | G35: 436862 | H35: HEMMING | I35: Kyle | K35: 02 | M35: Oncosts | N35: 50033 | O35: Oncosts | Q35: 4.35
C36: 43180 | D36: Graduate Research | E36: 6283 | G36: 429372 | H36: LOPEZ | I36: Angelica | K36: 04 | M36: Earnings | N36: 50002 | O36: Rate P - Other | P36: 5 | Q36: 226.4
C37: 43180 | D37: Graduate Research | E37: 6283 | G37: 429372 | H37: LOPEZ | I37: Angelica | K37: 04 | M37: Oncosts | N37: 50018 | O37: Oncosts | Q37: 15.51
C38: 43180 | D38: Graduate Research | E38: 6283 | G38: 429372 | H38: LOPEZ | I38: Angelica | K38: 04 | M38: Oncosts | N38: 50020 | O38: Oncosts | Q38: 1.47
C39: 43180 | D39: Graduate Research | E39: 6283 | G39: 429372 | H39: LOPEZ | I39: Angelica | K39: 04 | M39: Oncosts | N39: 50021 | O39: Oncosts | Q39: 2.83
C40: 43180 | D40: Graduate Research | E40: 6283 | G40: 429372 | H40: LOPEZ | I40: Angelica | K40: 04 | M40: Subsidies | N40: 50016 | O40: Super | Q40: 21.51
C41: 43180 | D41: Graduate Research | E41: 6283 | G41: 430664 | H41: MEDINA | I41: Margarita | K41: 04 | M41: Earnings | N41: 50002 | O41: Rate P - Other | P41: 5 | Q41: 226.4
C42: 43180 | D42: Graduate Research | E42: 6283 | G42: 430664 | H42: MEDINA | I42: Margarita | K42: 04 | M42: Oncosts | N42: 50018 | O42: Oncosts | Q42: 15.51
C43: 43180 | D43: Graduate Research | E43: 6283 | G43: 430664 | H43: MEDINA | I43: Margarita | K43: 04 | M43: Oncosts | N43: 50020 | O43: Oncosts | Q43: 1.47
C44: 43180 | D44: Graduate Research | E44: 6283 | G44: 430664 | H44: MEDINA | I44: Margarita | K44: 04 | M44: Oncosts | N44: 50021 | O44: Oncosts | Q44: 2.83
C45: 43180 | D45: Graduate Research | E45: 6283 | G45: 430664 | H45: MEDINA | I45: Margarita | K45: 04 | M45: Subsidies | N45: 50016 | O45: Super | Q45: 21.51
C46: 43180 | D46: Graduate Research | E46: 6283 | G46: 435389 | H46: DAVIDSON | I46: Anthony | K46: 02 | M46: Earnings | N46: 50007 | O46: Salary Casual | P46: 1 | Q46: 57.93
C47: 43180 | D47: Graduate Research | E47: 6283 | G47: 435389 | H47: DAVIDSON | I47: Anthony | K47: 02 | M47: Oncosts | N47: 50031 | O47: Oncosts | Q47: 3.97
C48: 43180 | D48: Graduate Research | E48: 6283 | G48: 435389 | H48: DAVIDSON | I48: Anthony | K48: 02 | M48: Oncosts | N48: 50033 | O48: Oncosts | Q48: 0.72
C49: 43180 | D49: Graduate Research | E49: 6283 | G49: 436862 | H49: HEMMING | I49: Kyle | K49: 02 | M49: Earnings | N49: 50007 | O49: Salary Casual | P49: 4 | Q49: 231.74
C50: 43180 | D50: Graduate Research | E50: 6283 | G50: 436862 | H50: HEMMING | I50: Kyle | K50: 02 | M50: Oncosts | N50: 50031 | O50: Oncosts | Q50: 15.88
C51: 43180 | D51: Graduate Research | E51: 6283 | G51: 436862 | H51: HEMMING | I51: Kyle | K51: 02 | M51: Oncosts | N51: 50032 | O51: Oncosts | Q51: 3.77
C52: 43180 | D52: Graduate Research | E52: 6283 | G52: 436862 | H52: HEMMING | I52: Kyle | K52: 02 | M52: Oncosts | N52: 50033 | O52: Oncosts | Q52: 2.9
C53: 43180 | D53: Graduate Research | E53: 6283 | G53: 436862 | H53: HEMMING | I53: Kyle | K53: 02 | M53: Subsidies | N53: 50027 | O53: Super | Q53: 55.04
C54: 43194 | D54: Graduate Research | E54: 6283 | G54: 429372 | H54: LOPEZ | I54: Angelica | K54: 04 | M54: Earnings | N54: 50002 | O54: Rate P - Other | P54: 5 | Q54: 226.4
C55: 43194 | D55: Graduate Research | E55: 6283 | G55: 429372 | H55: LOPEZ | I55: Angelica | K55: 04 | M55: Oncosts | N55: 50018 | O55: Oncosts | Q55: 15.51
C56: 43194 | D56: Graduate Research | E56: 6283 | G56: 429372 | H56: LOPEZ | I56: Angelica | K56: 04 | M56: Oncosts | N56: 50021 | O56: Oncosts | Q56: 2.83
C57: 43194 | D57: Graduate Research | E57: 6283 | G57: 430664 | H57: MEDINA | I57: Margarita | K57: 04 | M57: Earnings | N57: 50002 | O57: Rate P - Other | P57: 5 | Q57: 226.4
C58: 43194 | D58: Graduate Research | E58: 6283 | G58: 430664 | H58: MEDINA | I58: Margarita | K58: 04 | M58: Oncosts | N58: 50018 | O58: Oncosts | Q58: 15.51
C59: 43194 | D59: Graduate Research | E59: 6283 | G59: 430664 | H59: MEDINA | I59: Margarita | K59: 04 | M59: Oncosts | N59: 50020 | O59: Oncosts | Q59: 1.47
C60: 43194 | D60: Graduate Research | E60: 6283 | G60: 430664 | H60: MEDINA | I60: Margarita | K60: 04 | M60: Oncosts | N60: 50021 | O60: Oncosts | Q60: 2.83
C61: 43194 | D61: Graduate Research | E61: 6283 | G61: 430664 | H61: MEDINA | I61: Margarita | K61: 04 | M61: Subsidies | N61: 50016 | O61: Super | Q61: 21.51
C62: 43194 | D62: Graduate Research | E62: 6283 | G62: 436862 | H62: HEMMING | I62: Kyle | K62: 02 | M62: Earnings | N62: 50007 | O62: Salary Casual | P62: 5 | Q62: 289.67
C63: 43194 | D63: Graduate Research | E63: 6283 | G63: 436862 | H63: HEMMING | I63: Kyle | K63: 02 | M63: Oncosts | N63: 50031 | O63: Oncosts | Q63: 19.85
C64: 43194 | D64: Graduate Research | E64: 6283 | G64: 436862 | H64: HEMMING | I64: Kyle | K64: 02 | M64: Oncosts | N64: 50032 | O64: Oncosts | Q64: 0
C65: 43194 | D65: Graduate Research | E65: 6283 | G65: 436862 | H65: HEMMING | I65: Kyle | K65: 02 | M65: Oncosts | N65: 50033 | O65: Oncosts | Q65: 3.62
C66: 43194 | D66: Graduate Research | E66: 6283 | G66: 436862 | H66: HEMMING | I66: Kyle | K66: 02 | M66: Subsidies | N66: 50027 | O66: Super | Q66: 0
C67: 43208 | D67: Graduate Research | E67: 6283 | G67: 429372 | H67: LOPEZ | I67: Angelica | K67: 04 | M67: Oncosts | N67: 50020 | O67: Oncosts | Q67: 1.47
C68: 43208 | D68: Graduate Research | E68: 6283 | G68: 429372 | H68: LOPEZ | I68: Angelica | K68: 04 | M68: Subsidies | N68: 50016 | O68: Super | Q68: 21.51
C69: 43208 | D69: Graduate Research | E69: 6283 | G69: 436862 | H69: HEMMING | I69: Kyle | K69: 02 | M69: Oncosts | N69: 50032 | O69: Oncosts | Q69: 0
C70: 43208 | D70: Graduate Research | E70: 6283 | G70: 436862 | H70: HEMMING | I70: Kyle | K70: 02 | M70: Subsidies | N70: 50027 | O70: Super | Q70: 0
C71: 43222 | D71: Graduate Research | E71: 6283 | G71: 429372 | H71: LOPEZ | I71: Angelica | K71: 04 | M71: Earnings | N71: 50002 | O71: Rate P - Other | P71: 10 | Q71: 452.78
C72: 43222 | D72: Graduate Research | E72: 6283 | G72: 429372 | H72: LOPEZ | I72: Angelica | K72: 04 | M72: Oncosts | N72: 50018 | O72: Oncosts | Q72: 31.02
C73: 43222 | D73: Graduate Research | E73: 6283 | G73: 429372 | H73: LOPEZ | I73: Angelica | K73: 04 | M73: Oncosts | N73: 50020 | O73: Oncosts | Q73: 2.95
C74: 43222 | D74: Graduate Research | E74: 6283 | G74: 429372 | H74: LOPEZ | I74: Angelica | K74: 04 | M74: Oncosts | N74: 50021 | O74: Oncosts | Q74: 5.66
C75: 43222 | D75: Graduate Research | E75: 6283 | G75: 429372 | H75: LOPEZ | I75: Angelica | K75: 04 | M75: Subsidies | N75: 50016 | O75: Super | Q75: 43.01
C76: 43222 | D76: Graduate Research | E76: 6283 | G76: 430664 | H76: MEDINA | I76: Margarita | K76: 04 | M76: Earnings | N76: 50002 | O76: Rate P - Other | P76: 18 | Q76: 815.01
C77: 43222 | D77: Graduate Research | E77: 6283 | G77: 430664 | H77: MEDINA | I77: Margarita | K77: 04 | M77: Oncosts | N77: 50018 | O77: Oncosts | Q77: 55.83
C78: 43222 | D78: Graduate Research | E78: 6283 | G78: 430664 | H78: MEDINA | I78: Margarita | K78: 04 | M78: Oncosts | N78: 50020 | O78: Oncosts | Q78: 5.31
C79: 43222 | D79: Graduate Research | E79: 6283 | G79: 430664 | H79: MEDINA | I79: Margarita | K79: 04 | M79: Oncosts | N79: 50021 | O79: Oncosts | Q79: 10.19
C80: 43222 | D80: Graduate Research | E80: 6283 | G80: 430664 | H80: MEDINA | I80: Margarita | K80: 04 | M80: Subsidies | N80: 50016 | O80: Super | Q80: 77.43
C81: 43222 | D81: Graduate Research | E81: 6283 | G81: 435389 | H81: DAVIDSON | I81: Anthony | K81: 04 | M81: Earnings | N81: 50002 | O81: Rate P - Other | P81: 40.75 | Q81: 1845.12
C82: 43222 | D82: Graduate Research | E82: 6283 | G82: 435389 | H82: DAVIDSON | I82: Anthony | K82: 04 | M82: Oncosts | N82: 50018 | O82: Oncosts | Q82: 126.39
C83: 43222 | D83: Graduate Research | E83: 6283 | G83: 435389 | H83: DAVIDSON | I83: Anthony | K83: 04 | M83: Oncosts | N83: 50020 | O83: Oncosts | Q83: 12.01
C84: 43222 | D84: Graduate Research | E84: 6283 | G84: 435389 | H84: DAVIDSON | I84: Anthony | K84: 04 | M84: Oncosts | N84: 50021 | O84: Oncosts | Q84: 23.06
C85: 43222 | D85: Graduate Research | E85: 6283 | G85: 435389 | H85: DAVIDSON | I85: Anthony | K85: 04 | M85: Subsidies | N85: 50016 | O85: Super | Q85: 175.29
C86: 43222 | D86: Graduate Research | E86: 6283 | G86: 436862 | H86: HEMMING | I86: Kyle | K86: 02 | M86: Oncosts | N86: 50032 | O86: Oncosts | Q86: 0
C87: 43222 | D87: Graduate Research | E87: 6283 | G87: 436862 | H87: HEMMING | I87: Kyle | K87: 02 | M87: Subsidies | N87: 50027 | O87: Super | Q87: 0
C88: 43222 | D88: Graduate Research | E88: 6283 | G88: 436862 | H88: HEMMING | I88: Kyle | K88: 03 | M88: Earnings | N88: 50002 | O88: Rate P - Other | P88: 40 | Q88: 1811.16
C89: 43222 | D89: Graduate Research | E89: 6283 | G89: 436862 | H89: HEMMING | I89: Kyle | K89: 03 | M89: Oncosts | N89: 50018 | O89: Oncosts | Q89: 124.05
C90: 43222 | D90: Graduate Research | E90: 6283 | G90: 436862 | H90: HEMMING | I90: Kyle | K90: 03 | M90: Oncosts | N90: 50020 | O90: Oncosts | Q90: 11.79
C91: 43222 | D91: Graduate Research | E91: 6283 | G91: 436862 | H91: HEMMING | I91: Kyle | K91: 03 | M91: Oncosts | N91: 50021 | O91: Oncosts | Q91: 22.64
C92: 43222 | D92: Graduate Research | E92: 6283 | G92: 436862 | H92: HEMMING | I92: Kyle | K92: 03 | M92: Subsidies | N92: 50016 | O92: Super | Q92: 172.06
C93: 43236 | D93: Graduate Research | E93: 6283 | G93: 429372 | H93: LOPEZ | I93: Angelica | K93: 04 | M93: Earnings | N93: 50002 | O93: Rate O - Marking | P93: 22.5 | Q93: 1215.87
C94: 43236 | D94: Graduate Research | E94: 6283 | G94: 429372 | H94: LOPEZ | I94: Angelica | K94: 04 | M94: Oncosts | N94: 50018 | O94: Oncosts | Q94: 83.29
C95: 43236 | D95: Graduate Research | E95: 6283 | G95: 429372 | H95: LOPEZ | I95: Angelica | K95: 04 | M95: Oncosts | N95: 50020 | O95: Oncosts | Q95: 7.91
C96: 43236 | D96: Graduate Research | E96: 6283 | G96: 429372 | H96: LOPEZ | I96: Angelica | K96: 04 | M96: Oncosts | N96: 50021 | O96: Oncosts | Q96: 15.19
C97: 43236 | D97: Graduate Research | E97: 6283 | G97: 429372 | H97: LOPEZ | I97: Angelica | K97: 04 | M97: Subsidies | N97: 50016 | O97: Super | Q97: 115.51
C98: 43236 | D98: Graduate Research | E98: 6283 | G98: 430664 | H98: MEDINA | I98: Margarita | K98: 04 | M98: Earnings | N98: 50002 | O98: Rate P - Other | P98: 10 | Q98: 452.79
C99: 43236 | D99: Graduate Research | E99: 6283 | G99: 430664 | H99: MEDINA | I99: Margarita | K99: 04 | M99: Oncosts | N99: 50018 | O99: Oncosts | Q99: 31.02
C100: 43236 | D100: Graduate Research | E100: 6283 | G100: 430664 | H100: MEDINA | I100: Margarita | K100: 04 | M100: Oncosts | N100: 50020 | O100: Oncosts | Q100: 2.95
C101: 43236 | D101: Graduate Research | E101: 6283 | G101: 430664 | H101: MEDINA | I101: Margarita | K101: 04 | M101: Oncosts | N101: 50021 | O101: Oncosts | Q101: 5.66
C102: 43236 | D102: Graduate Research | E102: 6283 | G102: 430664 | H102: MEDINA | I102: Margarita | K102: 04 | M102: Subsidies | N102: 50016 | O102: Super | Q102: 43.02
C103: 43236 | D103: Graduate Research | E103: 6283 | G103: 435389 | H103: DAVIDSON | I103: Anthony | K103: 04 | M103: Earnings | N103: 50002 | O103: Rate P - Other | P103: 10 | Q103: 452.79
...

Sheet Extra_earnings
A1: 43166 | B1: Graduate Research | C1: 6283 | E1: 432401 | F1: GALVIN | G1: Catherine | I1: 03 | K1: Earnings | L1: 50002 | M1: Rate B - Lecturing | N1: 6 | O1: 1517.08
A2: 43166 | B2: Graduate Research | C2: 6283 | E2: 432401 | F2: GALVIN | G2: Catherine | I2: 03 | K2: Oncosts | L2: 50018 | M2: Oncosts | O2: 103.92
A3: 43166 | B3: Graduate Research | C3: 6283 | E3: 432401 | F3: GALVIN | G3: Catherine | I3: 03 | K3: Oncosts | L3: 50020 | M3: Oncosts | O3: 9.87
A4: 43166 | B4: Graduate Research | C4: 6283 | E4: 432401 | F4: GALVIN | G4: Catherine | I4: 03 | K4: Oncosts | L4: 50021 | M4: Oncosts | O4: 18.96
A5: 43166 | B5: Graduate Research | C5: 6283 | E5: 432401 | F5: GALVIN | G5: Catherine | I5: 03 | K5: Subsidies | L5: 50016 | M5: Super | O5: 144.12
A6: 43250 | B6: Graduate Research | C6: 6283 | E6: 432401 | F6: GALVIN | G6: Catherine | I6: 03 | K6: Oncosts | L6: 50020 | M6: Oncosts | O6: 0
A7: 43250 | B7: Graduate Research | C7: 6283 | E7: 432401 | F7: GALVIN | G7: Catherine | I7: 03 | K7: Subsidies | L7: 50016 | M7: Super | O7: 0

Sheet Removed_extra
A1: Period End Date | B1: Emp. No. | C1: Surname | D1: Preferred Name | E1: Job Number | F1: GL Record Type Description | G1: Account Number Prefix | H1: Paycode | I1: Salary Hours | J1: Amt$
A2: 43124 | B2: 435389 | C2: DAVIDSON | D2: Anthony | E2: 02 | F2: Earnings | G2: 50007 | H2: Salary Casual | I2: 12.5 | J2: 716.91
A3: 43124 | B3: 435389 | C3: DAVIDSON | D3: Anthony | E3: 02 | F3: Oncosts | G3: 50031 | H3: Oncosts | J3: 49.11
A4: 43124 | B4: 435389 | C4: DAVIDSON | D4: Anthony | E4: 02 | F4: Oncosts | G4: 50032 | H4: Oncosts | J4: 4.67
A5: 43124 | B5: 435389 | C5: DAVIDSON | D5: Anthony | E5: 02 | F5: Oncosts | G5: 50033 | H5: Oncosts | J5: 8.95
A6: 43124 | B6: 435389 | C6: DAVIDSON | D6: Anthony | E6: 02 | F6: Subsidies | G6: 50027 | H6: Super | J6: 68.11
A7: 43124 | B7: 436862 | C7: HEMMING | D7: Kyle | E7: 02 | F7: Earnings | G7: 50007 | H7: Salary Casual | I7: 6.5 | J7: 376.58
A8: 43124 | B8: 436862 | C8: HEMMING | D8: Kyle | E8: 02 | F8: Oncosts | G8: 50031 | H8: Oncosts | J8: 25.8
A9: 43124 | B9: 436862 | C9: HEMMING | D9: Kyle | E9: 02 | F9: Oncosts | G9: 50033 | H9: Oncosts | J9: 4.71
A10: 43138 | B10: 435389 | C10: DAVIDSON | D10: Anthony | E10: 02 | F10: Earnings | G10: 50007 | H10: Salary Casual | I10: 73.5 | J10: 4258.2
A11: 43138 | B11: 435389 | C11: DAVIDSON | D11: Anthony | E11: 02 | F11: Oncosts | G11: 50031 | H11: Oncosts | J11: 291.7
A12: 43138 | B12: 435389 | C12: DAVIDSON | D12: Anthony | E12: 02 | F12: Oncosts | G12: 50032 | H12: Oncosts | J12: 27.71
A13: 43138 | B13: 435389 | C13: DAVIDSON | D13: Anthony | E13: 02 | F13: Oncosts | G13: 50033 | H13: Oncosts | J13: 53.22
A14: 43138 | B14: 435389 | C14: DAVIDSON | D14: Anthony | E14: 02 | F14: Subsidies | G14: 50027 | H14: Super | J14: 404.53
A15: 43138 | B15: 436862 | C15: HEMMING | D15: Kyle | E15: 02 | F15: Earnings | G15: 50007 | H15: Salary Casual | I15: 21.5 | J15: 1245.59
A16: 43138 | B16: 436862 | C16: HEMMING | D16: Kyle | E16: 02 | F16: Oncosts | G16: 50031 | H16: Oncosts | J16: 85.33
A17: 43138 | B17: 436862 | C17: HEMMING | D17: Kyle | E17: 02 | F17: Oncosts | G17: 50032 | H17: Oncosts | J17: 8.11
A18: 43138 | B18: 436862 | C18: HEMMING | D18: Kyle | E18: 02 | F18: Oncosts | G18: 50033 | H18: Oncosts | J18: 15.57
A19: 43138 | B19: 436862 | C19: HEMMING | D19: Kyle | E19: 02 | F19: Subsidies | G19: 50027 | H19: Super | J19: 118.33
A20: 43166 | B20: 435389 | C20: DAVIDSON | D20: Anthony | E20: 02 | F20: Earnings | G20: 50007 | H20: Salary Casual | I20: 6 | J20: 347.6
A21: 43166 | B21: 435389 | C21: DAVIDSON | D21: Anthony | E21: 02 | F21: Oncosts | G21: 50031 | H21: Oncosts | J21: 23.81
A22: 43166 | B22: 435389 | C22: DAVIDSON | D22: Anthony | E22: 02 | F22: Oncosts | G22: 50033 | H22: Oncosts | J22: 4.35
A23: 43166 | B23: 436862 | C23: HEMMING | D23: Kyle | E23: 02 | F23: Earnings | G23: 50007 | H23: Salary Casual | I23: 6 | J23: 347.61
A24: 43166 | B24: 436862 | C24: HEMMING | D24: Kyle | E24: 02 | F24: Oncosts | G24: 50031 | H24: Oncosts | J24: 23.82
A25: 43166 | B25: 436862 | C25: HEMMING | D25: Kyle | E25: 02 | F25: Oncosts | G25: 50033 | H25: Oncosts | J25: 4.35
A26: 43180 | B26: 429372 | C26: LOPEZ | D26: Angelica | E26: 04 | F26: Earnings | G26: 50002 | H26: Rate P - Other | I26: 5 | J26: 226.4
A27: 43180 | B27: 429372 | C27: LOPEZ | D27: Angelica | E27: 04 | F27: Oncosts | G27: 50018 | H27: Oncosts | J27: 15.51
A28: 43180 | B28: 429372 | C28: LOPEZ | D28: Angelica | E28: 04 | F28: Oncosts | G28: 50020 | H28: Oncosts | J28: 1.47
A29: 43180 | B29: 429372 | C29: LOPEZ | D29: Angelica | E29: 04 | F29: Oncosts | G29: 50021 | H29: Oncosts | J29: 2.83
A30: 43180 | B30: 429372 | C30: LOPEZ | D30: Angelica | E30: 04 | F30: Subsidies | G30: 50016 | H30: Super | J30: 21.51
A31: 43180 | B31: 435389 | C31: DAVIDSON | D31: Anthony | E31: 02 | F31: Earnings | G31: 50007 | H31: Salary Casual | I31: 1 | J31: 57.93
A32: 43180 | B32: 435389 | C32: DAVIDSON | D32: Anthony | E32: 02 | F32: Oncosts | G32: 50031 | H32: Oncosts | J32: 3.97
A33: 43180 | B33: 435389 | C33: DAVIDSON | D33: Anthony | E33: 02 | F33: Oncosts | G33: 50033 | H33: Oncosts | J33: 0.72
A34: 43180 | B34: 436862 | C34: HEMMING | D34: Kyle | E34: 02 | F34: Earnings | G34: 50007 | H34: Salary Casual | I34: 4 | J34: 231.74
A35: 43180 | B35: 436862 | C35: HEMMING | D35: Kyle | E35: 02 | F35: Oncosts | G35: 50031 | H35: Oncosts | J35: 15.88
A36: 43180 | B36: 436862 | C36: HEMMING | D36: Kyle | E36: 02 | F36: Oncosts | G36: 50032 | H36: Oncosts | J36: 3.77
A37: 43180 | B37: 436862 | C37: HEMMING | D37: Kyle | E37: 02 | F37: Oncosts | G37: 50033 | H37: Oncosts | J37: 2.9
A38: 43180 | B38: 436862 | C38: HEMMING | D38: Kyle | E38: 02 | F38: Subsidies | G38: 50027 | H38: Super | J38: 55.04
A39: 43180 | B39: 430664 | C39: MEDINA | D39: Margarita | E39: 04 | F39: Earnings | G39: 50002 | H39: Rate P - Other | I39: 5 | J39: 226.4
A40: 43180 | B40: 430664 | C40: MEDINA | D40: Margarita | E40: 04 | F40: Oncosts | G40: 50018 | H40: Oncosts | J40: 15.51
A41: 43180 | B41: 430664 | C41: MEDINA | D41: Margarita | E41: 04 | F41: Oncosts | G41: 50020 | H41: Oncosts | J41: 1.47
A42: 43180 | B42: 430664 | C42: MEDINA | D42: Margarita | E42: 04 | F42: Oncosts | G42: 50021 | H42: Oncosts | J42: 2.83
A43: 43180 | B43: 430664 | C43: MEDINA | D43: Margarita | E43: 04 | F43: Subsidies | G43: 50016 | H43: Super | J43: 21.51
A44: 43194 | B44: 429372 | C44: LOPEZ | D44: Angelica | E44: 04 | F44: Earnings | G44: 50002 | H44: Rate P - Other | I44: 5 | J44: 226.4
A45: 43194 | B45: 429372 | C45: LOPEZ | D45: Angelica | E45: 04 | F45: Oncosts | G45: 50018 | H45: Oncosts | J45: 15.51
A46: 43194 | B46: 429372 | C46: LOPEZ | D46: Angelica | E46: 04 | F46: Oncosts | G46: 50021 | H46: Oncosts | J46: 2.83
A47: 43194 | B47: 436862 | C47: HEMMING | D47: Kyle | E47: 02 | F47: Earnings | G47: 50007 | H47: Salary Casual | I47: 5 | J47: 289.67
A48: 43194 | B48: 436862 | C48: HEMMING | D48: Kyle | E48: 02 | F48: Oncosts | G48: 50031 | H48: Oncosts | J48: 19.85
A49: 43194 | B49: 436862 | C49: HEMMING | D49: Kyle | E49: 02 | F49: Oncosts | G49: 50032 | H49: Oncosts | J49: 0
A50: 43194 | B50: 436862 | C50: HEMMING | D50: Kyle | E50: 02 | F50: Oncosts | G50: 50033 | H50: Oncosts | J50: 3.62
A51: 43194 | B51: 436862 | C51: HEMMING | D51: Kyle | E51: 02 | F51: Subsidies | G51: 50027 | H51: Super | J51: 0
A52: 43194 | B52: 430664 | C52: MEDINA | D52: Margarita | E52: 04 | F52: Earnings | G52: 50002 | H52: Rate P - Other | I52: 5 | J52: 226.4
A53: 43194 | B53: 430664 | C53: MEDINA | D53: Margarita | E53: 04 | F53: Oncosts | G53: 50018 | H53: Oncosts | J53: 15.51
A54: 43194 | B54: 430664 | C54: MEDINA | D54: Margarita | E54: 04 | F54: Oncosts | G54: 50020 | H54: Oncosts | J54: 1.47
A55: 43194 | B55: 430664 | C55: MEDINA | D55: Margarita | E55: 04 | F55: Oncosts | G55: 50021 | H55: Oncosts | J55: 2.83
A56: 43194 | B56: 430664 | C56: MEDINA | D56: Margarita | E56: 04 | F56: Subsidies | G56: 50016 | H56: Super | J56: 21.51
A57: 43208 | B57: 429372 | C57: LOPEZ | D57: Angelica | E57: 04 | F57: Oncosts | G57: 50020 | H57: Oncosts | J57: 1.47
A58: 43208 | B58: 429372 | C58: LOPEZ | D58: Angelica | E58: 04 | F58: Subsidies | G58: 50016 | H58: Super | J58: 21.51
A59: 43208 | B59: 436862 | C59: HEMMING | D59: Kyle | E59: 02 | F59: Oncosts | G59: 50032 | H59: Oncosts | J59: 0
A60: 43208 | B60: 436862 | C60: HEMMING | D60: Kyle | E60: 02 | F60: Subsidies | G60: 50027 | H60: Super | J60: 0
A61: 43222 | B61: 429372 | C61: LOPEZ | D61: Angelica | E61: 04 | F61: Earnings | G61: 50002 | H61: Rate P - Other | I61: 10 | J61: 452.78
A62: 43222 | B62: 429372 | C62: LOPEZ | D62: Angelica | E62: 04 | F62: Oncosts | G62: 50018 | H62: Oncosts | J62: 31.02
A63: 43222 | B63: 429372 | C63: LOPEZ | D63: Angelica | E63: 04 | F63: Oncosts | G63: 50020 | H63: Oncosts | J63: 2.95
A64: 43222 | B64: 429372 | C64: LOPEZ | D64: Angelica | E64: 04 | F64: Oncosts | G64: 50021 | H64: Oncosts | J64: 5.66
A65: 43222 | B65: 429372 | C65: LOPEZ | D65: Angelica | E65: 04 | F65: Subsidies | G65: 50016 | H65: Super | J65: 43.01
A66: 43222 | B66: 435389 | C66: DAVIDSON | D66: Anthony | E66: 04 | F66: Earnings | G66: 50002 | H66: Rate P - Other | I66: 40.75 | J66: 1845.12
A67: 43222 | B67: 435389 | C67: DAVIDSON | D67: Anthony | E67: 04 | F67: Oncosts | G67: 50018 | H67: Oncosts | J67: 126.39
A68: 43222 | B68: 435389 | C68: DAVIDSON | D68: Anthony | E68: 04 | F68: Oncosts | G68: 50020 | H68: Oncosts | J68: 12.01
A69: 43222 | B69: 435389 | C69: DAVIDSON | D69: Anthony | E69: 04 | F69: Oncosts | G69: 50021 | H69: Oncosts | J69: 23.06
A70: 43222 | B70: 435389 | C70: DAVIDSON | D70: Anthony | E70: 04 | F70: Subsidies | G70: 50016 | H70: Super | J70: 175.29
A71: 43222 | B71: 436862 | C71: HEMMING | D71: Kyle | E71: 02 | F71: Oncosts | G71: 50032 | H71: Oncosts | J71: 0
A72: 43222 | B72: 436862 | C72: HEMMING | D72: Kyle | E72: 02 | F72: Subsidies | G72: 50027 | H72: Super | J72: 0
A73: 43222 | B73: 436862 | C73: HEMMING | D73: Kyle | E73: 03 | F73: Earnings | G73: 50002 | H73: Rate P - Other | I73: 40 | J73: 1811.16
A74: 43222 | B74: 436862 | C74: HEMMING | D74: Kyle | E74: 03 | F74: Oncosts | G74: 50018 | H74: Oncosts | J74: 124.05
A75: 43222 | B75: 436862 | C75: HEMMING | D75: Kyle | E75: 03 | F75: Oncosts | G75: 50020 | H75: Oncosts | J75: 11.79
A76: 43222 | B76: 436862 | C76: HEMMING | D76: Kyle | E76: 03 | F76: Oncosts | G76: 50021 | H76: Oncosts | J76: 22.64
A77: 43222 | B77: 436862 | C77: HEMMING | D77: Kyle | E77: 03 | F77: Subsidies | G77: 50016 | H77: Super | J77: 172.06
A78: 43222 | B78: 430664 | C78: MEDINA | D78: Margarita | E78: 04 | F78: Earnings | G78: 50002 | H78: Rate P - Other | I78: 18 | J78: 815.01
A79: 43222 | B79: 430664 | C79: MEDINA | D79: Margarita | E79: 04 | F79: Oncosts | G79: 50018 | H79: Oncosts | J79: 55.83
A80: 43222 | B80: 430664 | C80: MEDINA | D80: Margarita | E80: 04 | F80: Oncosts | G80: 50020 | H80: Oncosts | J80: 5.31
A81: 43222 | B81: 430664 | C81: MEDINA | D81: Margarita | E81: 04 | F81: Oncosts | G81: 50021 | H81: Oncosts | J81: 10.19
A82: 43222 | B82: 430664 | C82: MEDINA | D82: Margarita | E82: 04 | F82: Subsidies | G82: 50016 | H82: Super | J82: 77.43
A83: 43236 | B83: 429372 | C83: LOPEZ | D83: Angelica | E83: 04 | F83: Earnings | G83: 50002 | H83: Rate O - Marking | I83: 22.5 | J83: 1215.87
A84: 43236 | B84: 429372 | C84: LOPEZ | D84: Angelica | E84: 04 | F84: Oncosts | G84: 50018 | H84: Oncosts | J84: 83.29
A85: 43236 | B85: 429372 | C85: LOPEZ | D85: Angelica | E85: 04 | F85: Oncosts | G85: 50020 | H85: Oncosts | J85: 7.91
A86: 43236 | B86: 429372 | C86: LOPEZ | D86: Angelica | E86: 04 | F86: Oncosts | G86: 50021 | H86: Oncosts | J86: 15.19
A87: 43236 | B87: 429372 | C87: LOPEZ | D87: Angelica | E87: 04 | F87: Subsidies | G87: 50016 | H87: Super | J87: 115.51
A88: 43236 | B88: 435389 | C88: DAVIDSON | D88: Anthony | E88: 04 | F88: Earnings | G88: 50002 | H88: Rate P - Other | I88: 10 | J88: 452.79
A89: 43236 | B89: 435389 | C89: DAVIDSON | D89: Anthony | E89: 04 | F89: Oncosts | G89: 50018 | H89: Oncosts | J89: 31.02
A90: 43236 | B90: 435389 | C90: DAVIDSON | D90: Anthony | E90: 04 | F90: Oncosts | G90: 50020 | H90: Oncosts | J90: 2.95
A91: 43236 | B91: 435389 | C91: DAVIDSON | D91: Anthony | E91: 04 | F91: Oncosts | G91: 50021 | H91: Oncosts | J91: 5.66
A92: 43236 | B92: 435389 | C92: DAVIDSON | D92: Anthony | E92: 04 | F92: Subsidies | G92: 50016 | H92: Super | J92: 43.02
A93: 43236 | B93: 436862 | C93: HEMMING | D93: Kyle | E93: 02 | F93: Oncosts | G93: 50032 | H93: Oncosts | J93: 0
A94: 43236 | B94: 436862 | C94: HEMMING | D94: Kyle | E94: 02 | F94: Subsidies | G94: 50027 | H94: Super | J94: 0
A95: 43236 | B95: 436862 | C95: HEMMING | D95: Kyle | E95: 03 | F95: Earnings | G95: 50002 | H95: Rate P - Other | I95: -19 | J95: -860.3
A96: 43236 | B96: 436862 | C96: HEMMING | D96: Kyle | E96: 03 | F96: Oncosts | G96: 50018 | H96: Oncosts | J96: -58.94
A97: 43236 | B97: 436862 | C97: HEMMING | D97: Kyle | E97: 03 | F97: Oncosts | G97: 50020 | H97: Oncosts | J97: -5.6
A98: 43236 | B98: 436862 | C98: HEMMING | D98: Kyle | E98: 03 | F98: Oncosts | G98: 50021 | H98: Oncosts | J98: -10.76
A99: 43236 | B99: 436862 | C99: HEMMING | D99: Kyle | E99: 03 | F99: Subsidies | G99: 50016 | H99: Super | J99: -81.73
A100: 43236 | B100: 430664 | C100: MEDINA | D100: Margarita | E100: 04 | F100: Earnings | G100: 50002 | H100: Rate P - Other | I100: 10 | J100: 452.79
...

Sheet Split_by_advisor
A1: Period End Date | B1: Emp. No. | C1: Surname | D1: Preferred Name | E1: Job Number | F1: GL Record Type Description | G1: Account Number Prefix | H1: Paycode | I1: Salary Hours | J1: Amt$
A2: 43180 | B2: 429372 | C2: LOPEZ | D2: Angelica | E2: 04 | F2: Earnings | G2: 50002 | H2: Rate P - Other | I2: 5 | J2: 226.4
A3: 43180 | B3: 429372 | C3: LOPEZ | D3: Angelica | E3: 04 | F3: Oncosts | G3: 50018 | H3: Oncosts | J3: 15.51
A4: 43180 | B4: 429372 | C4: LOPEZ | D4: Angelica | E4: 04 | F4: Oncosts | G4: 50020 | H4: Oncosts | J4: 1.47
A5: 43180 | B5: 429372 | C5: LOPEZ | D5: Angelica | E5: 04 | F5: Oncosts | G5: 50021 | H5: Oncosts | J5: 2.83
A6: 43180 | B6: 429372 | C6: LOPEZ | D6: Angelica | E6: 04 | F6: Subsidies | G6: 50016 | H6: Super | J6: 21.51
A7: 43194 | B7: 429372 | C7: LOPEZ | D7: Angelica | E7: 04 | F7: Earnings | G7: 50002 | H7: Rate P - Other | I7: 5 | J7: 226.4
A8: 43194 | B8: 429372 | C8: LOPEZ | D8: Angelica | E8: 04 | F8: Oncosts | G8: 50018 | H8: Oncosts | J8: 15.51
A9: 43194 | B9: 429372 | C9: LOPEZ | D9: Angelica | E9: 04 | F9: Oncosts | G9: 50021 | H9: Oncosts | J9: 2.83
A10: 43208 | B10: 429372 | C10: LOPEZ | D10: Angelica | E10: 04 | F10: Oncosts | G10: 50020 | H10: Oncosts | J10: 1.47
A11: 43208 | B11: 429372 | C11: LOPEZ | D11: Angelica | E11: 04 | F11: Subsidies | G11: 50016 | H11: Super | J11: 21.51
A12: 43222 | B12: 429372 | C12: LOPEZ | D12: Angelica | E12: 04 | F12: Earnings | G12: 50002 | H12: Rate P - Other | I12: 10 | J12: 452.78
A13: 43222 | B13: 429372 | C13: LOPEZ | D13: Angelica | E13: 04 | F13: Oncosts | G13: 50018 | H13: Oncosts | J13: 31.02
A14: 43222 | B14: 429372 | C14: LOPEZ | D14: Angelica | E14: 04 | F14: Oncosts | G14: 50020 | H14: Oncosts | J14: 2.95
A15: 43222 | B15: 429372 | C15: LOPEZ | D15: Angelica | E15: 04 | F15: Oncosts | G15: 50021 | H15: Oncosts | J15: 5.66
A16: 43222 | B16: 429372 | C16: LOPEZ | D16: Angelica | E16: 04 | F16: Subsidies | G16: 50016 | H16: Super | J16: 43.01
A17: 43236 | B17: 429372 | C17: LOPEZ | D17: Angelica | E17: 04 | F17: Earnings | G17: 50002 | H17: Rate O - Marking | I17: 22.5 | J17: 1215.87
A18: 43236 | B18: 429372 | C18: LOPEZ | D18: Angelica | E18: 04 | F18: Oncosts | G18: 50018 | H18: Oncosts | J18: 83.29
A19: 43236 | B19: 429372 | C19: LOPEZ | D19: Angelica | E19: 04 | F19: Oncosts | G19: 50020 | H19: Oncosts | J19: 7.91
A20: 43236 | B20: 429372 | C20: LOPEZ | D20: Angelica | E20: 04 | F20: Oncosts | G20: 50021 | H20: Oncosts | J20: 15.19
A21: 43236 | B21: 429372 | C21: LOPEZ | D21: Angelica | E21: 04 | F21: Subsidies | G21: 50016 | H21: Super | J21: 115.51
A22: 43250 | B22: 429372 | C22: LOPEZ | D22: Angelica | E22: 04 | F22: Earnings | G22: 50002 | H22: Rate O - Marking | I22: -22.5 | J22: -1215.87
A23: 43250 | B23: 429372 | C23: LOPEZ | D23: Angelica | E23: 04 | F23: Earnings | G23: 50002 | H23: Rate P - Other | I23: 52.5 | J23: 2377.15
A24: 43250 | B24: 429372 | C24: LOPEZ | D24: Angelica | E24: 04 | F24: Earnings | G24: 50002 | H24: Rate Q - Other | I24: 25 | J24: 1350.96
A25: 43250 | B25: 429372 | C25: LOPEZ | D25: Angelica | E25: 04 | F25: Oncosts | G25: 50018 | H25: Oncosts | J25: 172.08
A26: 43250 | B26: 429372 | C26: LOPEZ | D26: Angelica | E26: 04 | F26: Oncosts | G26: 50020 | H26: Oncosts | J26: 17.82
A27: 43250 | B27: 429372 | C27: LOPEZ | D27: Angelica | E27: 04 | F27: Oncosts | G27: 50021 | H27: Oncosts | J27: 31.4
A28: 43250 | B28: 429372 | C28: LOPEZ | D28: Angelica | E28: 04 | F28: Subsidies | G28: 50016 | H28: Super | J28: 260.17
A29: 43264 | B29: 429372 | C29: LOPEZ | D29: Angelica | E29: 04 | F29: Earnings | G29: 50002 | H29: Rate P - Other | I29: 30 | J29: 1358.37
A30: 43264 | B30: 429372 | C30: LOPEZ | D30: Angelica | E30: 04 | F30: Oncosts | G30: 50018 | H30: Oncosts | J30: 93.04
A31: 43264 | B31: 429372 | C31: LOPEZ | D31: Angelica | E31: 04 | F31: Oncosts | G31: 50020 | H31: Oncosts | J31: 8.84
A32: 43264 | B32: 429372 | C32: LOPEZ | D32: Angelica | E32: 04 | F32: Oncosts | G32: 50021 | H32: Oncosts | J32: 16.98
A33: 43264 | B33: 429372 | C33: LOPEZ | D33: Angelica | E33: 04 | F33: Subsidies | G33: 50016 | H33: Super | J33: 129.05
A34: 43278 | B34: 429372 | C34: LOPEZ | D34: Angelica | E34: 04 | F34: Earnings | G34: 50002 | H34: Rate P - Other | I34: 30 | J34: 1358.37
A35: 43278 | B35: 429372 | C35: LOPEZ | D35: Angelica | E35: 04 | F35: Oncosts | G35: 50018 | H35: Oncosts | J35: 93.04
A36: 43278 | B36: 429372 | C36: LOPEZ | D36: Angelica | E36: 04 | F36: Oncosts | G36: 50020 | H36: Oncosts | J36: 8.84
A37: 43278 | B37: 429372 | C37: LOPEZ | D37: Angelica | E37: 04 | F37: Oncosts | G37: 50021 | H37: Oncosts | J37: 16.98
A38: 43278 | B38: 429372 | C38: LOPEZ | D38: Angelica | E38: 04 | F38: Subsidies | G38: 50016 | H38: Super | J38: 129.05
A39: 43292 | B39: 429372 | C39: LOPEZ | D39: Angelica | E39: 04 | F39: Earnings | G39: 50002 | H39: Rate P - Other | I39: 15 | J39: 679.19
A40: 43292 | B40: 429372 | C40: LOPEZ | D40: Angelica | E40: 04 | F40: Earnings | G40: 50002 | H40: Rate Q - Other | I40: 16 | J40: 864.62
A41: 43292 | B41: 429372 | C41: LOPEZ | D41: Angelica | E41: 04 | F41: Oncosts | G41: 50018 | H41: Oncosts | J41: 105.75
A42: 43292 | B42: 429372 | C42: LOPEZ | D42: Angelica | E42: 04 | F42: Oncosts | G42: 50020 | H42: Oncosts | J42: 10.05
A43: 43292 | B43: 429372 | C43: LOPEZ | D43: Angelica | E43: 04 | F43: Oncosts | G43: 50021 | H43: Oncosts | J43: 19.3
A44: 43292 | B44: 429372 | C44: LOPEZ | D44: Angelica | E44: 04 | F44: Subsidies | G44: 50016 | H44: Super | J44: 146.66
A45: Period End Date | B45: Emp. No. | C45: Surname | D45: Preferred Name | E45: Job Number | F45: GL Record Type Description | G45: Account Number Prefix | H45: Paycode | I45: Salary Hours | J45: Amt$
A46: 43124 | B46: 435389 | C46: DAVIDSON | D46: Anthony | E46: 02 | F46: Earnings | G46: 50007 | H46: Salary Casual | I46: 12.5 | J46: 716.91
A47: 43124 | B47: 435389 | C47: DAVIDSON | D47: Anthony | E47: 02 | F47: Oncosts | G47: 50031 | H47: Oncosts | J47: 49.11
A48: 43124 | B48: 435389 | C48: DAVIDSON | D48: Anthony | E48: 02 | F48: Oncosts | G48: 50032 | H48: Oncosts | J48: 4.67
A49: 43124 | B49: 435389 | C49: DAVIDSON | D49: Anthony | E49: 02 | F49: Oncosts | G49: 50033 | H49: Oncosts | J49: 8.95
A50: 43124 | B50: 435389 | C50: DAVIDSON | D50: Anthony | E50: 02 | F50: Subsidies | G50: 50027 | H50: Super | J50: 68.11
A51: 43138 | B51: 435389 | C51: DAVIDSON | D51: Anthony | E51: 02 | F51: Earnings | G51: 50007 | H51: Salary Casual | I51: 73.5 | J51: 4258.2
A52: 43138 | B52: 435389 | C52: DAVIDSON | D52: Anthony | E52: 02 | F52: Oncosts | G52: 50031 | H52: Oncosts | J52: 291.7
A53: 43138 | B53: 435389 | C53: DAVIDSON | D53: Anthony | E53: 02 | F53: Oncosts | G53: 50032 | H53: Oncosts | J53: 27.71
A54: 43138 | B54: 435389 | C54: DAVIDSON | D54: Anthony | E54: 02 | F54: Oncosts | G54: 50033 | H54: Oncosts | J54: 53.22
A55: 43138 | B55: 435389 | C55: DAVIDSON | D55: Anthony | E55: 02 | F55: Subsidies | G55: 50027 | H55: Super | J55: 404.53
A56: 43166 | B56: 435389 | C56: DAVIDSON | D56: Anthony | E56: 02 | F56: Earnings | G56: 50007 | H56: Salary Casual | I56: 6 | J56: 347.6
A57: 43166 | B57: 435389 | C57: DAVIDSON | D57: Anthony | E57: 02 | F57: Oncosts | G57: 50031 | H57: Oncosts | J57: 23.81
A58: 43166 | B58: 435389 | C58: DAVIDSON | D58: Anthony | E58: 02 | F58: Oncosts | G58: 50033 | H58: Oncosts | J58: 4.35
A59: 43180 | B59: 435389 | C59: DAVIDSON | D59: Anthony | E59: 02 | F59: Earnings | G59: 50007 | H59: Salary Casual | I59: 1 | J59: 57.93
A60: 43180 | B60: 435389 | C60: DAVIDSON | D60: Anthony | E60: 02 | F60: Oncosts | G60: 50031 | H60: Oncosts | J60: 3.97
A61: 43180 | B61: 435389 | C61: DAVIDSON | D61: Anthony | E61: 02 | F61: Oncosts | G61: 50033 | H61: Oncosts | J61: 0.72
A62: 43222 | B62: 435389 | C62: DAVIDSON | D62: Anthony | E62: 04 | F62: Earnings | G62: 50002 | H62: Rate P - Other | I62: 40.75 | J62: 1845.12
A63: 43222 | B63: 435389 | C63: DAVIDSON | D63: Anthony | E63: 04 | F63: Oncosts | G63: 50018 | H63: Oncosts | J63: 126.39
A64: 43222 | B64: 435389 | C64: DAVIDSON | D64: Anthony | E64: 04 | F64: Oncosts | G64: 50020 | H64: Oncosts | J64: 12.01
A65: 43222 | B65: 435389 | C65: DAVIDSON | D65: Anthony | E65: 04 | F65: Oncosts | G65: 50021 | H65: Oncosts | J65: 23.06
A66: 43222 | B66: 435389 | C66: DAVIDSON | D66: Anthony | E66: 04 | F66: Subsidies | G66: 50016 | H66: Super | J66: 175.29
A67: 43236 | B67: 435389 | C67: DAVIDSON | D67: Anthony | E67: 04 | F67: Earnings | G67: 50002 | H67: Rate P - Other | I67: 10 | J67: 452.79
A68: 43236 | B68: 435389 | C68: DAVIDSON | D68: Anthony | E68: 04 | F68: Oncosts | G68: 50018 | H68: Oncosts | J68: 31.02
A69: 43236 | B69: 435389 | C69: DAVIDSON | D69: Anthony | E69: 04 | F69: Oncosts | G69: 50020 | H69: Oncosts | J69: 2.95
A70: 43236 | B70: 435389 | C70: DAVIDSON | D70: Anthony | E70: 04 | F70: Oncosts | G70: 50021 | H70: Oncosts | J70: 5.66
A71: 43236 | B71: 435389 | C71: DAVIDSON | D71: Anthony | E71: 04 | F71: Subsidies | G71: 50016 | H71: Super | J71: 43.02
A72: 43250 | B72: 435389 | C72: DAVIDSON | D72: Anthony | E72: 04 | F72: Earnings | G72: 50002 | H72: Rate P - Other | I72: 65.5 | J72: 2965.78
A73: 43250 | B73: 435389 | C73: DAVIDSON | D73: Anthony | E73: 04 | F73: Oncosts | G73: 50018 | H73: Oncosts | J73: 203.15
A74: 43250 | B74: 435389 | C74: DAVIDSON | D74: Anthony | E74: 04 | F74: Oncosts | G74: 50020 | H74: Oncosts | J74: 19.3
A75: 43250 | B75: 435389 | C75: DAVIDSON | D75: Anthony | E75: 04 | F75: Oncosts | G75: 50021 | H75: Oncosts | J75: 37.07
A76: 43250 | B76: 435389 | C76: DAVIDSON | D76: Anthony | E76: 04 | F76: Subsidies | G76: 50016 | H76: Super | J76: 281.75
A77: 43264 | B77: 435389 | C77: DAVIDSON | D77: Anthony | E77: 04 | F77: Earnings | G77: 50002 | H77: Rate P - Other | I77: 4 | J77: 181.12
A78: 43264 | B78: 435389 | C78: DAVIDSON | D78: Anthony | E78: 04 | F78: Oncosts | G78: 50018 | H78: Oncosts | J78: 12.4
A79: 43264 | B79: 435389 | C79: DAVIDSON | D79: Anthony | E79: 04 | F79: Oncosts | G79: 50021 | H79: Oncosts | J79: 2.26
A80: 43278 | B80: 435389 | C80: DAVIDSON | D80: Anthony | E80: 04 | F80: Earnings | G80: 50002 | H80: Rate P - Other | I80: 4 | J80: 181.12
A81: 43278 | B81: 435389 | C81: DAVIDSON | D81: Anthony | E81: 04 | F81: Oncosts | G81: 50018 | H81: Oncosts | J81: 12.4
A82: 43278 | B82: 435389 | C82: DAVIDSON | D82: Anthony | E82: 04 | F82: Oncosts | G82: 50021 | H82: Oncosts | J82: 2.26
A83: 43292 | B83: 435389 | C83: DAVIDSON | D83: Anthony | E83: 04 | F83: Earnings | G83: 50002 | H83: Rate P - Other | I83: 2 | J83: 90.56
A84: 43292 | B84: 435389 | C84: DAVIDSON | D84: Anthony | E84: 04 | F84: Oncosts | G84: 50018 | H84: Oncosts | J84: 6.2
A85: 43292 | B85: 435389 | C85: DAVIDSON | D85: Anthony | E85: 04 | F85: Oncosts | G85: 50021 | H85: Oncosts | J85: 1.13
A86: Period End Date | B86: Emp. No. | C86: Surname | D86: Preferred Name | E86: Job Number | F86: GL Record Type Description | G86: Account Number Prefix | H86: Paycode | I86: Salary Hours | J86: Amt$
A87: 43124 | B87: 436862 | C87: HEMMING | D87: Kyle | E87: 02 | F87: Earnings | G87: 50007 | H87: Salary Casual | I87: 6.5 | J87: 376.58
A88: 43124 | B88: 436862 | C88: HEMMING | D88: Kyle | E88: 02 | F88: Oncosts | G88: 50031 | H88: Oncosts | J88: 25.8
A89: 43124 | B89: 436862 | C89: HEMMING | D89: Kyle | E89: 02 | F89: Oncosts | G89: 50033 | H89: Oncosts | J89: 4.71
A90: 43138 | B90: 436862 | C90: HEMMING | D90: Kyle | E90: 02 | F90: Earnings | G90: 50007 | H90: Salary Casual | I90: 21.5 | J90: 1245.59
A91: 43138 | B91: 436862 | C91: HEMMING | D91: Kyle | E91: 02 | F91: Oncosts | G91: 50031 | H91: Oncosts | J91: 85.33
A92: 43138 | B92: 436862 | C92: HEMMING | D92: Kyle | E92: 02 | F92: Oncosts | G92: 50032 | H92: Oncosts | J92: 8.11
A93: 43138 | B93: 436862 | C93: HEMMING | D93: Kyle | E93: 02 | F93: Oncosts | G93: 50033 | H93: Oncosts | J93: 15.57
A94: 43138 | B94: 436862 | C94: HEMMING | D94: Kyle | E94: 02 | F94: Subsidies | G94: 50027 | H94: Super | J94: 118.33
A95: 43166 | B95: 436862 | C95: HEMMING | D95: Kyle | E95: 02 | F95: Earnings | G95: 50007 | H95: Salary Casual | I95: 6 | J95: 347.61
A96: 43166 | B96: 436862 | C96: HEMMING | D96: Kyle | E96: 02 | F96: Oncosts | G96: 50031 | H96: Oncosts | J96: 23.82
A97: 43166 | B97: 436862 | C97: HEMMING | D97: Kyle | E97: 02 | F97: Oncosts | G97: 50033 | H97: Oncosts | J97: 4.35
A98: 43180 | B98: 436862 | C98: HEMMING | D98: Kyle | E98: 02 | F98: Earnings | G98: 50007 | H98: Salary Casual | I98: 4 | J98: 231.74
A99: 43180 | B99: 436862 | C99: HEMMING | D99: Kyle | E99: 02 | F99: Oncosts | G99: 50031 | H99: Oncosts | J99: 15.88
A100: 43180 | B100: 436862 | C100: HEMMING | D100: Kyle | E100: 02 | F100: Oncosts | G100: 50032 | H100: Oncosts | J100: 3.77
...

Sheet Templates
A1: TEMPLATES FOR FUTURE TIMESHEETS
A3: TIMETABLE (Future)
A6: 27 August - 2 September 2018 | B6: WS=W4 | C6: Monday | D6: Tuesday | E6: Wednesday | F6: Thursday | G6: Friday | H6: Saturday | I6: Sunday | J6: Total
B7: Anthony | D7: 2 | J7: =SUM(C7:I7) -> 2 | K7: NOTE: Must have timesheet to be pay this by Monday 3rd
C8: 9am - 5pm office (3C3)
B9: Margarita | C9: 2 | D9: 4 | E9: RDO | F9: 7 | G9: 2 | J9: =SUM(C9:I9) -> 15
C10: One-on-one | F10: 9am - 4.30pm (30min break) | G10: One-on-one
B11: Angelica | C11: RDO | D11: RDO | E11: RDO | F11: RDO | G11: RDO | H11: Over weekend or evenings as needed | J11: =SUM(C11:I11) -> 0
B13: Kyle | C13: RDO | D13: RDO | E13: RDO | F13: 2 | G13: RDO | J13: 2
F14: Drop-in session (1:00 - 3:00) | J14: 4
B15: Researcher development | J15: =SUM(C15:I15) -> 0
B16: Total | C16: 2 | D16: 4 | E16: 2 | F16: 7 | G16: 4 | J16: =SUM(J7:J15) -> 23
A20: Quick budget tempate
C23: Time period | D23: Duration | E23: Weeks | F23: Hours | G23: Hourly rate | H23: Plus_On_Costs (18.5%) | I23: Total cost
C24: Trial | D24: … | E24: … | F24: … | G24: … | H24: …
C25: Stage one | D25: 1st February - 13th May | E25: … | F25: … | G25: …
C26: Stage two | D26: 14th May - 1 July
C27: Stage three: Current | D27: 2 July 2018 - 1st September 2018 | E27: 7 | F27: =SUM(J16,J3,Margarita!M324,Margarita!M311,Margarita!M298,Margarita!M283,Margarita!M270,Margarita!M258,Margarita!M242) -> 23 | G27: =SUM(F27*C36) -> 1035 | H27: =SUM(G27*C37) +G27 -> 1226.475
C28: Stage four: Projected | D28: 2nd September - 31 December | E28: 18 | F28: =SUM(E28*22.5) -> 405 | G28: =SUM(F28*C36) -> 18225 | H28: =SUM(G28*C37) +G28 -> 21596.625
C29: Total actual state (BUDGET) | D29: Everything above | E29: =SUM(E24:E28) -> 25 | F29: =SUM(F24:F28) -> 428 | G29: =SUM(F29*C36) -> 19260 | H29: =SUM(G29*C37) +G29 -> 22823.1
D30: Reduced to budget | E30: =SUM(E26:E28) -> 25 | F30: =SUM(F26:F28) -> 428 | G30: =SUM(F30*C36) -> 19260 | H30: =SUM(G30*C37) +G30 -> 22823.1
C31: Total reduced wage (BUDGET) | D31: 1st March - 31 December | E31: 39 | F31: =SUM(22.5*E31) -> 877.5 | G31: =SUM(F31*C36) -> 39487.5 | H31: =SUM(G31*C37) + G31 -> 46792.688
C32: Total full wage (BUDGET) | D32: 1st March - 31 December | E32: 39 | F32: =SUM(22.5*E32) -> 877.5 | G32: =SUM(F32*C38) -> 58573.125 | H32: =SUM(G32*C37) + G32 -> 69409.153
B35: Parameters | E35: Outcome
B36: Hourly rate | C36: 45 | E36: With wage cut | F36: Projected
B37: On costs | C37: 0.185 | E37: =H31 -> 46792.688 | F37: =H32 -> 69409.153
B38: Orginal | C38: 66.75
A41: TIMESHEET (what you will get paid)
B44: Week of | C44: Start | D44: Finish | E44: Hrs worked | F44: Total Pay | G44: Description
A45: 1 | B45: Monday
A46: 2 | B46: Tuesday
A47: 3 | B47: Wednesday
A48: 4 | B48: Thursday
A49: 5 | B49: Friday
A50: 6 | B50: Saturday
A51: 7 | B51: Sunday
B52: TOTAL | E52: =SUM(E44:E51) -> 0 | G52: 9hrs
A53: Pay date | B53: Payday | F53: 0 hrs | G53: 9hrs | H53: 10hrs paid
B55: Week of | C55: Start | D55: Finish | E55: Hrs worked | F55: Total Pay | G55: Description
A56: 12 | B56: Monday
A57: 13 | B57: Tuesday
A58: 14 | B58: Wednesday
A59: 15 | B59: Thursday
A60: 16 | B60: Friday
A61: 17 | B61: Saturday
A62: 18 | B62: Sunday | C62: 0.41666667 | D62: 0.45833333 | E62: 2 | G62: admin/emails
B63: TOTAL | E63: =SUM(E56:E62) -> 2 | G63: 20hrs
B65: Week of | C65: Start | D65: Finish | E65: Hrs worked | F65: Total Pay | G65: Description
A66: 23 | B66: Monday | C66: 0.45833333 | D66: 0.47916667 | E66: 0.5 | G66: photos
A67: 24 | B67: Tuesday | C67: 0.45833333 | D67: 0.52083333 | E67: 1.5 | G67: admin/meeting
A68: 25 | B68: Wednesday | C68: 0.4375 | D68: 0.47916667 | E68: 1 | G68: meeting Sajida
A69: 26 | C69: 0.29166667 | D69: 0.41666667 | E69: 3 | G69: map Sajida
A70: 27 | B70: Thursday | C70: 0.41666667 | D70: 0.45833333 | E70: 1 | G70: final map Sajida
A71: 28 | B71: Friday | C71: 0.45833333 | D71: 0.5 | E71: 1 | G71: admin/mails
A72: 29 | B72: Saturday | C72: 0.41666667 | D72: 0.54166667 | E72: 3 | G72: admin/slides
A73: 30 | B73: Sunday
B74: TOTAL | E74: =SUM(E66:E73) -> 11 | G74: 9hrs
A75: Pay date | B75: Payday | F75: 0 hrs | G75: 9hrs | H75: 10hrs paid
A77: DATES
A82: 43124
A83: 43138
A84: 43166
A85: 43194
A86: 43208
A87: 43222
A88: 43236
A89: 43250
A90: 43264
A91: 43278
A92: 43292
A93: TOTAL | G93: =SUM(G82:G92) -> 0 | H93: =SUM(H82:H92) -> 0
